Workbook

Sheet Quarterly Performance
J1: Transposed List of Unique Customer Names
A2: Company | B2: Industry | C2: Revenue | D2: Profits | E2: Costs | F2: Customer Satisfaction Score(%) | G2: Market Share (%) | H2: Growth Potential (%) | I2: Stock Price ($) | J2: {=TRANSPOSE(_xlfn.UNIQUE($A3:$A1146))} -> Apex Capital Partners | K2: Ascend Capital Advisors | L2: Atlas Blockchain Services | M2: Atlas Community Bank | N2: Atlas Private Equity | O2: Atlas Risk Management | P2: BlueSky Banking Corp. | Q2: BlueSky Mobile Payments | R2: BlueSky Risk Solutions | S2: CrestPoint Blockchain Solutions | T2: CrestPoint Capital | U2: CryptoBridge Systems | V2: Evergreen Coverage Co. | W2: Evergreen Depository Services | X2: Evergreen Equity Group | Y2: Evergreen FinTech Group | Z2: Golden Gate Depository | AA2: Golden Gate Digital Finance | AB2: Golden Gate Insurance Partners | AC2: Granite State Credit Union | AD2: Guardian Life Assurance | AE2: GuardianPay Tech | AF2: GuardianPay Technologies | AG2: Harborview Savings Bank | AH2: Horizon Health & Life | AI2: Horizon National Bank | AJ2: Horizon Wealth Management | AK2: HorizonPay Tech | AL2: Ironclad Risk Solutions | AM2: Keystone Credit Union | AN2: Liberty Digital Finance | AO2: Liberty First Bank | AP2: Liberty Mutual Risk Partners | AQ2: Meridian Asset Solutions | AR2: NorthBridge Financial | AS2: NorthBridge Insurance Group | AT2: NorthStar Capital Partners | AU2: NorthStar Payment Systems | AV2: Nova Equity Management | AW2: NovaWallet Digital | AX2: Orion Investment Group | AY2: PaySphere Technologies | AZ2: Pinnacle Banking Group | BA2: Pinnacle Property & Casualty | BB2: Polaris Wealth Partners | BC2: Prairie Horizon Bank | BD2: Prairie Horizon Insurance | BE2: Riverstone Trust Co. | BF2: SafeHarbor Ins. Group | BG2: SafeHarbor Insurance Group | BH2: ShieldPoint Insurance | BI2: Silverline Asset Advisors | BJ2: Sterling Asset Management | BK2: Sterling FinTech Labs | BL2: Sterling L&H | BM2: Sterling Life & Health | BN2: Sterling Trust & Deposits | BO2: Summit Savings & Loan | BP2: SummitStone Digital Wallets | BQ2: SummitStone Investments | BR2: SummitStone Risk Advisors | BS2: SwiftPay | BT2: SwiftPay Solutions | BU2: Titan Global Investments | BV2: Titan Global Invsts. | BW2: Titan Reinsurance Corp. | BX2: TitanPay Innovations | BY2: Unity Federal Credit Union | BZ2: Vanguard Wealth Strategies
A3: Apex Capital Partners | B3: Investment & Asset Management | C3: 2.4774974e+08 | D3: 12182989 | E3: =C3-D3 -> 2.3556675e+08 | F3: 18.174109 | G3: 32.939703 | H3: 7.3444336 | I3: 19.145243 | J3: =IF($A3=J$2,1,0) -> 1 | K3: =IF($A3=K$2,1,0) -> 0 | L3: =IF($A3=L$2,1,0) -> 0 | M3: =IF($A3=M$2,1,0) -> 0 | N3: =IF($A3=N$2,1,0) -> 0 | O3: =IF($A3=O$2,1,0) -> 0 | P3: =IF($A3=P$2,1,0) -> 0 | Q3: =IF($A3=Q$2,1,0) -> 0 | ... BZ3: =IF($A3=BZ$2,1,0) -> 0
A4: Apex Capital Partners | B4: Investment & Asset Management | C4: 2.505283e+08 | D4: 12793593 | E4: =C4-D4 -> 2.3773471e+08 | F4: 60.138705 | G4: 32.453607 | H4: 5.8531139 | I4: 27.241833 | J4: =IF($A4=J$2,1,0) -> 1 | K4: =IF($A4=K$2,1,0) -> 0 | L4: =IF($A4=L$2,1,0) -> 0 | M4: =IF($A4=M$2,1,0) -> 0 | N4: =IF($A4=N$2,1,0) -> 0 | O4: =IF($A4=O$2,1,0) -> 0 | P4: =IF($A4=P$2,1,0) -> 0 | Q4: =IF($A4=Q$2,1,0) -> 0 | ... BZ4: =IF($A4=BZ$2,1,0) -> 0
A5: Apex Capital Partners | B5: Investment & Asset Management | C5: 2.4052715e+08 | D5: =C5-E5 -> 84083612 | E5: 1.5644354e+08 | F5: 19.604072 | G5: 32.781267 | H5: 5.6798574 | I5: 35.652206 | J5: =IF($A5=J$2,1,0) -> 1 | K5: =IF($A5=K$2,1,0) -> 0 | L5: =IF($A5=L$2,1,0) -> 0 | M5: =IF($A5=M$2,1,0) -> 0 | N5: =IF($A5=N$2,1,0) -> 0 | O5: =IF($A5=O$2,1,0) -> 0 | P5: =IF($A5=P$2,1,0) -> 0 | Q5: =IF($A5=Q$2,1,0) -> 0 | ... BZ5: =IF($A5=BZ$2,1,0) -> 0
A6: Apex Capital Partners | B6: Investment & Asset Management | C6: 2.6934109e+08 | D6: 12903441 | E6: =C6-D6 -> 2.5643765e+08 | F6: 32.470632 | G6: 34.407901 | H6: 5.8982647 | I6: 39.35643 | J6: =IF($A6=J$2,1,0) -> 1 | K6: =IF($A6=K$2,1,0) -> 0 | L6: =IF($A6=L$2,1,0) -> 0 | M6: =IF($A6=M$2,1,0) -> 0 | N6: =IF($A6=N$2,1,0) -> 0 | O6: =IF($A6=O$2,1,0) -> 0 | P6: =IF($A6=P$2,1,0) -> 0 | Q6: =IF($A6=Q$2,1,0) -> 0 | ... BZ6: =IF($A6=BZ$2,1,0) -> 0
A7: Apex Capital Partners | B7: Investment & Asset Management | C7: 2.032438e+08 | D7: =C7-E7 -> 39655154 | E7: 1.6358865e+08 | F7: 63.476778 | G7: 0.36828509 | H7: 4.2349601 | I7: 40.309513 | J7: =IF($A7=J$2,1,0) -> 1 | K7: =IF($A7=K$2,1,0) -> 0 | L7: =IF($A7=L$2,1,0) -> 0 | M7: =IF($A7=M$2,1,0) -> 0 | N7: =IF($A7=N$2,1,0) -> 0 | O7: =IF($A7=O$2,1,0) -> 0 | P7: =IF($A7=P$2,1,0) -> 0 | Q7: =IF($A7=Q$2,1,0) -> 0 | ... BZ7: =IF($A7=BZ$2,1,0) -> 0
A8: Apex Capital Partners | B8: Investment & Asset Management | C8: 2.4285012e+08 | D8: =C8-E8 -> 78442525 | E8: 1.6440759e+08 | F8: 69.999336 | G8: 31.013721 | H8: 4.9613178 | I8: 41.07959 | J8: =IF($A8=J$2,1,0) -> 1 | K8: =IF($A8=K$2,1,0) -> 0 | L8: =IF($A8=L$2,1,0) -> 0 | M8: =IF($A8=M$2,1,0) -> 0 | N8: =IF($A8=N$2,1,0) -> 0 | O8: =IF($A8=O$2,1,0) -> 0 | P8: =IF($A8=P$2,1,0) -> 0 | Q8: =IF($A8=Q$2,1,0) -> 0 | ... BZ8: =IF($A8=BZ$2,1,0) -> 0
A9: Apex Capital Partners | B9: Investment & Asset Management | C9: 2.5959981e+08 | D9: =C9-E9 -> 95331036 | E9: 1.6426878e+08 | F9: 68.559223 | G9: 33.839917 | H9: 688.80462 | I9: 41.289074 | J9: =IF($A9=J$2,1,0) -> 1 | K9: =IF($A9=K$2,1,0) -> 0 | L9: =IF($A9=L$2,1,0) -> 0 | M9: =IF($A9=M$2,1,0) -> 0 | N9: =IF($A9=N$2,1,0) -> 0 | O9: =IF($A9=O$2,1,0) -> 0 | P9: =IF($A9=P$2,1,0) -> 0 | Q9: =IF($A9=Q$2,1,0) -> 0 | ... BZ9: =IF($A9=BZ$2,1,0) -> 0
A10: Apex Capital Partners | B10: Investment & Asset Management | C10: 2.2985332e+08 | D10: 11623384 | E10: =C10-D10 -> 2.1822993e+08 | F10: 38.269989 | G10: 30.615904 | H10: 6.8587482 | I10: 43.218911 | J10: =IF($A10=J$2,1,0) -> 1 | K10: =IF($A10=K$2,1,0) -> 0 | L10: =IF($A10=L$2,1,0) -> 0 | M10: =IF($A10=M$2,1,0) -> 0 | N10: =IF($A10=N$2,1,0) -> 0 | O10: =IF($A10=O$2,1,0) -> 0 | P10: =IF($A10=P$2,1,0) -> 0 | Q10: =IF($A10=Q$2,1,0) -> 0 | ... BZ10: =IF($A10=BZ$2,1,0) -> 0
A11: Apex Capital Partners | B11: Investment & Asset Management | C11: 2.5901078e+08 | D11: =C11-E11 -> 98459462 | E11: 1.6055132e+08 | F11: 18.399015 | G11: 25.6962 | H11: 7.0106137 | I11: 44.934124 | J11: =IF($A11=J$2,1,0) -> 1 | K11: =IF($A11=K$2,1,0) -> 0 | L11: =IF($A11=L$2,1,0) -> 0 | M11: =IF($A11=M$2,1,0) -> 0 | N11: =IF($A11=N$2,1,0) -> 0 | O11: =IF($A11=O$2,1,0) -> 0 | P11: =IF($A11=P$2,1,0) -> 0 | Q11: =IF($A11=Q$2,1,0) -> 0 | ... BZ11: =IF($A11=BZ$2,1,0) -> 0
A12: Apex Capital Partners | B12: Investment & Asset Management | C12: 2.6129792e+08 | D12: 12294407 | E12: =C12-D12 -> 2.4900352e+08 | F12: 51.849987 | G12: 29.709224 | H12: 7.4503661 | I12: 46.072482 | J12: =IF($A12=J$2,1,0) -> 1 | K12: =IF($A12=K$2,1,0) -> 0 | L12: =IF($A12=L$2,1,0) -> 0 | M12: =IF($A12=M$2,1,0) -> 0 | N12: =IF($A12=N$2,1,0) -> 0 | O12: =IF($A12=O$2,1,0) -> 0 | P12: =IF($A12=P$2,1,0) -> 0 | Q12: =IF($A12=Q$2,1,0) -> 0 | ... BZ12: =IF($A12=BZ$2,1,0) -> 0
A13: Apex Capital Partners | B13: Investment & Asset Management | C13: 2.5534944e+08 | D13: 12409813 | E13: =C13-D13 -> 2.4293963e+08 | F13: 34.404261 | G13: 0.45398678 | H13: 5.0253145 | I13: 46.598314 | J13: =IF($A13=J$2,1,0) -> 1 | K13: =IF($A13=K$2,1,0) -> 0 | L13: =IF($A13=L$2,1,0) -> 0 | M13: =IF($A13=M$2,1,0) -> 0 | N13: =IF($A13=N$2,1,0) -> 0 | O13: =IF($A13=O$2,1,0) -> 0 | P13: =IF($A13=P$2,1,0) -> 0 | Q13: =IF($A13=Q$2,1,0) -> 0 | ... BZ13: =IF($A13=BZ$2,1,0) -> 0
A14: Apex Capital Partners | B14: Investment & Asset Management | C14: 2.328779e+08 | D14: 13779425 | E14: =C14-D14 -> 2.1909847e+08 | F14: 25.055651 | G14: 32.097077 | H14: 3.5272792 | I14: 47.379051 | J14: =IF($A14=J$2,1,0) -> 1 | K14: =IF($A14=K$2,1,0) -> 0 | L14: =IF($A14=L$2,1,0) -> 0 | M14: =IF($A14=M$2,1,0) -> 0 | N14: =IF($A14=N$2,1,0) -> 0 | O14: =IF($A14=O$2,1,0) -> 0 | P14: =IF($A14=P$2,1,0) -> 0 | Q14: =IF($A14=Q$2,1,0) -> 0 | ... BZ14: =IF($A14=BZ$2,1,0) -> 0
A15: Apex Capital Partners | B15: Investment & Asset Management | C15: 2.8161644e+08 | D15: =C15-E15 -> 1.2173523e+08 | E15: 1.5988121e+08 | F15: 100 | G15: 0.34048647 | H15: 3.1942242 | I15: 47.618958 | J15: =IF($A15=J$2,1,0) -> 1 | K15: =IF($A15=K$2,1,0) -> 0 | L15: =IF($A15=L$2,1,0) -> 0 | M15: =IF($A15=M$2,1,0) -> 0 | N15: =IF($A15=N$2,1,0) -> 0 | O15: =IF($A15=O$2,1,0) -> 0 | P15: =IF($A15=P$2,1,0) -> 0 | Q15: =IF($A15=Q$2,1,0) -> 0 | ... BZ15: =IF($A15=BZ$2,1,0) -> 0
A16: Apex Capital Partners | B16: Investment & Asset Management | C16: 2.5017249e+08 | D16: =C16-E16 -> 86623191 | E16: 1.635493e+08 | F16: 51.413709 | G16: 37.112942 | H16: 5.3009657 | I16: 48.092019 | J16: =IF($A16=J$2,1,0) -> 1 | K16: =IF($A16=K$2,1,0) -> 0 | L16: =IF($A16=L$2,1,0) -> 0 | M16: =IF($A16=M$2,1,0) -> 0 | N16: =IF($A16=N$2,1,0) -> 0 | O16: =IF($A16=O$2,1,0) -> 0 | P16: =IF($A16=P$2,1,0) -> 0 | Q16: =IF($A16=Q$2,1,0) -> 0 | ... BZ16: =IF($A16=BZ$2,1,0) -> 0
A17: Apex Capital Partners | B17: Investment & Asset Management | C17: 2.6065468e+08 | D17: =C17-E17 -> 95583636 | E17: 1.6507104e+08 | F17: 41.560718 | G17: 30.668518 | H17: 387.18324 | I17: 48.832514 | J17: =IF($A17=J$2,1,0) -> 1 | K17: =IF($A17=K$2,1,0) -> 0 | L17: =IF($A17=L$2,1,0) -> 0 | M17: =IF($A17=M$2,1,0) -> 0 | N17: =IF($A17=N$2,1,0) -> 0 | O17: =IF($A17=O$2,1,0) -> 0 | P17: =IF($A17=P$2,1,0) -> 0 | Q17: =IF($A17=Q$2,1,0) -> 0 | ... BZ17: =IF($A17=BZ$2,1,0) -> 0
A18: Apex Capital Partners | B18: Investment & Asset Management | C18: 2.3496279e+08 | D18: 11055519 | E18: =C18-D18 -> 2.2390727e+08 | F18: 100 | G18: 38.351475 | H18: 3.3093938 | I18: 53.846885 | J18: =IF($A18=J$2,1,0) -> 1 | K18: =IF($A18=K$2,1,0) -> 0 | L18: =IF($A18=L$2,1,0) -> 0 | M18: =IF($A18=M$2,1,0) -> 0 | N18: =IF($A18=N$2,1,0) -> 0 | O18: =IF($A18=O$2,1,0) -> 0 | P18: =IF($A18=P$2,1,0) -> 0 | Q18: =IF($A18=Q$2,1,0) -> 0 | ... BZ18: =IF($A18=BZ$2,1,0) -> 0
A19: Apex Capital Partners | B19: Investment & Asset Management | C19: 2.4001577e+08 | D19: 12236256 | E19: =C19-D19 -> 2.2777951e+08 | F19: 63.360848 | G19: 28.340815 | H19: 433.34181 | I19: 54.190413 | J19: =IF($A19=J$2,1,0) -> 1 | K19: =IF($A19=K$2,1,0) -> 0 | L19: =IF($A19=L$2,1,0) -> 0 | M19: =IF($A19=M$2,1,0) -> 0 | N19: =IF($A19=N$2,1,0) -> 0 | O19: =IF($A19=O$2,1,0) -> 0 | P19: =IF($A19=P$2,1,0) -> 0 | Q19: =IF($A19=Q$2,1,0) -> 0 | ... BZ19: =IF($A19=BZ$2,1,0) -> 0
A20: Apex Capital Partners | B20: Investment & Asset Management | C20: 2.1035666e+08 | D20: =C20-E20 -> 43384476 | E20: 1.6697219e+08 | F20: 100 | G20: 37.794227 | H20: 2.3773843 | I20: 62.409896 | J20: =IF($A20=J$2,1,0) -> 1 | K20: =IF($A20=K$2,1,0) -> 0 | L20: =IF($A20=L$2,1,0) -> 0 | M20: =IF($A20=M$2,1,0) -> 0 | N20: =IF($A20=N$2,1,0) -> 0 | O20: =IF($A20=O$2,1,0) -> 0 | P20: =IF($A20=P$2,1,0) -> 0 | Q20: =IF($A20=Q$2,1,0) -> 0 | ... BZ20: =IF($A20=BZ$2,1,0) -> 0
A21: Apex Capital Partners | B21: Investment & Asset Management | C21: 2.8789081e+08 | D21: =C21-E21 -> 1.2652042e+08 | E21: 1.6137038e+08 | F21: 71.57063 | G21: 0.33727384 | H21: 4.1859898 | I21: 66.137796 | J21: =IF($A21=J$2,1,0) -> 1 | K21: =IF($A21=K$2,1,0) -> 0 | L21: =IF($A21=L$2,1,0) -> 0 | M21: =IF($A21=M$2,1,0) -> 0 | N21: =IF($A21=N$2,1,0) -> 0 | O21: =IF($A21=O$2,1,0) -> 0 | P21: =IF($A21=P$2,1,0) -> 0 | Q21: =IF($A21=Q$2,1,0) -> 0 | ... BZ21: =IF($A21=BZ$2,1,0) -> 0
A22: Ascend Capital Advisors | B22: Investment & Asset Management | C22: 2.5106556e+08 | D22: =C22-E22 -> 91337339 | E22: 1.5972822e+08 | F22: 49.900688 | G22: 49.612975 | H22: 1.2365358 | I22: 36.111244 | J22: =IF($A22=J$2,1,0) -> 0 | K22: =IF($A22=K$2,1,0) -> 1 | L22: =IF($A22=L$2,1,0) -> 0 | M22: =IF($A22=M$2,1,0) -> 0 | N22: =IF($A22=N$2,1,0) -> 0 | O22: =IF($A22=O$2,1,0) -> 0 | P22: =IF($A22=P$2,1,0) -> 0 | Q22: =IF($A22=Q$2,1,0) -> 0 | ... BZ22: =IF($A22=BZ$2,1,0) -> 0
A23: Ascend Capital Advisors | B23: Investment & Asset Management | C23: 2.3321826e+08 | D23: =C23-E23 -> 62763832 | E23: 1.7045443e+08 | F23: 100 | G23: 40.005825 | H23: 8.7984706 | I23: 38.612734 | J23: =IF($A23=J$2,1,0) -> 0 | K23: =IF($A23=K$2,1,0) -> 1 | L23: =IF($A23=L$2,1,0) -> 0 | M23: =IF($A23=M$2,1,0) -> 0 | N23: =IF($A23=N$2,1,0) -> 0 | O23: =IF($A23=O$2,1,0) -> 0 | P23: =IF($A23=P$2,1,0) -> 0 | Q23: =IF($A23=Q$2,1,0) -> 0 | ... BZ23: =IF($A23=BZ$2,1,0) -> 0
A24: Ascend Capital Advisors | B24: Investment & Asset Management | C24: 2.6446819e+08 | D24: =C24-E24 -> 98512100 | E24: 1.6595609e+08 | F24: 14.946762 | G24: 43.895945 | H24: 3.8644883 | I24: 39.245364 | J24: =IF($A24=J$2,1,0) -> 0 | K24: =IF($A24=K$2,1,0) -> 1 | L24: =IF($A24=L$2,1,0) -> 0 | M24: =IF($A24=M$2,1,0) -> 0 | N24: =IF($A24=N$2,1,0) -> 0 | O24: =IF($A24=O$2,1,0) -> 0 | P24: =IF($A24=P$2,1,0) -> 0 | Q24: =IF($A24=Q$2,1,0) -> 0 | ... BZ24: =IF($A24=BZ$2,1,0) -> 0
A25: Ascend Capital Advisors | B25: Investment & Asset Management | C25: 2.3064354e+08 | D25: 12761330 | E25: =C25-D25 -> 2.1788221e+08 | F25: 100 | G25: 35.106357 | H25: 797.25631 | I25: 41.655969 | J25: =IF($A25=J$2,1,0) -> 0 | K25: =IF($A25=K$2,1,0) -> 1 | L25: =IF($A25=L$2,1,0) -> 0 | M25: =IF($A25=M$2,1,0) -> 0 | N25: =IF($A25=N$2,1,0) -> 0 | O25: =IF($A25=O$2,1,0) -> 0 | P25: =IF($A25=P$2,1,0) -> 0 | Q25: =IF($A25=Q$2,1,0) -> 0 | ... BZ25: =IF($A25=BZ$2,1,0) -> 0
A26: Ascend Capital Advisors | B26: Investment & Asset Management | C26: 2.507027e+08 | D26: 14356170 | E26: =C26-D26 -> 2.3634653e+08 | F26: 100 | G26: 45.756634 | H26: 4.3007112 | I26: 41.751786 | J26: =IF($A26=J$2,1,0) -> 0 | K26: =IF($A26=K$2,1,0) -> 1 | L26: =IF($A26=L$2,1,0) -> 0 | M26: =IF($A26=M$2,1,0) -> 0 | N26: =IF($A26=N$2,1,0) -> 0 | O26: =IF($A26=O$2,1,0) -> 0 | P26: =IF($A26=P$2,1,0) -> 0 | Q26: =IF($A26=Q$2,1,0) -> 0 | ... BZ26: =IF($A26=BZ$2,1,0) -> 0
A27: Ascend Capital Advisors | B27: Investment & Asset Management | C27: 2.4014766e+08 | D27: 13647690 | E27: =C27-D27 -> 2.2649997e+08 | F27: 57.561085 | G27: 43.937187 | H27: 3.288441 | I27: 42.77253 | J27: =IF($A27=J$2,1,0) -> 0 | K27: =IF($A27=K$2,1,0) -> 1 | L27: =IF($A27=L$2,1,0) -> 0 | M27: =IF($A27=M$2,1,0) -> 0 | N27: =IF($A27=N$2,1,0) -> 0 | O27: =IF($A27=O$2,1,0) -> 0 | P27: =IF($A27=P$2,1,0) -> 0 | Q27: =IF($A27=Q$2,1,0) -> 0 | ... BZ27: =IF($A27=BZ$2,1,0) -> 0
A28: Ascend Capital Advisors | B28: Investment & Asset Management | C28: 2.6358774e+08 | D28: =C28-E28 -> 1.0987674e+08 | E28: 1.53711e+08 | F28: 67.79836 | G28: 0.30602275 | H28: 4.9115463 | I28: 44.98894 | J28: =IF($A28=J$2,1,0) -> 0 | K28: =IF($A28=K$2,1,0) -> 1 | L28: =IF($A28=L$2,1,0) -> 0 | M28: =IF($A28=M$2,1,0) -> 0 | N28: =IF($A28=N$2,1,0) -> 0 | O28: =IF($A28=O$2,1,0) -> 0 | P28: =IF($A28=P$2,1,0) -> 0 | Q28: =IF($A28=Q$2,1,0) -> 0 | ... BZ28: =IF($A28=BZ$2,1,0) -> 0
A29: Ascend Capital Advisors | B29: Investment & Asset Management | C29: 2.2374623e+08 | D29: =C29-E29 -> 60035519 | E29: 1.6371071e+08 | F29: 100 | G29: 50.204209 | H29: 3.3567706 | I29: 45.895838 | J29: =IF($A29=J$2,1,0) -> 0 | K29: =IF($A29=K$2,1,0) -> 1 | L29: =IF($A29=L$2,1,0) -> 0 | M29: =IF($A29=M$2,1,0) -> 0 | N29: =IF($A29=N$2,1,0) -> 0 | O29: =IF($A29=O$2,1,0) -> 0 | P29: =IF($A29=P$2,1,0) -> 0 | Q29: =IF($A29=Q$2,1,0) -> 0 | ... BZ29: =IF($A29=BZ$2,1,0) -> 0
A30: Ascend Capital Advisors | B30: Investment & Asset Management | C30: 2.75354e+08 | D30: =C30-E30 -> 1.0891827e+08 | E30: 1.6643574e+08 | F30: 40.803761 | G30: 48.905377 | H30: 860.82742 | I30: 46.766618 | J30: =IF($A30=J$2,1,0) -> 0 | K30: =IF($A30=K$2,1,0) -> 1 | L30: =IF($A30=L$2,1,0) -> 0 | M30: =IF($A30=M$2,1,0) -> 0 | N30: =IF($A30=N$2,1,0) -> 0 | O30: =IF($A30=O$2,1,0) -> 0 | P30: =IF($A30=P$2,1,0) -> 0 | Q30: =IF($A30=Q$2,1,0) -> 0 | ... BZ30: =IF($A30=BZ$2,1,0) -> 0
A31: Ascend Capital Advisors | B31: Investment & Asset Management | C31: 2.3362921e+08 | D31: =C31-E31 -> 57847816 | E31: 1.757814e+08 | F31: 100 | G31: 45.414144 | H31: 2.6753709 | I31: 47.516792 | J31: =IF($A31=J$2,1,0) -> 0 | K31: =IF($A31=K$2,1,0) -> 1 | L31: =IF($A31=L$2,1,0) -> 0 | M31: =IF($A31=M$2,1,0) -> 0 | N31: =IF($A31=N$2,1,0) -> 0 | O31: =IF($A31=O$2,1,0) -> 0 | P31: =IF($A31=P$2,1,0) -> 0 | Q31: =IF($A31=Q$2,1,0) -> 0 | ... BZ31: =IF($A31=BZ$2,1,0) -> 0
A32: Ascend Capital Advisors | B32: Investment & Asset Management | C32: 2.4190419e+08 | D32: =C32-E32 -> 75727253 | E32: 1.6617693e+08 | F32: 100 | G32: 40.956264 | H32: 0.94963735 | I32: 47.516792 | J32: =IF($A32=J$2,1,0) -> 0 | K32: =IF($A32=K$2,1,0) -> 1 | L32: =IF($A32=L$2,1,0) -> 0 | M32: =IF($A32=M$2,1,0) -> 0 | N32: =IF($A32=N$2,1,0) -> 0 | O32: =IF($A32=O$2,1,0) -> 0 | P32: =IF($A32=P$2,1,0) -> 0 | Q32: =IF($A32=Q$2,1,0) -> 0 | ... BZ32: =IF($A32=BZ$2,1,0) -> 0
A33: Ascend Capital Advisors | B33: Investment & Asset Management | C33: 2.3663475e+08 | D33: 11303022 | E33: =C33-D33 -> 2.2533173e+08 | F33: 49.598694 | G33: 45.68605 | H33: 1.6039229 | I33: 47.516792 | J33: =IF($A33=J$2,1,0) -> 0 | K33: =IF($A33=K$2,1,0) -> 1 | L33: =IF($A33=L$2,1,0) -> 0 | M33: =IF($A33=M$2,1,0) -> 0 | N33: =IF($A33=N$2,1,0) -> 0 | O33: =IF($A33=O$2,1,0) -> 0 | P33: =IF($A33=P$2,1,0) -> 0 | Q33: =IF($A33=Q$2,1,0) -> 0 | ... BZ33: =IF($A33=BZ$2,1,0) -> 0
A34: Ascend Capital Advisors | B34: Investment & Asset Management | C34: 2.638053e+08 | D34: =C34-E34 -> 1.1025273e+08 | E34: 1.5355257e+08 | F34: 35.719723 | G34: 45.464528 | H34: 3.2555649 | I34: 47.516792 | J34: =IF($A34=J$2,1,0) -> 0 | K34: =IF($A34=K$2,1,0) -> 1 | L34: =IF($A34=L$2,1,0) -> 0 | M34: =IF($A34=M$2,1,0) -> 0 | N34: =IF($A34=N$2,1,0) -> 0 | O34: =IF($A34=O$2,1,0) -> 0 | P34: =IF($A34=P$2,1,0) -> 0 | Q34: =IF($A34=Q$2,1,0) -> 0 | ... BZ34: =IF($A34=BZ$2,1,0) -> 0
A35: Ascend Capital Advisors | B35: Investment & Asset Management | C35: 2.1991773e+08 | D35: =C35-E35 -> 48885674 | E35: 1.7103206e+08 | F35: 100 | G35: 44.939349 | H35: 7.4352217 | I35: 48.570326 | J35: =IF($A35=J$2,1,0) -> 0 | K35: =IF($A35=K$2,1,0) -> 1 | L35: =IF($A35=L$2,1,0) -> 0 | M35: =IF($A35=M$2,1,0) -> 0 | N35: =IF($A35=N$2,1,0) -> 0 | O35: =IF($A35=O$2,1,0) -> 0 | P35: =IF($A35=P$2,1,0) -> 0 | Q35: =IF($A35=Q$2,1,0) -> 0 | ... BZ35: =IF($A35=BZ$2,1,0) -> 0
A36: Ascend Capital Advisors | B36: Investment & Asset Management | C36: 2.481852e+08 | D36: 12481549 | E36: =C36-D36 -> 2.3570365e+08 | F36: 34.19378 | G36: 48.901174 | H36: 3.046129 | I36: 49.560224 | J36: =IF($A36=J$2,1,0) -> 0 | K36: =IF($A36=K$2,1,0) -> 1 | L36: =IF($A36=L$2,1,0) -> 0 | M36: =IF($A36=M$2,1,0) -> 0 | N36: =IF($A36=N$2,1,0) -> 0 | O36: =IF($A36=O$2,1,0) -> 0 | P36: =IF($A36=P$2,1,0) -> 0 | Q36: =IF($A36=Q$2,1,0) -> 0 | ... BZ36: =IF($A36=BZ$2,1,0) -> 0
A37: Ascend Capital Advisors | B37: Investment & Asset Management | C37: 2.2784605e+08 | D37: 12652198 | E37: =C37-D37 -> 2.1519385e+08 | F37: 47.022033 | G37: 43.061967 | H37: 6.8095022 | I37: 50.110579 | J37: =IF($A37=J$2,1,0) -> 0 | K37: =IF($A37=K$2,1,0) -> 1 | L37: =IF($A37=L$2,1,0) -> 0 | M37: =IF($A37=M$2,1,0) -> 0 | N37: =IF($A37=N$2,1,0) -> 0 | O37: =IF($A37=O$2,1,0) -> 0 | P37: =IF($A37=P$2,1,0) -> 0 | Q37: =IF($A37=Q$2,1,0) -> 0 | ... BZ37: =IF($A37=BZ$2,1,0) -> 0
A38: Ascend Capital Advisors | B38: Investment & Asset Management | C38: 2.5983872e+08 | D38: 13130176 | E38: =C38-D38 -> 2.4670855e+08 | F38: 44.997815 | G38: 0.45744103 | H38: 0.33470299 | I38: 55.421811 | J38: =IF($A38=J$2,1,0) -> 0 | K38: =IF($A38=K$2,1,0) -> 1 | L38: =IF($A38=L$2,1,0) -> 0 | M38: =IF($A38=M$2,1,0) -> 0 | N38: =IF($A38=N$2,1,0) -> 0 | O38: =IF($A38=O$2,1,0) -> 0 | P38: =IF($A38=P$2,1,0) -> 0 | Q38: =IF($A38=Q$2,1,0) -> 0 | ... BZ38: =IF($A38=BZ$2,1,0) -> 0
A39: Ascend Capital Advisors | B39: Investment & Asset Management | C39: 2.5800445e+08 | D39: =C39-E39 -> 1.0266779e+08 | E39: 1.5533666e+08 | F39: 26.353828 | G39: 42.327395 | H39: 4.7233589 | I39: 57.553447 | J39: =IF($A39=J$2,1,0) -> 0 | K39: =IF($A39=K$2,1,0) -> 1 | L39: =IF($A39=L$2,1,0) -> 0 | M39: =IF($A39=M$2,1,0) -> 0 | N39: =IF($A39=N$2,1,0) -> 0 | O39: =IF($A39=O$2,1,0) -> 0 | P39: =IF($A39=P$2,1,0) -> 0 | Q39: =IF($A39=Q$2,1,0) -> 0 | ... BZ39: =IF($A39=BZ$2,1,0) -> 0
A40: Ascend Capital Advisors | B40: Investment & Asset Management | C40: 2.6356627e+08 | D40: =C40-E40 -> 1.039433e+08 | E40: 1.5962296e+08 | F40: 73.09948 | G40: 43.767441 | H40: 1.6132018 | I40: 59.642141 | J40: =IF($A40=J$2,1,0) -> 0 | K40: =IF($A40=K$2,1,0) -> 1 | L40: =IF($A40=L$2,1,0) -> 0 | M40: =IF($A40=M$2,1,0) -> 0 | N40: =IF($A40=N$2,1,0) -> 0 | O40: =IF($A40=O$2,1,0) -> 0 | P40: =IF($A40=P$2,1,0) -> 0 | Q40: =IF($A40=Q$2,1,0) -> 0 | ... BZ40: =IF($A40=BZ$2,1,0) -> 0
A41: Ascend Capital Advisors | B41: Investment & Asset Management | C41: 2.3123352e+08 | D41: 12433786 | E41: =C41-D41 -> 2.1879973e+08 | F41: 100 | G41: 0.47759217 | H41: 4.7353749 | I41: 61.609121 | J41: =IF($A41=J$2,1,0) -> 0 | K41: =IF($A41=K$2,1,0) -> 1 | L41: =IF($A41=L$2,1,0) -> 0 | M41: =IF($A41=M$2,1,0) -> 0 | N41: =IF($A41=N$2,1,0) -> 0 | O41: =IF($A41=O$2,1,0) -> 0 | P41: =IF($A41=P$2,1,0) -> 0 | Q41: =IF($A41=Q$2,1,0) -> 0 | ... BZ41: =IF($A41=BZ$2,1,0) -> 0
A42: Atlas Blockchain Services | B42: FinTech & Payment Systems | C42: 2.5492578e+08 | D42: =C42-E42 -> 92902253 | E42: 1.6202352e+08 | F42: 64.165081 | G42: 48.105769 | H42: 5.0025849 | I42: 38.129617 | J42: =IF($A42=J$2,1,0) -> 0 | K42: =IF($A42=K$2,1,0) -> 0 | L42: =IF($A42=L$2,1,0) -> 1 | M42: =IF($A42=M$2,1,0) -> 0 | N42: =IF($A42=N$2,1,0) -> 0 | O42: =IF($A42=O$2,1,0) -> 0 | P42: =IF($A42=P$2,1,0) -> 0 | Q42: =IF($A42=Q$2,1,0) -> 0 | ... BZ42: =IF($A42=BZ$2,1,0) -> 0
A43: Atlas Blockchain Services | B43: FinTech & Payment Systems | C43: 2.3283332e+08 | D43: 13055116 | E43: =C43-D43 -> 2.197782e+08 | F43: 100 | G43: 42.057015 | H43: 9.0141652 | I43: 42.236874 | J43: =IF($A43=J$2,1,0) -> 0 | K43: =IF($A43=K$2,1,0) -> 0 | L43: =IF($A43=L$2,1,0) -> 1 | M43: =IF($A43=M$2,1,0) -> 0 | N43: =IF($A43=N$2,1,0) -> 0 | O43: =IF($A43=O$2,1,0) -> 0 | P43: =IF($A43=P$2,1,0) -> 0 | Q43: =IF($A43=Q$2,1,0) -> 0 | ... BZ43: =IF($A43=BZ$2,1,0) -> 0
A44: Atlas Blockchain Services | B44: FinTech & Payment Systems | C44: 3.0022213e+08 | D44: 12478108 | E44: =C44-D44 -> 2.8774402e+08 | F44: 100 | G44: 38.583742 | H44: 3.4208087 | I44: 42.599845 | J44: =IF($A44=J$2,1,0) -> 0 | K44: =IF($A44=K$2,1,0) -> 0 | L44: =IF($A44=L$2,1,0) -> 1 | M44: =IF($A44=M$2,1,0) -> 0 | N44: =IF($A44=N$2,1,0) -> 0 | O44: =IF($A44=O$2,1,0) -> 0 | P44: =IF($A44=P$2,1,0) -> 0 | Q44: =IF($A44=Q$2,1,0) -> 0 | ... BZ44: =IF($A44=BZ$2,1,0) -> 0
A45: Atlas Blockchain Services | B45: FinTech & Payment Systems | C45: 2.4698316e+08 | D45: =C45-E45 -> 81289248 | E45: 1.6569391e+08 | F45: 61.926374 | G45: 44.00552 | H45: 3.8252788 | I45: 42.766493 | J45: =IF($A45=J$2,1,0) -> 0 | K45: =IF($A45=K$2,1,0) -> 0 | L45: =IF($A45=L$2,1,0) -> 1 | M45: =IF($A45=M$2,1,0) -> 0 | N45: =IF($A45=N$2,1,0) -> 0 | O45: =IF($A45=O$2,1,0) -> 0 | P45: =IF($A45=P$2,1,0) -> 0 | Q45: =IF($A45=Q$2,1,0) -> 0 | ... BZ45: =IF($A45=BZ$2,1,0) -> 0
A46: Atlas Blockchain Services | B46: FinTech & Payment Systems | C46: 2.5849922e+08 | D46: 14326863 | E46: =C46-D46 -> 2.4417235e+08 | F46: 100 | G46: 55.393682 | H46: 5.8254675 | I46: 43.791709 | J46: =IF($A46=J$2,1,0) -> 0 | K46: =IF($A46=K$2,1,0) -> 0 | L46: =IF($A46=L$2,1,0) -> 1 | M46: =IF($A46=M$2,1,0) -> 0 | N46: =IF($A46=N$2,1,0) -> 0 | O46: =IF($A46=O$2,1,0) -> 0 | P46: =IF($A46=P$2,1,0) -> 0 | Q46: =IF($A46=Q$2,1,0) -> 0 | ... BZ46: =IF($A46=BZ$2,1,0) -> 0
A47: Atlas Blockchain Services | B47: FinTech & Payment Systems | C47: 2.7697718e+08 | D47: =C47-E47 -> 1.2696641e+08 | E47: 1.5001077e+08 | F47: 41.227009 | G47: 49.397079 | H47: 272.20768 | I47: 46.516918 | J47: =IF($A47=J$2,1,0) -> 0 | K47: =IF($A47=K$2,1,0) -> 0 | L47: =IF($A47=L$2,1,0) -> 1 | M47: =IF($A47=M$2,1,0) -> 0 | N47: =IF($A47=N$2,1,0) -> 0 | O47: =IF($A47=O$2,1,0) -> 0 | P47: =IF($A47=P$2,1,0) -> 0 | Q47: =IF($A47=Q$2,1,0) -> 0 | ... BZ47: =IF($A47=BZ$2,1,0) -> 0
A48: Atlas Blockchain Services | B48: FinTech & Payment Systems | C48: 2.1592246e+08 | D48: =C48-E48 -> 55150734 | E48: 1.6077172e+08 | F48: 23.362526 | G48: 0.48125701 | H48: 545.48828 | I48: 50.829658 | J48: =IF($A48=J$2,1,0) -> 0 | K48: =IF($A48=K$2,1,0) -> 0 | L48: =IF($A48=L$2,1,0) -> 1 | M48: =IF($A48=M$2,1,0) -> 0 | N48: =IF($A48=N$2,1,0) -> 0 | O48: =IF($A48=O$2,1,0) -> 0 | P48: =IF($A48=P$2,1,0) -> 0 | Q48: =IF($A48=Q$2,1,0) -> 0 | ... BZ48: =IF($A48=BZ$2,1,0) -> 0
A49: Atlas Blockchain Services | B49: FinTech & Payment Systems | C49: 2.6883397e+08 | D49: 12637067 | E49: =C49-D49 -> 2.561969e+08 | F49: 87.099957 | G49: 0.42327575 | H49: 0.40674344 | I49: 52.236415 | J49: =IF($A49=J$2,1,0) -> 0 | K49: =IF($A49=K$2,1,0) -> 0 | L49: =IF($A49=L$2,1,0) -> 1 | M49: =IF($A49=M$2,1,0) -> 0 | N49: =IF($A49=N$2,1,0) -> 0 | O49: =IF($A49=O$2,1,0) -> 0 | P49: =IF($A49=P$2,1,0) -> 0 | Q49: =IF($A49=Q$2,1,0) -> 0 | ... BZ49: =IF($A49=BZ$2,1,0) -> 0
A50: Atlas Blockchain Services | B50: FinTech & Payment Systems | C50: 2.6891697e+08 | D50: =C50-E50 -> 1.1068218e+08 | E50: 1.5823478e+08 | F50: 45.589694 | G50: 0.48444848 | H50: 471.40424 | I50: 52.236415 | J50: =IF($A50=J$2,1,0) -> 0 | K50: =IF($A50=K$2,1,0) -> 0 | L50: =IF($A50=L$2,1,0) -> 1 | M50: =IF($A50=M$2,1,0) -> 0 | N50: =IF($A50=N$2,1,0) -> 0 | O50: =IF($A50=O$2,1,0) -> 0 | P50: =IF($A50=P$2,1,0) -> 0 | Q50: =IF($A50=Q$2,1,0) -> 0 | ... BZ50: =IF($A50=BZ$2,1,0) -> 0
A51: Atlas Blockchain Services | B51: FinTech & Payment Systems | C51: 2.0619771e+08 | D51: =C51-E51 -> 57990311 | E51: 1.482074e+08 | F51: 100 | G51: 43.108835 | H51: 6.486165 | I51: 52.43166 | J51: =IF($A51=J$2,1,0) -> 0 | K51: =IF($A51=K$2,1,0) -> 0 | L51: =IF($A51=L$2,1,0) -> 1 | M51: =IF($A51=M$2,1,0) -> 0 | N51: =IF($A51=N$2,1,0) -> 0 | O51: =IF($A51=O$2,1,0) -> 0 | P51: =IF($A51=P$2,1,0) -> 0 | Q51: =IF($A51=Q$2,1,0) -> 0 | ... BZ51: =IF($A51=BZ$2,1,0) -> 0
A52: Atlas Blockchain Services | B52: FinTech & Payment Systems | C52: 2.6882009e+08 | D52: 10887960 | E52: =C52-D52 -> 2.5793213e+08 | F52: 34.706005 | G52: 44.519736 | H52: 609.93542 | I52: 52.917271 | J52: =IF($A52=J$2,1,0) -> 0 | K52: =IF($A52=K$2,1,0) -> 0 | L52: =IF($A52=L$2,1,0) -> 1 | M52: =IF($A52=M$2,1,0) -> 0 | N52: =IF($A52=N$2,1,0) -> 0 | O52: =IF($A52=O$2,1,0) -> 0 | P52: =IF($A52=P$2,1,0) -> 0 | Q52: =IF($A52=Q$2,1,0) -> 0 | ... BZ52: =IF($A52=BZ$2,1,0) -> 0
A53: Atlas Blockchain Services | B53: FinTech & Payment Systems | C53: 2.5332422e+08 | D53: =C53-E53 -> 83240501 | E53: 1.7008372e+08 | F53: 39.76528 | G53: 51.217369 | H53: 2.8377056 | I53: 53.044661 | J53: =IF($A53=J$2,1,0) -> 0 | K53: =IF($A53=K$2,1,0) -> 0 | L53: =IF($A53=L$2,1,0) -> 1 | M53: =IF($A53=M$2,1,0) -> 0 | N53: =IF($A53=N$2,1,0) -> 0 | O53: =IF($A53=O$2,1,0) -> 0 | P53: =IF($A53=P$2,1,0) -> 0 | Q53: =IF($A53=Q$2,1,0) -> 0 | ... BZ53: =IF($A53=BZ$2,1,0) -> 0
A54: Atlas Blockchain Services | B54: FinTech & Payment Systems | C54: 2.4661854e+08 | D54: =C54-E54 -> 75296694 | E54: 1.7132185e+08 | F54: 68.044869 | G54: 41.487821 | H54: 389.28645 | I54: 54.127144 | J54: =IF($A54=J$2,1,0) -> 0 | K54: =IF($A54=K$2,1,0) -> 0 | L54: =IF($A54=L$2,1,0) -> 1 | M54: =IF($A54=M$2,1,0) -> 0 | N54: =IF($A54=N$2,1,0) -> 0 | O54: =IF($A54=O$2,1,0) -> 0 | P54: =IF($A54=P$2,1,0) -> 0 | Q54: =IF($A54=Q$2,1,0) -> 0 | ... BZ54: =IF($A54=BZ$2,1,0) -> 0
A55: Atlas Blockchain Services | B55: FinTech & Payment Systems | C55: 2.1629966e+08 | D55: 13582629 | E55: =C55-D55 -> 2.0271703e+08 | F55: 98.803235 | G55: 0.45971893 | H55: 5.9349966 | I55: 55.665645 | J55: =IF($A55=J$2,1,0) -> 0 | K55: =IF($A55=K$2,1,0) -> 0 | L55: =IF($A55=L$2,1,0) -> 1 | M55: =IF($A55=M$2,1,0) -> 0 | N55: =IF($A55=N$2,1,0) -> 0 | O55: =IF($A55=O$2,1,0) -> 0 | P55: =IF($A55=P$2,1,0) -> 0 | Q55: =IF($A55=Q$2,1,0) -> 0 | ... BZ55: =IF($A55=BZ$2,1,0) -> 0
A56: Atlas Blockchain Services | B56: FinTech & Payment Systems | C56: 2.2766382e+08 | D56: 13096152 | E56: =C56-D56 -> 2.1456767e+08 | F56: 54.03459 | G56: 41.825959 | H56: 4.9593794 | I56: 58.168088 | J56: =IF($A56=J$2,1,0) -> 0 | K56: =IF($A56=K$2,1,0) -> 0 | L56: =IF($A56=L$2,1,0) -> 1 | M56: =IF($A56=M$2,1,0) -> 0 | N56: =IF($A56=N$2,1,0) -> 0 | O56: =IF($A56=O$2,1,0) -> 0 | P56: =IF($A56=P$2,1,0) -> 0 | Q56: =IF($A56=Q$2,1,0) -> 0 | ... BZ56: =IF($A56=BZ$2,1,0) -> 0
A57: Atlas Blockchain Services | B57: FinTech & Payment Systems | C57: 2.4942489e+08 | D57: 11391317 | E57: =C57-D57 -> 2.3803357e+08 | F57: 100 | G57: 0.51101305 | H57: 4.8328924 | I57: 60.230846 | J57: =IF($A57=J$2,1,0) -> 0 | K57: =IF($A57=K$2,1,0) -> 0 | L57: =IF($A57=L$2,1,0) -> 1 | M57: =IF($A57=M$2,1,0) -> 0 | N57: =IF($A57=N$2,1,0) -> 0 | O57: =IF($A57=O$2,1,0) -> 0 | P57: =IF($A57=P$2,1,0) -> 0 | Q57: =IF($A57=Q$2,1,0) -> 0 | ... BZ57: =IF($A57=BZ$2,1,0) -> 0
A58: Atlas Blockchain Services | B58: FinTech & Payment Systems | C58: 2.4286673e+08 | D58: 14481975 | E58: =C58-D58 -> 2.2838476e+08 | F58: 47.304466 | G58: 0.48682589 | H58: 7.7998438 | I58: 61.659902 | J58: =IF($A58=J$2,1,0) -> 0 | K58: =IF($A58=K$2,1,0) -> 0 | L58: =IF($A58=L$2,1,0) -> 1 | M58: =IF($A58=M$2,1,0) -> 0 | N58: =IF($A58=N$2,1,0) -> 0 | O58: =IF($A58=O$2,1,0) -> 0 | P58: =IF($A58=P$2,1,0) -> 0 | Q58: =IF($A58=Q$2,1,0) -> 0 | ... BZ58: =IF($A58=BZ$2,1,0) -> 0
A59: Atlas Blockchain Services | B59: FinTech & Payment Systems | C59: 2.4291862e+08 | D59: =C59-E59 -> 77019255 | E59: 1.6589937e+08 | F59: 55.11606 | G59: 35.904366 | H59: 761.22682 | I59: 63.263272 | J59: =IF($A59=J$2,1,0) -> 0 | K59: =IF($A59=K$2,1,0) -> 0 | L59: =IF($A59=L$2,1,0) -> 1 | M59: =IF($A59=M$2,1,0) -> 0 | N59: =IF($A59=N$2,1,0) -> 0 | O59: =IF($A59=O$2,1,0) -> 0 | P59: =IF($A59=P$2,1,0) -> 0 | Q59: =IF($A59=Q$2,1,0) -> 0 | ... BZ59: =IF($A59=BZ$2,1,0) -> 0
A60: Atlas Blockchain Services | B60: FinTech & Payment Systems | C60: 2.5160114e+08 | D60: 13576176 | E60: =C60-D60 -> 2.3802496e+08 | F60: 100 | G60: 0.50890141 | H60: 2.9277575 | I60: 69.639448 | J60: =IF($A60=J$2,1,0) -> 0 | K60: =IF($A60=K$2,1,0) -> 0 | L60: =IF($A60=L$2,1,0) -> 1 | M60: =IF($A60=M$2,1,0) -> 0 | N60: =IF($A60=N$2,1,0) -> 0 | O60: =IF($A60=O$2,1,0) -> 0 | P60: =IF($A60=P$2,1,0) -> 0 | Q60: =IF($A60=Q$2,1,0) -> 0 | ... BZ60: =IF($A60=BZ$2,1,0) -> 0
A61: Atlas Community Bank | B61: Banking & Depository Services | C61: 2.4092438e+08 | D61: 11446563 | E61: =C61-D61 -> 2.2947781e+08 | F61: 100 | G61: 40.456499 | H61: 2.330909 | I61: 37.882987 | J61: =IF($A61=J$2,1,0) -> 0 | K61: =IF($A61=K$2,1,0) -> 0 | L61: =IF($A61=L$2,1,0) -> 0 | M61: =IF($A61=M$2,1,0) -> 1 | N61: =IF($A61=N$2,1,0) -> 0 | O61: =IF($A61=O$2,1,0) -> 0 | P61: =IF($A61=P$2,1,0) -> 0 | Q61: =IF($A61=Q$2,1,0) -> 0 | ... BZ61: =IF($A61=BZ$2,1,0) -> 0
A62: Atlas Community Bank | B62: Banking & Depository Services | C62: 2.5509642e+08 | D62: 11607888 | E62: =C62-D62 -> 2.4348853e+08 | F62: 39.148038 | G62: 26.620443 | H62: 7.3571739 | I62: 38.53277 | J62: =IF($A62=J$2,1,0) -> 0 | K62: =IF($A62=K$2,1,0) -> 0 | L62: =IF($A62=L$2,1,0) -> 0 | M62: =IF($A62=M$2,1,0) -> 1 | N62: =IF($A62=N$2,1,0) -> 0 | O62: =IF($A62=O$2,1,0) -> 0 | P62: =IF($A62=P$2,1,0) -> 0 | Q62: =IF($A62=Q$2,1,0) -> 0 | ... BZ62: =IF($A62=BZ$2,1,0) -> 0
A63: Atlas Community Bank | B63: Banking & Depository Services | C63: 2.7535252e+08 | D63: =C63-E63 -> 1.1006995e+08 | E63: 1.6528257e+08 | F63: 43.154805 | G63: 0.43661681 | H63: 1.062733 | I63: 39.696011 | J63: =IF($A63=J$2,1,0) -> 0 | K63: =IF($A63=K$2,1,0) -> 0 | L63: =IF($A63=L$2,1,0) -> 0 | M63: =IF($A63=M$2,1,0) -> 1 | N63: =IF($A63=N$2,1,0) -> 0 | O63: =IF($A63=O$2,1,0) -> 0 | P63: =IF($A63=P$2,1,0) -> 0 | Q63: =IF($A63=Q$2,1,0) -> 0 | ... BZ63: =IF($A63=BZ$2,1,0) -> 0
A64: Atlas Community Bank | B64: Banking & Depository Services | C64: 2.6792245e+08 | D64: =C64-E64 -> 1.0133599e+08 | E64: 1.6658646e+08 | F64: 49.292637 | G64: 32.738045 | H64: 8.0683281 | I64: 41.647815 | J64: =IF($A64=J$2,1,0) -> 0 | K64: =IF($A64=K$2,1,0) -> 0 | L64: =IF($A64=L$2,1,0) -> 0 | M64: =IF($A64=M$2,1,0) -> 1 | N64: =IF($A64=N$2,1,0) -> 0 | O64: =IF($A64=O$2,1,0) -> 0 | P64: =IF($A64=P$2,1,0) -> 0 | Q64: =IF($A64=Q$2,1,0) -> 0 | ... BZ64: =IF($A64=BZ$2,1,0) -> 0
A65: Atlas Community Bank | B65: Banking & Depository Services | C65: 2.5097008e+08 | D65: =C65-E65 -> 78926681 | E65: 1.720434e+08 | F65: 30.908886 | G65: 28.955286 | H65: 2.2898024 | I65: 41.958261 | J65: =IF($A65=J$2,1,0) -> 0 | K65: =IF($A65=K$2,1,0) -> 0 | L65: =IF($A65=L$2,1,0) -> 0 | M65: =IF($A65=M$2,1,0) -> 1 | N65: =IF($A65=N$2,1,0) -> 0 | O65: =IF($A65=O$2,1,0) -> 0 | P65: =IF($A65=P$2,1,0) -> 0 | Q65: =IF($A65=Q$2,1,0) -> 0 | ... BZ65: =IF($A65=BZ$2,1,0) -> 0
A66: Atlas Community Bank | B66: Banking & Depository Services | C66: 2.275724e+08 | D66: 11676588 | E66: =C66-D66 -> 2.1589581e+08 | F66: 28.005581 | G66: 36.779844 | H66: 5.6587074 | I66: 47.314547 | J66: =IF($A66=J$2,1,0) -> 0 | K66: =IF($A66=K$2,1,0) -> 0 | L66: =IF($A66=L$2,1,0) -> 0 | M66: =IF($A66=M$2,1,0) -> 1 | N66: =IF($A66=N$2,1,0) -> 0 | O66: =IF($A66=O$2,1,0) -> 0 | P66: =IF($A66=P$2,1,0) -> 0 | Q66: =IF($A66=Q$2,1,0) -> 0 | ... BZ66: =IF($A66=BZ$2,1,0) -> 0
A67: Atlas Community Bank | B67: Banking & Depository Services | C67: 2.5279846e+08 | D67: =C67-E67 -> 95463990 | E67: 1.5733447e+08 | F67: 66.881277 | G67: 30.341402 | H67: 3.169884 | I67: 49.797867 | J67: =IF($A67=J$2,1,0) -> 0 | K67: =IF($A67=K$2,1,0) -> 0 | L67: =IF($A67=L$2,1,0) -> 0 | M67: =IF($A67=M$2,1,0) -> 1 | N67: =IF($A67=N$2,1,0) -> 0 | O67: =IF($A67=O$2,1,0) -> 0 | P67: =IF($A67=P$2,1,0) -> 0 | Q67: =IF($A67=Q$2,1,0) -> 0 | ... BZ67: =IF($A67=BZ$2,1,0) -> 0
A68: Atlas Community Bank | B68: Banking & Depository Services | C68: 2.3398373e+08 | D68: 10673207 | E68: =C68-D68 -> 2.2331052e+08 | F68: 13.350888 | G68: 0.35891938 | H68: 6.1701491 | I68: 50.785646 | J68: =IF($A68=J$2,1,0) -> 0 | K68: =IF($A68=K$2,1,0) -> 0 | L68: =IF($A68=L$2,1,0) -> 0 | M68: =IF($A68=M$2,1,0) -> 1 | N68: =IF($A68=N$2,1,0) -> 0 | O68: =IF($A68=O$2,1,0) -> 0 | P68: =IF($A68=P$2,1,0) -> 0 | Q68: =IF($A68=Q$2,1,0) -> 0 | ... BZ68: =IF($A68=BZ$2,1,0) -> 0
A69: Atlas Community Bank | B69: Banking & Depository Services | C69: 2.268642e+08 | D69: 14235771 | E69: =C69-D69 -> 2.1262843e+08 | F69: 25.322853 | G69: 37.253584 | H69: 7.0581902 | I69: 52.05988 | J69: =IF($A69=J$2,1,0) -> 0 | K69: =IF($A69=K$2,1,0) -> 0 | L69: =IF($A69=L$2,1,0) -> 0 | M69: =IF($A69=M$2,1,0) -> 1 | N69: =IF($A69=N$2,1,0) -> 0 | O69: =IF($A69=O$2,1,0) -> 0 | P69: =IF($A69=P$2,1,0) -> 0 | Q69: =IF($A69=Q$2,1,0) -> 0 | ... BZ69: =IF($A69=BZ$2,1,0) -> 0
A70: Atlas Community Bank | B70: Banking & Depository Services | C70: 2.4387235e+08 | D70: 13407807 | E70: =C70-D70 -> 2.3046454e+08 | F70: 28.250656 | G70: 27.332807 | H70: 5.2958951 | I70: 56.116601 | J70: =IF($A70=J$2,1,0) -> 0 | K70: =IF($A70=K$2,1,0) -> 0 | L70: =IF($A70=L$2,1,0) -> 0 | M70: =IF($A70=M$2,1,0) -> 1 | N70: =IF($A70=N$2,1,0) -> 0 | O70: =IF($A70=O$2,1,0) -> 0 | P70: =IF($A70=P$2,1,0) -> 0 | Q70: =IF($A70=Q$2,1,0) -> 0 | ... BZ70: =IF($A70=BZ$2,1,0) -> 0
A71: Atlas Community Bank | B71: Banking & Depository Services | C71: 2.6006916e+08 | D71: 11804161 | E71: =C71-D71 -> 2.48265e+08 | F71: 100 | G71: 28.689562 | H71: 3.7753189 | I71: 56.317416 | J71: =IF($A71=J$2,1,0) -> 0 | K71: =IF($A71=K$2,1,0) -> 0 | L71: =IF($A71=L$2,1,0) -> 0 | M71: =IF($A71=M$2,1,0) -> 1 | N71: =IF($A71=N$2,1,0) -> 0 | O71: =IF($A71=O$2,1,0) -> 0 | P71: =IF($A71=P$2,1,0) -> 0 | Q71: =IF($A71=Q$2,1,0) -> 0 | ... BZ71: =IF($A71=BZ$2,1,0) -> 0
A72: Atlas Community Bank | B72: Banking & Depository Services | C72: 2.4550416e+08 | D72: 12120625 | E72: =C72-D72 -> 2.3338353e+08 | F72: 100 | G72: 38.012694 | H72: 3.4502834 | I72: 57.462007 | J72: =IF($A72=J$2,1,0) -> 0 | K72: =IF($A72=K$2,1,0) -> 0 | L72: =IF($A72=L$2,1,0) -> 0 | M72: =IF($A72=M$2,1,0) -> 1 | N72: =IF($A72=N$2,1,0) -> 0 | O72: =IF($A72=O$2,1,0) -> 0 | P72: =IF($A72=P$2,1,0) -> 0 | Q72: =IF($A72=Q$2,1,0) -> 0 | ... BZ72: =IF($A72=BZ$2,1,0) -> 0
A73: Atlas Community Bank | B73: Banking & Depository Services | C73: 2.7236732e+08 | D73: =C73-E73 -> 1.0882974e+08 | E73: 1.6353758e+08 | F73: 6.0070277 | G73: 0.26657202 | H73: 1.3189558 | I73: 60.108964 | J73: =IF($A73=J$2,1,0) -> 0 | K73: =IF($A73=K$2,1,0) -> 0 | L73: =IF($A73=L$2,1,0) -> 0 | M73: =IF($A73=M$2,1,0) -> 1 | N73: =IF($A73=N$2,1,0) -> 0 | O73: =IF($A73=O$2,1,0) -> 0 | P73: =IF($A73=P$2,1,0) -> 0 | Q73: =IF($A73=Q$2,1,0) -> 0 | ... BZ73: =IF($A73=BZ$2,1,0) -> 0
A74: Atlas Community Bank | B74: Banking & Depository Services | C74: 2.6585042e+08 | D74: 12371226 | E74: =C74-D74 -> 2.5347919e+08 | F74: 51.749535 | G74: 34.855794 | H74: 3.6967644 | I74: 61.367428 | J74: =IF($A74=J$2,1,0) -> 0 | K74: =IF($A74=K$2,1,0) -> 0 | L74: =IF($A74=L$2,1,0) -> 0 | M74: =IF($A74=M$2,1,0) -> 1 | N74: =IF($A74=N$2,1,0) -> 0 | O74: =IF($A74=O$2,1,0) -> 0 | P74: =IF($A74=P$2,1,0) -> 0 | Q74: =IF($A74=Q$2,1,0) -> 0 | ... BZ74: =IF($A74=BZ$2,1,0) -> 0
A75: Atlas Community Bank | B75: Banking & Depository Services | C75: 2.533455e+08 | D75: =C75-E75 -> 96727192 | E75: 1.5661831e+08 | F75: 100 | G75: 35.346938 | H75: 5.5849962 | I75: 62.503932 | J75: =IF($A75=J$2,1,0) -> 0 | K75: =IF($A75=K$2,1,0) -> 0 | L75: =IF($A75=L$2,1,0) -> 0 | M75: =IF($A75=M$2,1,0) -> 1 | N75: =IF($A75=N$2,1,0) -> 0 | O75: =IF($A75=O$2,1,0) -> 0 | P75: =IF($A75=P$2,1,0) -> 0 | Q75: =IF($A75=Q$2,1,0) -> 0 | ... BZ75: =IF($A75=BZ$2,1,0) -> 0
A76: Atlas Community Bank | B76: Banking & Depository Services | C76: 2.7425799e+08 | D76: 12692142 | E76: =C76-D76 -> 2.6156584e+08 | F76: 62.566106 | G76: 30.47938 | H76: 6.8922121 | I76: 63.409173 | J76: =IF($A76=J$2,1,0) -> 0 | K76: =IF($A76=K$2,1,0) -> 0 | L76: =IF($A76=L$2,1,0) -> 0 | M76: =IF($A76=M$2,1,0) -> 1 | N76: =IF($A76=N$2,1,0) -> 0 | O76: =IF($A76=O$2,1,0) -> 0 | P76: =IF($A76=P$2,1,0) -> 0 | Q76: =IF($A76=Q$2,1,0) -> 0 | ... BZ76: =IF($A76=BZ$2,1,0) -> 0
A77: Atlas Community Bank | B77: Banking & Depository Services | C77: 2.3003446e+08 | D77: =C77-E77 -> 72653892 | E77: 1.5738057e+08 | F77: 95.134995 | G77: 40.76617 | H77: 8.5315432 | I77: 68.056654 | J77: =IF($A77=J$2,1,0) -> 0 | K77: =IF($A77=K$2,1,0) -> 0 | L77: =IF($A77=L$2,1,0) -> 0 | M77: =IF($A77=M$2,1,0) -> 1 | N77: =IF($A77=N$2,1,0) -> 0 | O77: =IF($A77=O$2,1,0) -> 0 | P77: =IF($A77=P$2,1,0) -> 0 | Q77: =IF($A77=Q$2,1,0) -> 0 | ... BZ77: =IF($A77=BZ$2,1,0) -> 0
A78: Atlas Private Equity | B78: Investment & Asset Management | C78: 2.4633594e+08 | D78: =C78-E78 -> 80877707 | E78: 1.6545823e+08 | F78: 52.69848 | G78: 47.553456 | H78: 6.1695854 | I78: 41.056188 | J78: =IF($A78=J$2,1,0) -> 0 | K78: =IF($A78=K$2,1,0) -> 0 | L78: =IF($A78=L$2,1,0) -> 0 | M78: =IF($A78=M$2,1,0) -> 0 | N78: =IF($A78=N$2,1,0) -> 1 | O78: =IF($A78=O$2,1,0) -> 0 | P78: =IF($A78=P$2,1,0) -> 0 | Q78: =IF($A78=Q$2,1,0) -> 0 | ... BZ78: =IF($A78=BZ$2,1,0) -> 0
A79: Atlas Private Equity | B79: Investment & Asset Management | C79: 2.709165e+08 | D79: 10181854 | E79: =C79-D79 -> 2.6073465e+08 | F79: 32.223036 | G79: 53.684903 | H79: 0.92902838 | I79: 44.180878 | J79: =IF($A79=J$2,1,0) -> 0 | K79: =IF($A79=K$2,1,0) -> 0 | L79: =IF($A79=L$2,1,0) -> 0 | M79: =IF($A79=M$2,1,0) -> 0 | N79: =IF($A79=N$2,1,0) -> 1 | O79: =IF($A79=O$2,1,0) -> 0 | P79: =IF($A79=P$2,1,0) -> 0 | Q79: =IF($A79=Q$2,1,0) -> 0 | ... BZ79: =IF($A79=BZ$2,1,0) -> 0
A80: Atlas Private Equity | B80: Investment & Asset Management | C80: 2.0894257e+08 | D80: =C80-E80 -> 60224444 | E80: 1.4871813e+08 | F80: 26.143552 | G80: 39.338661 | H80: 604.51314 | I80: 45.671543 | J80: =IF($A80=J$2,1,0) -> 0 | K80: =IF($A80=K$2,1,0) -> 0 | L80: =IF($A80=L$2,1,0) -> 0 | M80: =IF($A80=M$2,1,0) -> 0 | N80: =IF($A80=N$2,1,0) -> 1 | O80: =IF($A80=O$2,1,0) -> 0 | P80: =IF($A80=P$2,1,0) -> 0 | Q80: =IF($A80=Q$2,1,0) -> 0 | ... BZ80: =IF($A80=BZ$2,1,0) -> 0
A81: Atlas Private Equity | B81: Investment & Asset Management | C81: 2.3718273e+08 | D81: 12791147 | E81: =C81-D81 -> 2.2439159e+08 | F81: 69.814917 | G81: 45.607201 | H81: 510.89893 | I81: 46.342863 | J81: =IF($A81=J$2,1,0) -> 0 | K81: =IF($A81=K$2,1,0) -> 0 | L81: =IF($A81=L$2,1,0) -> 0 | M81: =IF($A81=M$2,1,0) -> 0 | N81: =IF($A81=N$2,1,0) -> 1 | O81: =IF($A81=O$2,1,0) -> 0 | P81: =IF($A81=P$2,1,0) -> 0 | Q81: =IF($A81=Q$2,1,0) -> 0 | ... BZ81: =IF($A81=BZ$2,1,0) -> 0
A82: Atlas Private Equity | B82: Investment & Asset Management | C82: 2.4153095e+08 | D82: 12213656 | E82: =C82-D82 -> 2.2931729e+08 | F82: 31.796262 | G82: 47.45392 | H82: 3.4335319 | I82: 47.134082 | J82: =IF($A82=J$2,1,0) -> 0 | K82: =IF($A82=K$2,1,0) -> 0 | L82: =IF($A82=L$2,1,0) -> 0 | M82: =IF($A82=M$2,1,0) -> 0 | N82: =IF($A82=N$2,1,0) -> 1 | O82: =IF($A82=O$2,1,0) -> 0 | P82: =IF($A82=P$2,1,0) -> 0 | Q82: =IF($A82=Q$2,1,0) -> 0 | ... BZ82: =IF($A82=BZ$2,1,0) -> 0
A83: Atlas Private Equity | B83: Investment & Asset Management | C83: 2.7182253e+08 | D83: 11845027 | E83: =C83-D83 -> 2.5997751e+08 | F83: 0 | G83: 41.057193 | H83: 7.9944789 | I83: 47.508258 | J83: =IF($A83=J$2,1,0) -> 0 | K83: =IF($A83=K$2,1,0) -> 0 | L83: =IF($A83=L$2,1,0) -> 0 | M83: =IF($A83=M$2,1,0) -> 0 | N83: =IF($A83=N$2,1,0) -> 1 | O83: =IF($A83=O$2,1,0) -> 0 | P83: =IF($A83=P$2,1,0) -> 0 | Q83: =IF($A83=Q$2,1,0) -> 0 | ... BZ83: =IF($A83=BZ$2,1,0) -> 0
A84: Atlas Private Equity | B84: Investment & Asset Management | C84: 2.707475e+08 | D84: =C84-E84 -> 1.1924698e+08 | E84: 1.5150052e+08 | F84: 39.233147 | G84: 36.539706 | H84: 689.98083 | I84: 48.124104 | J84: =IF($A84=J$2,1,0) -> 0 | K84: =IF($A84=K$2,1,0) -> 0 | L84: =IF($A84=L$2,1,0) -> 0 | M84: =IF($A84=M$2,1,0) -> 0 | N84: =IF($A84=N$2,1,0) -> 1 | O84: =IF($A84=O$2,1,0) -> 0 | P84: =IF($A84=P$2,1,0) -> 0 | Q84: =IF($A84=Q$2,1,0) -> 0 | ... BZ84: =IF($A84=BZ$2,1,0) -> 0
A85: Atlas Private Equity | B85: Investment & Asset Management | C85: 2.4631318e+08 | D85: =C85-E85 -> 93222980 | E85: 1.530902e+08 | F85: 100 | G85: 43.348732 | H85: 4.6528961 | I85: 49.332071 | J85: =IF($A85=J$2,1,0) -> 0 | K85: =IF($A85=K$2,1,0) -> 0 | L85: =IF($A85=L$2,1,0) -> 0 | M85: =IF($A85=M$2,1,0) -> 0 | N85: =IF($A85=N$2,1,0) -> 1 | O85: =IF($A85=O$2,1,0) -> 0 | P85: =IF($A85=P$2,1,0) -> 0 | Q85: =IF($A85=Q$2,1,0) -> 0 | ... BZ85: =IF($A85=BZ$2,1,0) -> 0
A86: Atlas Private Equity | B86: Investment & Asset Management | C86: 2.5563924e+08 | D86: =C86-E86 -> 96636509 | E86: 1.5900273e+08 | F86: 100 | G86: 0.42071627 | H86: 4.2517593 | I86: 51.226792 | J86: =IF($A86=J$2,1,0) -> 0 | K86: =IF($A86=K$2,1,0) -> 0 | L86: =IF($A86=L$2,1,0) -> 0 | M86: =IF($A86=M$2,1,0) -> 0 | N86: =IF($A86=N$2,1,0) -> 1 | O86: =IF($A86=O$2,1,0) -> 0 | P86: =IF($A86=P$2,1,0) -> 0 | Q86: =IF($A86=Q$2,1,0) -> 0 | ... BZ86: =IF($A86=BZ$2,1,0) -> 0
A87: Atlas Private Equity | B87: Investment & Asset Management | C87: 2.5437548e+08 | D87: 11104983 | E87: =C87-D87 -> 2.432705e+08 | F87: 100 | G87: 41.892602 | H87: 6.1549877 | I87: 52.87945 | J87: =IF($A87=J$2,1,0) -> 0 | K87: =IF($A87=K$2,1,0) -> 0 | L87: =IF($A87=L$2,1,0) -> 0 | M87: =IF($A87=M$2,1,0) -> 0 | N87: =IF($A87=N$2,1,0) -> 1 | O87: =IF($A87=O$2,1,0) -> 0 | P87: =IF($A87=P$2,1,0) -> 0 | Q87: =IF($A87=Q$2,1,0) -> 0 | ... BZ87: =IF($A87=BZ$2,1,0) -> 0
A88: Atlas Private Equity | B88: Investment & Asset Management | C88: 2.3086484e+08 | D88: 12414017 | E88: =C88-D88 -> 2.1845083e+08 | F88: 65.285086 | G88: 40.620712 | H88: 9.0144823 | I88: 54.896236 | J88: =IF($A88=J$2,1,0) -> 0 | K88: =IF($A88=K$2,1,0) -> 0 | L88: =IF($A88=L$2,1,0) -> 0 | M88: =IF($A88=M$2,1,0) -> 0 | N88: =IF($A88=N$2,1,0) -> 1 | O88: =IF($A88=O$2,1,0) -> 0 | P88: =IF($A88=P$2,1,0) -> 0 | Q88: =IF($A88=Q$2,1,0) -> 0 | ... BZ88: =IF($A88=BZ$2,1,0) -> 0
A89: Atlas Private Equity | B89: Investment & Asset Management | C89: 2.4273256e+08 | D89: 11726161 | E89: =C89-D89 -> 2.310064e+08 | F89: 76.605317 | G89: 48.18153 | H89: 7.6232692 | I89: 55.0633 | J89: =IF($A89=J$2,1,0) -> 0 | K89: =IF($A89=K$2,1,0) -> 0 | L89: =IF($A89=L$2,1,0) -> 0 | M89: =IF($A89=M$2,1,0) -> 0 | N89: =IF($A89=N$2,1,0) -> 1 | O89: =IF($A89=O$2,1,0) -> 0 | P89: =IF($A89=P$2,1,0) -> 0 | Q89: =IF($A89=Q$2,1,0) -> 0 | ... BZ89: =IF($A89=BZ$2,1,0) -> 0
A90: Atlas Private Equity | B90: Investment & Asset Management | C90: 2.6047167e+08 | D90: 13391307 | E90: =C90-D90 -> 2.4708036e+08 | F90: 48.453164 | G90: 0.37380714 | H90: 7.8678407 | I90: 55.943931 | J90: =IF($A90=J$2,1,0) -> 0 | K90: =IF($A90=K$2,1,0) -> 0 | L90: =IF($A90=L$2,1,0) -> 0 | M90: =IF($A90=M$2,1,0) -> 0 | N90: =IF($A90=N$2,1,0) -> 1 | O90: =IF($A90=O$2,1,0) -> 0 | P90: =IF($A90=P$2,1,0) -> 0 | Q90: =IF($A90=Q$2,1,0) -> 0 | ... BZ90: =IF($A90=BZ$2,1,0) -> 0
A91: Atlas Private Equity | B91: Investment & Asset Management | C91: 2.5402867e+08 | D91: 13370511 | E91: =C91-D91 -> 2.4065816e+08 | F91: 57.472288 | G91: 44.974704 | H91: 732.90586 | I91: 57.298855 | J91: =IF($A91=J$2,1,0) -> 0 | K91: =IF($A91=K$2,1,0) -> 0 | L91: =IF($A91=L$2,1,0) -> 0 | M91: =IF($A91=M$2,1,0) -> 0 | N91: =IF($A91=N$2,1,0) -> 1 | O91: =IF($A91=O$2,1,0) -> 0 | P91: =IF($A91=P$2,1,0) -> 0 | Q91: =IF($A91=Q$2,1,0) -> 0 | ... BZ91: =IF($A91=BZ$2,1,0) -> 0
A92: Atlas Private Equity | B92: Investment & Asset Management | C92: 2.2891803e+08 | D92: 13440090 | E92: =C92-D92 -> 2.1547794e+08 | F92: 42.568851 | G92: 37.753019 | H92: 3.2662228 | I92: 58.450372 | J92: =IF($A92=J$2,1,0) -> 0 | K92: =IF($A92=K$2,1,0) -> 0 | L92: =IF($A92=L$2,1,0) -> 0 | M92: =IF($A92=M$2,1,0) -> 0 | N92: =IF($A92=N$2,1,0) -> 1 | O92: =IF($A92=O$2,1,0) -> 0 | P92: =IF($A92=P$2,1,0) -> 0 | Q92: =IF($A92=Q$2,1,0) -> 0 | ... BZ92: =IF($A92=BZ$2,1,0) -> 0
A93: Atlas Private Equity | B93: Investment & Asset Management | C93: 2.6336125e+08 | D93: =C93-E93 -> 98247650 | E93: 1.651136e+08 | F93: 80.635444 | G93: 49.427572 | H93: 3.5027028 | I93: 60.76184 | J93: =IF($A93=J$2,1,0) -> 0 | K93: =IF($A93=K$2,1,0) -> 0 | L93: =IF($A93=L$2,1,0) -> 0 | M93: =IF($A93=M$2,1,0) -> 0 | N93: =IF($A93=N$2,1,0) -> 1 | O93: =IF($A93=O$2,1,0) -> 0 | P93: =IF($A93=P$2,1,0) -> 0 | Q93: =IF($A93=Q$2,1,0) -> 0 | ... BZ93: =IF($A93=BZ$2,1,0) -> 0
A94: Atlas Private Equity | B94: Investment & Asset Management | C94: 2.2187339e+08 | D94: 12627680 | E94: =C94-D94 -> 2.0924571e+08 | F94: 66.297472 | G94: 49.442897 | H94: 9.4614238 | I94: 62.294472 | J94: =IF($A94=J$2,1,0) -> 0 | K94: =IF($A94=K$2,1,0) -> 0 | L94: =IF($A94=L$2,1,0) -> 0 | M94: =IF($A94=M$2,1,0) -> 0 | N94: =IF($A94=N$2,1,0) -> 1 | O94: =IF($A94=O$2,1,0) -> 0 | P94: =IF($A94=P$2,1,0) -> 0 | Q94: =IF($A94=Q$2,1,0) -> 0 | ... BZ94: =IF($A94=BZ$2,1,0) -> 0
A95: Atlas Private Equity | B95: Investment & Asset Management | C95: 2.3936003e+08 | D95: =C95-E95 -> 67664315 | E95: 1.7169571e+08 | F95: 100 | G95: 49.67959 | H95: 3.8750856 | I95: 70.141742 | J95: =IF($A95=J$2,1,0) -> 0 | K95: =IF($A95=K$2,1,0) -> 0 | L95: =IF($A95=L$2,1,0) -> 0 | M95: =IF($A95=M$2,1,0) -> 0 | N95: =IF($A95=N$2,1,0) -> 1 | O95: =IF($A95=O$2,1,0) -> 0 | P95: =IF($A95=P$2,1,0) -> 0 | Q95: =IF($A95=Q$2,1,0) -> 0 | ... BZ95: =IF($A95=BZ$2,1,0) -> 0
A96: Atlas Risk Management | B96: Insurance & Risk Management | C96: 2.5054672e+08 | D96: 13537580 | E96: =C96-D96 -> 2.3700914e+08 | F96: 86.351346 | G96: 44.245304 | H96: 328.64875 | I96: 36.576832 | J96: =IF($A96=J$2,1,0) -> 0 | K96: =IF($A96=K$2,1,0) -> 0 | L96: =IF($A96=L$2,1,0) -> 0 | M96: =IF($A96=M$2,1,0) -> 0 | N96: =IF($A96=N$2,1,0) -> 0 | O96: =IF($A96=O$2,1,0) -> 1 | P96: =IF($A96=P$2,1,0) -> 0 | Q96: =IF($A96=Q$2,1,0) -> 0 | ... BZ96: =IF($A96=BZ$2,1,0) -> 0
A97: Atlas Risk Management | B97: Insurance & Risk Management | C97: 2.2683808e+08 | D97: 11301778 | E97: =C97-D97 -> 2.155363e+08 | F97: 36.901082 | G97: 44.436778 | H97: 4.7383001 | I97: 40.125629 | J97: =IF($A97=J$2,1,0) -> 0 | K97: =IF($A97=K$2,1,0) -> 0 | L97: =IF($A97=L$2,1,0) -> 0 | M97: =IF($A97=M$2,1,0) -> 0 | N97: =IF($A97=N$2,1,0) -> 0 | O97: =IF($A97=O$2,1,0) -> 1 | P97: =IF($A97=P$2,1,0) -> 0 | Q97: =IF($A97=Q$2,1,0) -> 0 | ... BZ97: =IF($A97=BZ$2,1,0) -> 0
A98: Atlas Risk Management | B98: Insurance & Risk Management | C98: 2.6692109e+08 | D98: 12910733 | E98: =C98-D98 -> 2.5401035e+08 | F98: 80.543621 | G98: 42.25597 | H98: 6.481779 | I98: 44.837836 | J98: =IF($A98=J$2,1,0) -> 0 | K98: =IF($A98=K$2,1,0) -> 0 | L98: =IF($A98=L$2,1,0) -> 0 | M98: =IF($A98=M$2,1,0) -> 0 | N98: =IF($A98=N$2,1,0) -> 0 | O98: =IF($A98=O$2,1,0) -> 1 | P98: =IF($A98=P$2,1,0) -> 0 | Q98: =IF($A98=Q$2,1,0) -> 0 | ... BZ98: =IF($A98=BZ$2,1,0) -> 0
A99: Atlas Risk Management | B99: Insurance & Risk Management | C99: 2.652193e+08 | D99: 11719459 | E99: =C99-D99 -> 2.5349984e+08 | F99: 47.731745 | G99: 0.44636523 | H99: 1.770919 | I99: 48.158676 | J99: =IF($A99=J$2,1,0) -> 0 | K99: =IF($A99=K$2,1,0) -> 0 | L99: =IF($A99=L$2,1,0) -> 0 | M99: =IF($A99=M$2,1,0) -> 0 | N99: =IF($A99=N$2,1,0) -> 0 | O99: =IF($A99=O$2,1,0) -> 1 | P99: =IF($A99=P$2,1,0) -> 0 | Q99: =IF($A99=Q$2,1,0) -> 0 | ... BZ99: =IF($A99=BZ$2,1,0) -> 0
A100: Atlas Risk Management | B100: Insurance & Risk Management | C100: 2.36924e+08 | D100: =C100-E100 -> 79590358 | E100: 1.5733364e+08 | F100: 63.290046 | G100: 42.337733 | H100: 5.8867895 | I100: 48.983088 | J100: =IF($A100=J$2,1,0) -> 0 | K100: =IF($A100=K$2,1,0) -> 0 | L100: =IF($A100=L$2,1,0) -> 0 | M100: =IF($A100=M$2,1,0) -> 0 | N100: =IF($A100=N$2,1,0) -> 0 | O100: =IF($A100=O$2,1,0) -> 1 | P100: =IF($A100=P$2,1,0) -> 0 | Q100: =IF($A100=Q$2,1,0) -> 0 | ... BZ100: =IF($A100=BZ$2,1,0) -> 0
...

Sheet Average Annual Performance
A1: Company | B1: Average of Revenue | C1: Average of Profits | D1: Average of Costs | E1: Average of Customer Satisfaction Score | F1: Average of Market Share | G1: Average of Growth Potential | H1: Average of Stock Price | I1: Customer Satifaction Ranking | J1: Reveune Ranking | K1: Profit Ranking | L1: Cost Ranking | M1: Stock Price Ranking | N1: Market Share ZScore Normalizaton | O1: Growth Potential ZScore Normailzaton | P1: BCG Group
A2: {=_xlfn.UNIQUE('Quarterly Performance'!A3:A1146)} -> Apex Capital Partners | B2: =AVERAGEIF('Quarterly Performance'!$J$3:$J$1146, 1, 'Quarterly Performance'!C$3:C$1146) -> 2.4831047e+08 | C2: =AVERAGEIF('Quarterly Performance'!$J$3:$J$1146, 1, 'Quarterly Performance'!D$3:D$1146) -> 51636714 | D2: =AVERAGEIF('Quarterly Performance'!$J$3:$J$1146, 1, 'Quarterly Performance'!E$3:E$1146) -> 1.9667376e+08 | E2: =AVERAGEIF('Quarterly Performance'!$J$3:$J$1146, 1, 'Quarterly Performance'!F$3:F$1146) -> 54.121456 | F2: =AVERAGEIF('Quarterly Performance'!$J$3:$J$1146, 1, 'Quarterly Performance'!G$3:G$1146) -> 25.753817 | G2: =AVERAGEIF('Quarterly Performance'!$J$3:$J$1146, 1, 'Quarterly Performance'!H$3:H$1146) -> 83.765363 | H2: =AVERAGEIF('Quarterly Performance'!$J$3:$J$1146, 1, 'Quarterly Performance'!I$3:I$1146) -> 44.916066 | I2: =IF(E2 <Percentiles!$E$3, "Low", IF(E2 <= Percentiles!$E$4, "Medium", "High")) -> Low | J2: =IF(B2 <Percentiles!B$3, "Low", IF(B2 <= Percentiles!B$4, "Medium", "High")) -> Medium | K2: =IF(C2 <Percentiles!C$3, "Low", IF(C2 <= Percentiles!C$4, "Medium", "High")) -> Medium | L2: =IF(D2 <Percentiles!D$3, "Low", IF(D2 <= Percentiles!D$4, "Medium", "High")) -> Medium | M2: =IF(H2 <Percentiles!$H$3, "Low", IF(H2 <= Percentiles!$H$4, "Medium", "High")) -> Low | N2: =(F2 - AVERAGE(F$2:$F$70)) / _xlfn.STDEV.S(F$2:F$70) -> -1.1157592 | O2: =(G2 - AVERAGE($G$2:G$70)) / _xlfn.STDEV.S(G$2:G$70) -> -0.41662273 | P2: =IF(AND(N2>=0, O2>=0), "Star", IF(AND(N2>=0, O2<0), "Cash Cow", IF(AND(N2<0, O2>=0), "Question Mark", "Dog"))) -> Dog
A3: Ascend Capital Advisors | B3: =AVERAGEIF('Quarterly Performance'!$K$3:$K$1146, 1, 'Quarterly Performance'!C$3:C$1146) -> 2.4587496e+08 | C3: =AVERAGEIF('Quarterly Performance'!$K$3:$K$1146, 1, 'Quarterly Performance'!D$3:D$1146) -> 56676714 | D3: =AVERAGEIF('Quarterly Performance'!$K$3:$K$1146, 1, 'Quarterly Performance'!E$3:E$1146) -> 1.8919825e+08 | E3: =AVERAGEIF('Quarterly Performance'!$K$3:$K$1146, 1, 'Quarterly Performance'!F$3:F$1146) -> 67.0998 | F3: =AVERAGEIF('Quarterly Performance'!$K$3:$K$1146, 1, 'Quarterly Performance'!G$3:G$1146) -> 37.959194 | G3: =AVERAGEIF('Quarterly Performance'!$K$3:$K$1146, 1, 'Quarterly Performance'!H$3:H$1146) -> 86.251134 | H3: =AVERAGEIF('Quarterly Performance'!$K$3:$K$1146, 1, 'Quarterly Performance'!I$3:I$1146) -> 47.516792 | I3: =IF(E3 <Percentiles!$E$3, "Low", IF(E3 <= Percentiles!$E$4, "Medium", "High")) -> High | J3: =IF(B3 <Percentiles!B$3, "Low", IF(B3 <= Percentiles!B$4, "Medium", "High")) -> Low | K3: =IF(C3 <Percentiles!C$3, "Low", IF(C3 <= Percentiles!C$4, "Medium", "High")) -> High | L3: =IF(D3 <Percentiles!D$3, "Low", IF(D3 <= Percentiles!D$4, "Medium", "High")) -> Low | M3: =IF(H3 <Percentiles!$H$3, "Low", IF(H3 <= Percentiles!$H$4, "Medium", "High")) -> Low | N3: =(F3 - AVERAGE(F$2:$F$70)) / _xlfn.STDEV.S(F$2:F$70) -> 1.0022244 | O3: =(G3 - AVERAGE($G$2:G$70)) / _xlfn.STDEV.S(G$2:G$70) -> -0.37274038 | P3: =IF(AND(N3>=0, O3>=0), "Star", IF(AND(N3>=0, O3<0), "Cash Cow", IF(AND(N3<0, O3>=0), "Question Mark", "Dog"))) -> Cash Cow
A4: Atlas Blockchain Services | B4: =AVERAGEIF('Quarterly Performance'!L$3:L$1146, 1, 'Quarterly Performance'!C$3:C$1146) -> 2.4893945e+08 | C4: =AVERAGEIF('Quarterly Performance'!$L$3:$L$1146, 1, 'Quarterly Performance'!D$3:D$1146) -> 46844787 | D4: =AVERAGEIF('Quarterly Performance'!$L$3:$L$1146, 1, 'Quarterly Performance'!E$3:E$1146) -> 2.0209466e+08 | E4: =AVERAGEIF('Quarterly Performance'!$L$3:$L$1146, 1, 'Quarterly Performance'!F$3:F$1146) -> 69.533955 | F4: =AVERAGEIF('Quarterly Performance'!$L$3:$L$1146, 1, 'Quarterly Performance'!G$3:G$1146) -> 28.366439 | G4: =AVERAGEIF('Quarterly Performance'!$L$3:$L$1146, 1, 'Quarterly Performance'!H$3:H$1146) -> 163.83277 | H4: =AVERAGEIF('Quarterly Performance'!$L$3:$L$1146, 1, 'Quarterly Performance'!I$3:I$1146) -> 52.236415 | I4: =IF(E4 <Percentiles!$E$3, "Low", IF(E4 <= Percentiles!$E$4, "Medium", "High")) -> High | J4: =IF(B4 <Percentiles!B$3, "Low", IF(B4 <= Percentiles!B$4, "Medium", "High")) -> Medium | K4: =IF(C4 <Percentiles!C$3, "Low", IF(C4 <= Percentiles!C$4, "Medium", "High")) -> Medium | L4: =IF(D4 <Percentiles!D$3, "Low", IF(D4 <= Percentiles!D$4, "Medium", "High")) -> Medium | M4: =IF(H4 <Percentiles!$H$3, "Low", IF(H4 <= Percentiles!$H$4, "Medium", "High")) -> Medium | N4: =(F4 - AVERAGE(F$2:$F$70)) / _xlfn.STDEV.S(F$2:F$70) -> -0.66239433 | O4: =(G4 - AVERAGE($G$2:G$70)) / _xlfn.STDEV.S(G$2:G$70) -> 0.99684076 | P4: =IF(AND(N4>=0, O4>=0), "Star", IF(AND(N4>=0, O4<0), "Cash Cow", IF(AND(N4<0, O4>=0), "Question Mark", "Dog"))) -> Question Mark
A5: Atlas Community Bank | B5: =AVERAGEIF('Quarterly Performance'!M$3:M$1146, 1, 'Quarterly Performance'!C$3:C$1146) -> 2.5157565e+08 | C5: =AVERAGEIF('Quarterly Performance'!$M$3:$M$1146, 1, 'Quarterly Performance'!D$3:D$1146) -> 46237848 | D5: =AVERAGEIF('Quarterly Performance'!$M$3:$M$1146, 1, 'Quarterly Performance'!E$3:E$1146) -> 2.053378e+08 | E5: =AVERAGEIF('Quarterly Performance'!$M$3:$M$1146, 1, 'Quarterly Performance'!F$3:F$1146) -> 55.280781 | F5: =AVERAGEIF('Quarterly Performance'!$M$3:$M$1146, 1, 'Quarterly Performance'!G$3:G$1146) -> 27.628856 | G5: =AVERAGEIF('Quarterly Performance'!$M$3:$M$1146, 1, 'Quarterly Performance'!H$3:H$1146) -> 4.8065792 | H5: =AVERAGEIF('Quarterly Performance'!$M$3:$M$1146, 1, 'Quarterly Performance'!I$3:I$1146) -> 52.05988 | I5: =IF(E5 <Percentiles!$E$3, "Low", IF(E5 <= Percentiles!$E$4, "Medium", "High")) -> Low | J5: =IF(B5 <Percentiles!B$3, "Low", IF(B5 <= Percentiles!B$4, "Medium", "High")) -> Medium | K5: =IF(C5 <Percentiles!C$3, "Low", IF(C5 <= Percentiles!C$4, "Medium", "High")) -> Medium | L5: =IF(D5 <Percentiles!D$3, "Low", IF(D5 <= Percentiles!D$4, "Medium", "High")) -> Medium | M5: =IF(H5 <Percentiles!$H$3, "Low", IF(H5 <= Percentiles!$H$4, "Medium", "High")) -> Medium | N5: =(F5 - AVERAGE(F$2:$F$70)) / _xlfn.STDEV.S(F$2:F$70) -> -0.79038605 | O5: =(G5 - AVERAGE($G$2:G$70)) / _xlfn.STDEV.S(G$2:G$70) -> -1.8105152 | P5: =IF(AND(N5>=0, O5>=0), "Star", IF(AND(N5>=0, O5<0), "Cash Cow", IF(AND(N5<0, O5>=0), "Question Mark", "Dog"))) -> Dog
A6: Atlas Private Equity | B6: =AVERAGEIF('Quarterly Performance'!N$3:N$1146, 1, 'Quarterly Performance'!C$3:C$1146) -> 2.4696762e+08 | C6: =AVERAGEIF('Quarterly Performance'!$N$3:$N$1146, 1, 'Quarterly Performance'!D$3:D$1146) -> 41734835 | D6: =AVERAGEIF('Quarterly Performance'!$N$3:$N$1146, 1, 'Quarterly Performance'!E$3:E$1146) -> 2.0523278e+08 | E6: =AVERAGEIF('Quarterly Performance'!$N$3:$N$1146, 1, 'Quarterly Performance'!F$3:F$1146) -> 60.512612 | F6: =AVERAGEIF('Quarterly Performance'!$N$3:$N$1146, 1, 'Quarterly Performance'!G$3:G$1146) -> 39.852829 | G6: =AVERAGEIF('Quarterly Performance'!$N$3:$N$1146, 1, 'Quarterly Performance'!H$3:H$1146) -> 145.36089 | H6: =AVERAGEIF('Quarterly Performance'!$N$3:$N$1146, 1, 'Quarterly Performance'!I$3:I$1146) -> 52.683721 | I6: =IF(E6 <Percentiles!$E$3, "Low", IF(E6 <= Percentiles!$E$4, "Medium", "High")) -> Medium | J6: =IF(B6 <Percentiles!B$3, "Low", IF(B6 <= Percentiles!B$4, "Medium", "High")) -> Medium | K6: =IF(C6 <Percentiles!C$3, "Low", IF(C6 <= Percentiles!C$4, "Medium", "High")) -> Medium | L6: =IF(D6 <Percentiles!D$3, "Low", IF(D6 <= Percentiles!D$4, "Medium", "High")) -> Medium | M6: =IF(H6 <Percentiles!$H$3, "Low", IF(H6 <= Percentiles!$H$4, "Medium", "High")) -> High | N6: =(F6 - AVERAGE(F$2:$F$70)) / _xlfn.STDEV.S(F$2:F$70) -> 1.3308246 | O6: =(G6 - AVERAGE($G$2:G$70)) / _xlfn.STDEV.S(G$2:G$70) -> 0.67074891 | P6: =IF(AND(N6>=0, O6>=0), "Star", IF(AND(N6>=0, O6<0), "Cash Cow", IF(AND(N6<0, O6>=0), "Question Mark", "Dog"))) -> Star
A7: Atlas Risk Management | B7: =AVERAGEIF('Quarterly Performance'!O$3:O$1146, 1, 'Quarterly Performance'!C$3:C$1146) -> 2.5049353e+08 | C7: =AVERAGEIF('Quarterly Performance'!$O$3:$O$1146, 1, 'Quarterly Performance'!D$3:D$1146) -> 46244964 | D7: =AVERAGEIF('Quarterly Performance'!$O$3:$O$1146, 1, 'Quarterly Performance'!E$3:E$1146) -> 2.0424857e+08 | E7: =AVERAGEIF('Quarterly Performance'!$O$3:$O$1146, 1, 'Quarterly Performance'!F$3:F$1146) -> 61.525078 | F7: =AVERAGEIF('Quarterly Performance'!$O$3:$O$1146, 1, 'Quarterly Performance'!G$3:G$1146) -> 36.544603 | G7: =AVERAGEIF('Quarterly Performance'!$O$3:$O$1146, 1, 'Quarterly Performance'!H$3:H$1146) -> 24.092841 | H7: =AVERAGEIF('Quarterly Performance'!$O$3:$O$1146, 1, 'Quarterly Performance'!I$3:I$1146) -> 52.578622 | I7: =IF(E7 <Percentiles!$E$3, "Low", IF(E7 <= Percentiles!$E$4, "Medium", "High")) -> Medium | J7: =IF(B7 <Percentiles!B$3, "Low", IF(B7 <= Percentiles!B$4, "Medium", "High")) -> Medium | K7: =IF(C7 <Percentiles!C$3, "Low", IF(C7 <= Percentiles!C$4, "Medium", "High")) -> Medium | L7: =IF(D7 <Percentiles!D$3, "Low", IF(D7 <= Percentiles!D$4, "Medium", "High")) -> Medium | M7: =IF(H7 <Percentiles!$H$3, "Low", IF(H7 <= Percentiles!$H$4, "Medium", "High")) -> High | N7: =(F7 - AVERAGE(F$2:$F$70)) / _xlfn.STDEV.S(F$2:F$70) -> 0.75675233 | O7: =(G7 - AVERAGE($G$2:G$70)) / _xlfn.STDEV.S(G$2:G$70) -> -1.4700468 | P7: =IF(AND(N7>=0, O7>=0), "Star", IF(AND(N7>=0, O7<0), "Cash Cow", IF(AND(N7<0, O7>=0), "Question Mark", "Dog"))) -> Cash Cow
A8: BlueSky Banking Corp. | B8: =AVERAGEIF('Quarterly Performance'!P$3:P$1146, 1, 'Quarterly Performance'!C$3:C$1146) -> 2.52725e+08 | C8: =AVERAGEIF('Quarterly Performance'!$P$3:$P$1146, 1, 'Quarterly Performance'!D$3:D$1146) -> 55556578 | D8: =AVERAGEIF('Quarterly Performance'!$P$3:$P$1146, 1, 'Quarterly Performance'!E$3:E$1146) -> 1.9716842e+08 | E8: =AVERAGEIF('Quarterly Performance'!$P$3:$P$1146, 1, 'Quarterly Performance'!F$3:F$1146) -> 58.951712 | F8: =AVERAGEIF('Quarterly Performance'!$P$3:$P$1146, 1, 'Quarterly Performance'!G$3:G$1146) -> 31.214133 | G8: =AVERAGEIF('Quarterly Performance'!$P$3:$P$1146, 1, 'Quarterly Performance'!H$3:H$1146) -> 100.85232 | H8: =AVERAGEIF('Quarterly Performance'!$P$3:$P$1146, 1, 'Quarterly Performance'!I$3:I$1146) -> 53.070695 | I8: =IF(E8 <Percentiles!$E$3, "Low", IF(E8 <= Percentiles!$E$4, "Medium", "High")) -> Medium | J8: =IF(B8 <Percentiles!B$3, "Low", IF(B8 <= Percentiles!B$4, "Medium", "High")) -> High | K8: =IF(C8 <Percentiles!C$3, "Low", IF(C8 <= Percentiles!C$4, "Medium", "High")) -> High | L8: =IF(D8 <Percentiles!D$3, "Low", IF(D8 <= Percentiles!D$4, "Medium", "High")) -> Medium | M8: =IF(H8 <Percentiles!$H$3, "Low", IF(H8 <= Percentiles!$H$4, "Medium", "High")) -> High | N8: =(F8 - AVERAGE(F$2:$F$70)) / _xlfn.STDEV.S(F$2:F$70) -> -0.16823742 | O8: =(G8 - AVERAGE($G$2:G$70)) / _xlfn.STDEV.S(G$2:G$70) -> -0.11497955 | P8: =IF(AND(N8>=0, O8>=0), "Star", IF(AND(N8>=0, O8<0), "Cash Cow", IF(AND(N8<0, O8>=0), "Question Mark", "Dog"))) -> Dog
A9: BlueSky Mobile Payments | B9: =AVERAGEIF('Quarterly Performance'!Q$3:Q$1146, 1, 'Quarterly Performance'!C$3:C$1146) -> 2.4406333e+08 | C9: =AVERAGEIF('Quarterly Performance'!$Q$3:$Q$1146, 1, 'Quarterly Performance'!D$3:D$1146) -> 47120286 | D9: =AVERAGEIF('Quarterly Performance'!$Q$3:$Q$1146, 1, 'Quarterly Performance'!E$3:E$1146) -> 1.9694305e+08 | E9: =AVERAGEIF('Quarterly Performance'!$Q$3:$Q$1146, 1, 'Quarterly Performance'!F$3:F$1146) -> 63.472889 | F9: =AVERAGEIF('Quarterly Performance'!$Q$3:$Q$1146, 1, 'Quarterly Performance'!G$3:G$1146) -> 24.630623 | G9: =AVERAGEIF('Quarterly Performance'!$Q$3:$Q$1146, 1, 'Quarterly Performance'!H$3:H$1146) -> 158.81829 | H9: =AVERAGEIF('Quarterly Performance'!$Q$3:$Q$1146, 1, 'Quarterly Performance'!I$3:I$1146) -> 52.835914 | I9: =IF(E9 <Percentiles!$E$3, "Low", IF(E9 <= Percentiles!$E$4, "Medium", "High")) -> Medium | J9: =IF(B9 <Percentiles!B$3, "Low", IF(B9 <= Percentiles!B$4, "Medium", "High")) -> Low | K9: =IF(C9 <Percentiles!C$3, "Low", IF(C9 <= Percentiles!C$4, "Medium", "High")) -> Medium | L9: =IF(D9 <Percentiles!D$3, "Low", IF(D9 <= Percentiles!D$4, "Medium", "High")) -> Medium | M9: =IF(H9 <Percentiles!$H$3, "Low", IF(H9 <= Percentiles!$H$4, "Medium", "High")) -> High | N9: =(F9 - AVERAGE(F$2:$F$70)) / _xlfn.STDEV.S(F$2:F$70) -> -1.3106656 | O9: =(G9 - AVERAGE($G$2:G$70)) / _xlfn.STDEV.S(G$2:G$70) -> 0.90831797 | P9: =IF(AND(N9>=0, O9>=0), "Star", IF(AND(N9>=0, O9<0), "Cash Cow", IF(AND(N9<0, O9>=0), "Question Mark", "Dog"))) -> Question Mark
A10: BlueSky Risk Solutions | B10: =AVERAGEIF('Quarterly Performance'!R$3:R$1146, 1, 'Quarterly Performance'!C$3:C$1146) -> 2.5891494e+08 | C10: =AVERAGEIF('Quarterly Performance'!$R$3:$R$1146, 1, 'Quarterly Performance'!D$3:D$1146) -> 43242243 | D10: =AVERAGEIF('Quarterly Performance'!$R$3:$R$1146, 1, 'Quarterly Performance'!E$3:E$1146) -> 2.1567269e+08 | E10: =AVERAGEIF('Quarterly Performance'!$R$3:$R$1146, 1, 'Quarterly Performance'!F$3:F$1146) -> 56.004864 | F10: =AVERAGEIF('Quarterly Performance'!$R$3:$R$1146, 1, 'Quarterly Performance'!G$3:G$1146) -> 30.810871 | G10: =AVERAGEIF('Quarterly Performance'!$R$3:$R$1146, 1, 'Quarterly Performance'!H$3:H$1146) -> 156.96239 | H10: =AVERAGEIF('Quarterly Performance'!$R$3:$R$1146, 1, 'Quarterly Performance'!I$3:I$1146) -> 54.117774 | I10: =IF(E10 <Percentiles!$E$3, "Low", IF(E10 <= Percentiles!$E$4, "Medium", "High")) -> Medium | J10: =IF(B10 <Percentiles!B$3, "Low", IF(B10 <= Percentiles!B$4, "Medium", "High")) -> High | K10: =IF(C10 <Percentiles!C$3, "Low", IF(C10 <= Percentiles!C$4, "Medium", "High")) -> Medium | L10: =IF(D10 <Percentiles!D$3, "Low", IF(D10 <= Percentiles!D$4, "Medium", "High")) -> High | M10: =IF(H10 <Percentiles!$H$3, "Low", IF(H10 <= Percentiles!$H$4, "Medium", "High")) -> High | N10: =(F10 - AVERAGE(F$2:$F$70)) / _xlfn.STDEV.S(F$2:F$70) -> -0.23821498 | O10: =(G10 - AVERAGE($G$2:G$70)) / _xlfn.STDEV.S(G$2:G$70) -> 0.87555507 | P10: =IF(AND(N10>=0, O10>=0), "Star", IF(AND(N10>=0, O10<0), "Cash Cow", IF(AND(N10<0, O10>=0), "Question Mark", "Dog"))) -> Question Mark
A11: CrestPoint Blockchain Solutions | B11: =AVERAGEIF('Quarterly Performance'!S$3:S$1146, 1, 'Quarterly Performance'!C$3:C$1146) -> 2.4843118e+08 | C11: =AVERAGEIF('Quarterly Performance'!$S$3:$S$1146, 1, 'Quarterly Performance'!D$3:D$1146) -> 55881504 | D11: =AVERAGEIF('Quarterly Performance'!$S$3:$S$1146, 1, 'Quarterly Performance'!E$3:E$1146) -> 1.9254967e+08 | E11: =AVERAGEIF('Quarterly Performance'!$S$3:$S$1146, 1, 'Quarterly Performance'!F$3:F$1146) -> 60.19932 | F11: =AVERAGEIF('Quarterly Performance'!$S$3:$S$1146, 1, 'Quarterly Performance'!G$3:G$1146) -> 27.067216 | G11: =AVERAGEIF('Quarterly Performance'!$S$3:$S$1146, 1, 'Quarterly Performance'!H$3:H$1146) -> 114.15672 | H11: =AVERAGEIF('Quarterly Performance'!$S$3:$S$1146, 1, 'Quarterly Performance'!I$3:I$1146) -> 51.189084 | I11: =IF(E11 <Percentiles!$E$3, "Low", IF(E11 <= Percentiles!$E$4, "Medium", "High")) -> Medium | J11: =IF(B11 <Percentiles!B$3, "Low", IF(B11 <= Percentiles!B$4, "Medium", "High")) -> Medium | K11: =IF(C11 <Percentiles!C$3, "Low", IF(C11 <= Percentiles!C$4, "Medium", "High")) -> High | L11: =IF(D11 <Percentiles!D$3, "Low", IF(D11 <= Percentiles!D$4, "Medium", "High")) -> Low | M11: =IF(H11 <Percentiles!$H$3, "Low", IF(H11 <= Percentiles!$H$4, "Medium", "High")) -> Medium | N11: =(F11 - AVERAGE(F$2:$F$70)) / _xlfn.STDEV.S(F$2:F$70) -> -0.88784678 | O11: =(G11 - AVERAGE($G$2:G$70)) / _xlfn.STDEV.S(G$2:G$70) -> 0.11988857 | P11: =IF(AND(N11>=0, O11>=0), "Star", IF(AND(N11>=0, O11<0), "Cash Cow", IF(AND(N11<0, O11>=0), "Question Mark", "Dog"))) -> Question Mark
A12: CrestPoint Capital | B12: =AVERAGEIF('Quarterly Performance'!T$3:T$1146, 1, 'Quarterly Performance'!C$3:C$1146) -> 2.5510177e+08 | C12: =AVERAGEIF('Quarterly Performance'!$T$3:$T$1146, 1, 'Quarterly Performance'!D$3:D$1146) -> 56491063 | D12: =AVERAGEIF('Quarterly Performance'!$T$3:$T$1146, 1, 'Quarterly Performance'!E$3:E$1146) -> 1.9861071e+08 | E12: =AVERAGEIF('Quarterly Performance'!$T$3:$T$1146, 1, 'Quarterly Performance'!F$3:F$1146) -> 55.260188 | F12: =AVERAGEIF('Quarterly Performance'!$T$3:$T$1146, 1, 'Quarterly Performance'!G$3:G$1146) -> 28.209216 | G12: =AVERAGEIF('Quarterly Performance'!$T$3:$T$1146, 1, 'Quarterly Performance'!H$3:H$1146) -> 83.223643 | H12: =AVERAGEIF('Quarterly Performance'!$T$3:$T$1146, 1, 'Quarterly Performance'!I$3:I$1146) -> 51.978358 | I12: =IF(E12 <Percentiles!$E$3, "Low", IF(E12 <= Percentiles!$E$4, "Medium", "High")) -> Low | J12: =IF(B12 <Percentiles!B$3, "Low", IF(B12 <= Percentiles!B$4, "Medium", "High")) -> High | K12: =IF(C12 <Percentiles!C$3, "Low", IF(C12 <= Percentiles!C$4, "Medium", "High")) -> High | L12: =IF(D12 <Percentiles!D$3, "Low", IF(D12 <= Percentiles!D$4, "Medium", "High")) -> Medium | M12: =IF(H12 <Percentiles!$H$3, "Low", IF(H12 <= Percentiles!$H$4, "Medium", "High")) -> Medium | N12: =(F12 - AVERAGE(F$2:$F$70)) / _xlfn.STDEV.S(F$2:F$70) -> -0.68967698 | O12: =(G12 - AVERAGE($G$2:G$70)) / _xlfn.STDEV.S(G$2:G$70) -> -0.42618595 | P12: =IF(AND(N12>=0, O12>=0), "Star", IF(AND(N12>=0, O12<0), "Cash Cow", IF(AND(N12<0, O12>=0), "Question Mark", "Dog"))) -> Dog
A13: CryptoBridge Systems | B13: =AVERAGEIF('Quarterly Performance'!U$3:U$1146, 1, 'Quarterly Performance'!C$3:C$1146) -> 2.5165992e+08 | C13: =AVERAGEIF('Quarterly Performance'!$U$3:$U$1146, 1, 'Quarterly Performance'!D$3:D$1146) -> 48156530 | D13: =AVERAGEIF('Quarterly Performance'!$U$3:$U$1146, 1, 'Quarterly Performance'!E$3:E$1146) -> 2.0350339e+08 | E13: =AVERAGEIF('Quarterly Performance'!$U$3:$U$1146, 1, 'Quarterly Performance'!F$3:F$1146) -> 68.115829 | F13: =AVERAGEIF('Quarterly Performance'!$U$3:$U$1146, 1, 'Quarterly Performance'!G$3:G$1146) -> 35.884402 | G13: =AVERAGEIF('Quarterly Performance'!$U$3:$U$1146, 1, 'Quarterly Performance'!H$3:H$1146) -> 104.39582 | H13: =AVERAGEIF('Quarterly Performance'!$U$3:$U$1146, 1, 'Quarterly Performance'!I$3:I$1146) -> 53.165772 | I13: =IF(E13 <Percentiles!$E$3, "Low", IF(E13 <= Percentiles!$E$4, "Medium", "High")) -> High | J13: =IF(B13 <Percentiles!B$3, "Low", IF(B13 <= Percentiles!B$4, "Medium", "High")) -> Medium | K13: =IF(C13 <Percentiles!C$3, "Low", IF(C13 <= Percentiles!C$4, "Medium", "High")) -> Medium | L13: =IF(D13 <Percentiles!D$3, "Low", IF(D13 <= Percentiles!D$4, "Medium", "High")) -> Medium | M13: =IF(H13 <Percentiles!$H$3, "Low", IF(H13 <= Percentiles!$H$4, "Medium", "High")) -> High | N13: =(F13 - AVERAGE(F$2:$F$70)) / _xlfn.STDEV.S(F$2:F$70) -> 0.64218841 | O13: =(G13 - AVERAGE($G$2:G$70)) / _xlfn.STDEV.S(G$2:G$70) -> -0.05242465 | P13: =IF(AND(N13>=0, O13>=0), "Star", IF(AND(N13>=0, O13<0), "Cash Cow", IF(AND(N13<0, O13>=0), "Question Mark", "Dog"))) -> Cash Cow
A14: Evergreen Coverage Co. | B14: =AVERAGEIF('Quarterly Performance'!V$3:V$1146, 1, 'Quarterly Performance'!C$3:C$1146) -> 2.4663916e+08 | C14: =AVERAGEIF('Quarterly Performance'!$V$3:$V$1146, 1, 'Quarterly Performance'!D$3:D$1146) -> 55656821 | D14: =AVERAGEIF('Quarterly Performance'!$V$3:$V$1146, 1, 'Quarterly Performance'!E$3:E$1146) -> 1.9098234e+08 | E14: =AVERAGEIF('Quarterly Performance'!$V$3:$V$1146, 1, 'Quarterly Performance'!F$3:F$1146) -> 59.874227 | F14: =AVERAGEIF('Quarterly Performance'!$V$3:$V$1146, 1, 'Quarterly Performance'!G$3:G$1146) -> 27.261187 | G14: =AVERAGEIF('Quarterly Performance'!$V$3:$V$1146, 1, 'Quarterly Performance'!H$3:H$1146) -> 224.93924 | H14: =AVERAGEIF('Quarterly Performance'!$V$3:$V$1146, 1, 'Quarterly Performance'!I$3:I$1146) -> 49.114182 | I14: =IF(E14 <Percentiles!$E$3, "Low", IF(E14 <= Percentiles!$E$4, "Medium", "High")) -> Medium | J14: =IF(B14 <Percentiles!B$3, "Low", IF(B14 <= Percentiles!B$4, "Medium", "High")) -> Medium | K14: =IF(C14 <Percentiles!C$3, "Low", IF(C14 <= Percentiles!C$4, "Medium", "High")) -> High | L14: =IF(D14 <Percentiles!D$3, "Low", IF(D14 <= Percentiles!D$4, "Medium", "High")) -> Low | M14: =IF(H14 <Percentiles!$H$3, "Low", IF(H14 <= Percentiles!$H$4, "Medium", "High")) -> Medium | N14: =(F14 - AVERAGE(F$2:$F$70)) / _xlfn.STDEV.S(F$2:F$70) -> -0.85418727 | O14: =(G14 - AVERAGE($G$2:G$70)) / _xlfn.STDEV.S(G$2:G$70) -> 2.0755788 | P14: =IF(AND(N14>=0, O14>=0), "Star", IF(AND(N14>=0, O14<0), "Cash Cow", IF(AND(N14<0, O14>=0), "Question Mark", "Dog"))) -> Question Mark
A15: Evergreen Depository Services | B15: =AVERAGEIF('Quarterly Performance'!W$3:W$1146, 1, 'Quarterly Performance'!C$3:C$1146) -> 2.4507366e+08 | C15: =AVERAGEIF('Quarterly Performance'!$W$3:$W$1146, 1, 'Quarterly Performance'!D$3:D$1146) -> 40612044 | D15: =AVERAGEIF('Quarterly Performance'!$W$3:$W$1146, 1, 'Quarterly Performance'!E$3:E$1146) -> 2.0446162e+08 | E15: =AVERAGEIF('Quarterly Performance'!$W$3:$W$1146, 1, 'Quarterly Performance'!F$3:F$1146) -> 55.901821 | F15: =AVERAGEIF('Quarterly Performance'!$W$3:$W$1146, 1, 'Quarterly Performance'!G$3:G$1146) -> 34.889367 | G15: =AVERAGEIF('Quarterly Performance'!$W$3:$W$1146, 1, 'Quarterly Performance'!H$3:H$1146) -> 91.224128 | H15: =AVERAGEIF('Quarterly Performance'!$W$3:$W$1146, 1, 'Quarterly Performance'!I$3:I$1146) -> 48.879208 | I15: =IF(E15 <Percentiles!$E$3, "Low", IF(E15 <= Percentiles!$E$4, "Medium", "High")) -> Medium | J15: =IF(B15 <Percentiles!B$3, "Low", IF(B15 <= Percentiles!B$4, "Medium", "High")) -> Low | K15: =IF(C15 <Percentiles!C$3, "Low", IF(C15 <= Percentiles!C$4, "Medium", "High")) -> Low | L15: =IF(D15 <Percentiles!D$3, "Low", IF(D15 <= Percentiles!D$4, "Medium", "High")) -> Medium | M15: =IF(H15 <Percentiles!$H$3, "Low", IF(H15 <= Percentiles!$H$4, "Medium", "High")) -> Medium | N15: =(F15 - AVERAGE(F$2:$F$70)) / _xlfn.STDEV.S(F$2:F$70) -> 0.46952129 | O15: =(G15 - AVERAGE($G$2:G$70)) / _xlfn.STDEV.S(G$2:G$70) -> -0.28495003 | P15: =IF(AND(N15>=0, O15>=0), "Star", IF(AND(N15>=0, O15<0), "Cash Cow", IF(AND(N15<0, O15>=0), "Question Mark", "Dog"))) -> Cash Cow
A16: Evergreen Equity Group | B16: =AVERAGEIF('Quarterly Performance'!X$3:X$1146, 1, 'Quarterly Performance'!C$3:C$1146) -> 2.5820677e+08 | C16: =AVERAGEIF('Quarterly Performance'!$X$3:$X$1146, 1, 'Quarterly Performance'!D$3:D$1146) -> 38149610 | D16: =AVERAGEIF('Quarterly Performance'!$X$3:$X$1146, 1, 'Quarterly Performance'!E$3:E$1146) -> 2.2005716e+08 | E16: =AVERAGEIF('Quarterly Performance'!$X$3:$X$1146, 1, 'Quarterly Performance'!F$3:F$1146) -> 60.245896 | F16: =AVERAGEIF('Quarterly Performance'!$X$3:$X$1146, 1, 'Quarterly Performance'!G$3:G$1146) -> 25.647622 | G16: =AVERAGEIF('Quarterly Performance'!$X$3:$X$1146, 1, 'Quarterly Performance'!H$3:H$1146) -> 104.18933 | H16: =AVERAGEIF('Quarterly Performance'!$X$3:$X$1146, 1, 'Quarterly Performance'!I$3:I$1146) -> 50.914046 | I16: =IF(E16 <Percentiles!$E$3, "Low", IF(E16 <= Percentiles!$E$4, "Medium", "High")) -> Medium | J16: =IF(B16 <Percentiles!B$3, "Low", IF(B16 <= Percentiles!B$4, "Medium", "High")) -> High | K16: =IF(C16 <Percentiles!C$3, "Low", IF(C16 <= Percentiles!C$4, "Medium", "High")) -> Low | L16: =IF(D16 <Percentiles!D$3, "Low", IF(D16 <= Percentiles!D$4, "Medium", "High")) -> High | M16: =IF(H16 <Percentiles!$H$3, "Low", IF(H16 <= Percentiles!$H$4, "Medium", "High")) -> Medium | N16: =(F16 - AVERAGE(F$2:$F$70)) / _xlfn.STDEV.S(F$2:F$70) -> -1.1341872 | O16: =(G16 - AVERAGE($G$2:G$70)) / _xlfn.STDEV.S(G$2:G$70) -> -0.056069961 | P16: =IF(AND(N16>=0, O16>=0), "Star", IF(AND(N16>=0, O16<0), "Cash Cow", IF(AND(N16<0, O16>=0), "Question Mark", "Dog"))) -> Dog
A17: Evergreen FinTech Group | B17: =AVERAGEIF('Quarterly Performance'!Y$3:Y$1146, 1, 'Quarterly Performance'!C$3:C$1146) -> 2.4964782e+08 | C17: =AVERAGEIF('Quarterly Performance'!$Y$3:$Y$1146, 1, 'Quarterly Performance'!D$3:D$1146) -> 50183039 | D17: =AVERAGEIF('Quarterly Performance'!$Y$3:$Y$1146, 1, 'Quarterly Performance'!E$3:E$1146) -> 1.9946478e+08 | E17: =AVERAGEIF('Quarterly Performance'!$Y$3:$Y$1146, 1, 'Quarterly Performance'!F$3:F$1146) -> 53.665232 | F17: =AVERAGEIF('Quarterly Performance'!$Y$3:$Y$1146, 1, 'Quarterly Performance'!G$3:G$1146) -> 25.462883 | G17: =AVERAGEIF('Quarterly Performance'!$Y$3:$Y$1146, 1, 'Quarterly Performance'!H$3:H$1146) -> 83.994721 | H17: =AVERAGEIF('Quarterly Performance'!$Y$3:$Y$1146, 1, 'Quarterly Performance'!I$3:I$1146) -> 49.532884 | I17: =IF(E17 <Percentiles!$E$3, "Low", IF(E17 <= Percentiles!$E$4, "Medium", "High")) -> Low | J17: =IF(B17 <Percentiles!B$3, "Low", IF(B17 <= Percentiles!B$4, "Medium", "High")) -> Medium | K17: =IF(C17 <Percentiles!C$3, "Low", IF(C17 <= Percentiles!C$4, "Medium", "High")) -> Medium | L17: =IF(D17 <Percentiles!D$3, "Low", IF(D17 <= Percentiles!D$4, "Medium", "High")) -> Medium | M17: =IF(H17 <Percentiles!$H$3, "Low", IF(H17 <= Percentiles!$H$4, "Medium", "High")) -> Medium | N17: =(F17 - AVERAGE(F$2:$F$70)) / _xlfn.STDEV.S(F$2:F$70) -> -1.1662447 | O17: =(G17 - AVERAGE($G$2:G$70)) / _xlfn.STDEV.S(G$2:G$70) -> -0.41257378 | P17: =IF(AND(N17>=0, O17>=0), "Star", IF(AND(N17>=0, O17<0), "Cash Cow", IF(AND(N17<0, O17>=0), "Question Mark", "Dog"))) -> Dog
A18: Golden Gate Depository | B18: =AVERAGEIF('Quarterly Performance'!Z$3:Z$1146, 1, 'Quarterly Performance'!C$3:C$1146) -> 2.5315191e+08 | C18: =AVERAGEIF('Quarterly Performance'!$Z$3:$Z$1146, 1, 'Quarterly Performance'!D$3:D$1146) -> 28892596 | D18: =AVERAGEIF('Quarterly Performance'!$Z$3:$Z$1146, 1, 'Quarterly Performance'!E$3:E$1146) -> 2.2425932e+08 | E18: =AVERAGEIF('Quarterly Performance'!$Z$3:$Z$1146, 1, 'Quarterly Performance'!F$3:F$1146) -> 62.333471 | F18: =AVERAGEIF('Quarterly Performance'!$Z$3:$Z$1146, 1, 'Quarterly Performance'!G$3:G$1146) -> 26.656375 | G18: =AVERAGEIF('Quarterly Performance'!$Z$3:$Z$1146, 1, 'Quarterly Performance'!H$3:H$1146) -> 131.66862 | H18: =AVERAGEIF('Quarterly Performance'!$Z$3:$Z$1146, 1, 'Quarterly Performance'!I$3:I$1146) -> 47.322868 | I18: =IF(E18 <Percentiles!$E$3, "Low", IF(E18 <= Percentiles!$E$4, "Medium", "High")) -> Medium | J18: =IF(B18 <Percentiles!B$3, "Low", IF(B18 <= Percentiles!B$4, "Medium", "High")) -> High | K18: =IF(C18 <Percentiles!C$3, "Low", IF(C18 <= Percentiles!C$4, "Medium", "High")) -> Low | L18: =IF(D18 <Percentiles!D$3, "Low", IF(D18 <= Percentiles!D$4, "Medium", "High")) -> High | M18: =IF(H18 <Percentiles!$H$3, "Low", IF(H18 <= Percentiles!$H$4, "Medium", "High")) -> Low | N18: =(F18 - AVERAGE(F$2:$F$70)) / _xlfn.STDEV.S(F$2:F$70) -> -0.95913945 | O18: =(G18 - AVERAGE($G$2:G$70)) / _xlfn.STDEV.S(G$2:G$70) -> 0.42903348 | P18: =IF(AND(N18>=0, O18>=0), "Star", IF(AND(N18>=0, O18<0), "Cash Cow", IF(AND(N18<0, O18>=0), "Question Mark", "Dog"))) -> Question Mark
A19: Golden Gate Digital Finance | B19: =AVERAGEIF('Quarterly Performance'!AA$3:AA$1146, 1, 'Quarterly Performance'!C$3:C$1146) -> 2.5041025e+08 | C19: =AVERAGEIF('Quarterly Performance'!$AA$3:$AA$1146, 1, 'Quarterly Performance'!D$3:D$1146) -> 47991137 | D19: =AVERAGEIF('Quarterly Performance'!$AA$3:$AA$1146, 1, 'Quarterly Performance'!E$3:E$1146) -> 2.0241911e+08 | E19: =AVERAGEIF('Quarterly Performance'!$AA$3:$AA$1146, 1, 'Quarterly Performance'!F$3:F$1146) -> 64.994594 | F19: =AVERAGEIF('Quarterly Performance'!$AA$3:$AA$1146, 1, 'Quarterly Performance'!G$3:G$1146) -> 44.525106 | G19: =AVERAGEIF('Quarterly Performance'!$AA$3:$AA$1146, 1, 'Quarterly Performance'!H$3:H$1146) -> 73.050206 | H19: =AVERAGEIF('Quarterly Performance'!$AA$3:$AA$1146, 1, 'Quarterly Performance'!I$3:I$1146) -> 49.877328 | I19: =IF(E19 <Percentiles!$E$3, "Low", IF(E19 <= Percentiles!$E$4, "Medium", "High")) -> High | J19: =IF(B19 <Percentiles!B$3, "Low", IF(B19 <= Percentiles!B$4, "Medium", "High")) -> Medium | K19: =IF(C19 <Percentiles!C$3, "Low", IF(C19 <= Percentiles!C$4, "Medium", "High")) -> Medium | L19: =IF(D19 <Percentiles!D$3, "Low", IF(D19 <= Percentiles!D$4, "Medium", "High")) -> Medium | M19: =IF(H19 <Percentiles!$H$3, "Low", IF(H19 <= Percentiles!$H$4, "Medium", "High")) -> Medium | N19: =(F19 - AVERAGE(F$2:$F$70)) / _xlfn.STDEV.S(F$2:F$70) -> 2.141599 | O19: =(G19 - AVERAGE($G$2:G$70)) / _xlfn.STDEV.S(G$2:G$70) -> -0.60578189 | P19: =IF(AND(N19>=0, O19>=0), "Star", IF(AND(N19>=0, O19<0), "Cash Cow", IF(AND(N19<0, O19>=0), "Question Mark", "Dog"))) -> Cash Cow
A20: Golden Gate Insurance Partners | B20: =AVERAGEIF('Quarterly Performance'!AB$3:AB$1146, 1, 'Quarterly Performance'!C$3:C$1146) -> 2.4706455e+08 | C20: =AVERAGEIF('Quarterly Performance'!$AB$3:$AB$1146, 1, 'Quarterly Performance'!D$3:D$1146) -> 37664376 | D20: =AVERAGEIF('Quarterly Performance'!$AB$3:$AB$1146, 1, 'Quarterly Performance'!E$3:E$1146) -> 2.0940017e+08 | E20: =AVERAGEIF('Quarterly Performance'!$AB$3:$AB$1146, 1, 'Quarterly Performance'!F$3:F$1146) -> 55.486538 | F20: =AVERAGEIF('Quarterly Performance'!$AB$3:$AB$1146, 1, 'Quarterly Performance'!G$3:G$1146) -> 39.606641 | G20: =AVERAGEIF('Quarterly Performance'!$AB$3:$AB$1146, 1, 'Quarterly Performance'!H$3:H$1146) -> 74.1652 | H20: =AVERAGEIF('Quarterly Performance'!$AB$3:$AB$1146, 1, 'Quarterly Performance'!I$3:I$1146) -> 47.40751 | I20: =IF(E20 <Percentiles!$E$3, "Low", IF(E20 <= Percentiles!$E$4, "Medium", "High")) -> Low | J20: =IF(B20 <Percentiles!B$3, "Low", IF(B20 <= Percentiles!B$4, "Medium", "High")) -> Medium | K20: =IF(C20 <Percentiles!C$3, "Low", IF(C20 <= Percentiles!C$4, "Medium", "High")) -> Low | L20: =IF(D20 <Percentiles!D$3, "Low", IF(D20 <= Percentiles!D$4, "Medium", "High")) -> High | M20: =IF(H20 <Percentiles!$H$3, "Low", IF(H20 <= Percentiles!$H$4, "Medium", "High")) -> Low | N20: =(F20 - AVERAGE(F$2:$F$70)) / _xlfn.STDEV.S(F$2:F$70) -> 1.2881038 | O20: =(G20 - AVERAGE($G$2:G$70)) / _xlfn.STDEV.S(G$2:G$70) -> -0.58609844 | P20: =IF(AND(N20>=0, O20>=0), "Star", IF(AND(N20>=0, O20<0), "Cash Cow", IF(AND(N20<0, O20>=0), "Question Mark", "Dog"))) -> Cash Cow
A21: Granite State Credit Union | B21: =AVERAGEIF('Quarterly Performance'!AC$3:AC$1146, 1, 'Quarterly Performance'!C$3:C$1146) -> 2.4463677e+08 | C21: =AVERAGEIF('Quarterly Performance'!$AC$3:$AC$1146, 1, 'Quarterly Performance'!D$3:D$1146) -> 42853953 | D21: =AVERAGEIF('Quarterly Performance'!$AC$3:$AC$1146, 1, 'Quarterly Performance'!E$3:E$1146) -> 2.0178281e+08 | E21: =AVERAGEIF('Quarterly Performance'!$AC$3:$AC$1146, 1, 'Quarterly Performance'!F$3:F$1146) -> 53.730777 | F21: =AVERAGEIF('Quarterly Performance'!$AC$3:$AC$1146, 1, 'Quarterly Performance'!G$3:G$1146) -> 35.218058 | G21: =AVERAGEIF('Quarterly Performance'!$AC$3:$AC$1146, 1, 'Quarterly Performance'!H$3:H$1146) -> 108.95306 | H21: =AVERAGEIF('Quarterly Performance'!$AC$3:$AC$1146, 1, 'Quarterly Performance'!I$3:I$1146) -> 48.493704 | I21: =IF(E21 <Percentiles!$E$3, "Low", IF(E21 <= Percentiles!$E$4, "Medium", "High")) -> Low | J21: =IF(B21 <Percentiles!B$3, "Low", IF(B21 <= Percentiles!B$4, "Medium", "High")) -> Low | K21: =IF(C21 <Percentiles!C$3, "Low", IF(C21 <= Percentiles!C$4, "Medium", "High")) -> Medium | L21: =IF(D21 <Percentiles!D$3, "Low", IF(D21 <= Percentiles!D$4, "Medium", "High")) -> Medium | M21: =IF(H21 <Percentiles!$H$3, "Low", IF(H21 <= Percentiles!$H$4, "Medium", "High")) -> Medium | N21: =(F21 - AVERAGE(F$2:$F$70)) / _xlfn.STDEV.S(F$2:F$70) -> 0.52655858 | O21: =(G21 - AVERAGE($G$2:G$70)) / _xlfn.STDEV.S(G$2:G$70) -> 0.028026151 | P21: =IF(AND(N21>=0, O21>=0), "Star", IF(AND(N21>=0, O21<0), "Cash Cow", IF(AND(N21<0, O21>=0), "Question Mark", "Dog"))) -> Star
A22: Guardian Life Assurance | B22: =AVERAGEIF('Quarterly Performance'!AD$3:AD$1146, 1, 'Quarterly Performance'!C$3:C$1146) -> 2.4765086e+08 | C22: =AVERAGEIF('Quarterly Performance'!$AD$3:$AD$1146, 1, 'Quarterly Performance'!D$3:D$1146) -> 51363347 | D22: =AVERAGEIF('Quarterly Performance'!$AD$3:$AD$1146, 1, 'Quarterly Performance'!E$3:E$1146) -> 1.9628751e+08 | E22: =AVERAGEIF('Quarterly Performance'!$AD$3:$AD$1146, 1, 'Quarterly Performance'!F$3:F$1146) -> 51.069611 | F22: =AVERAGEIF('Quarterly Performance'!$AD$3:$AD$1146, 1, 'Quarterly Performance'!G$3:G$1146) -> 22.3705 | G22: =AVERAGEIF('Quarterly Performance'!$AD$3:$AD$1146, 1, 'Quarterly Performance'!H$3:H$1146) -> 102.69472 | H22: =AVERAGEIF('Quarterly Performance'!$AD$3:$AD$1146, 1, 'Quarterly Performance'!I$3:I$1146) -> 48.935889 | I22: =IF(E22 <Percentiles!$E$3, "Low", IF(E22 <= Percentiles!$E$4, "Medium", "High")) -> Low | J22: =IF(B22 <Percentiles!B$3, "Low", IF(B22 <= Percentiles!B$4, "Medium", "High")) -> Medium | K22: =IF(C22 <Percentiles!C$3, "Low", IF(C22 <= Percentiles!C$4, "Medium", "High")) -> Medium | L22: =IF(D22 <Percentiles!D$3, "Low", IF(D22 <= Percentiles!D$4, "Medium", "High")) -> Medium | M22: =IF(H22 <Percentiles!$H$3, "Low", IF(H22 <= Percentiles!$H$4, "Medium", "High")) -> Medium | N22: =(F22 - AVERAGE(F$2:$F$70)) / _xlfn.STDEV.S(F$2:F$70) -> -1.7028621 | O22: =(G22 - AVERAGE($G$2:G$70)) / _xlfn.STDEV.S(G$2:G$70) -> -0.082454792 | P22: =IF(AND(N22>=0, O22>=0), "Star", IF(AND(N22>=0, O22<0), "Cash Cow", IF(AND(N22<0, O22>=0), "Question Mark", "Dog"))) -> Dog
A23: GuardianPay Tech | B23: =AVERAGEIF('Quarterly Performance'!AE$3:AE$1146, 1, 'Quarterly Performance'!C$3:C$1146) -> 2.5821169e+08 | C23: =AVERAGEIF('Quarterly Performance'!$AE$3:$AE$1146, 1, 'Quarterly Performance'!D$3:D$1146) -> 80218068 | D23: =AVERAGEIF('Quarterly Performance'!$AE$3:$AE$1146, 1, 'Quarterly Performance'!E$3:E$1146) -> 1.7799363e+08 | E23: =AVERAGEIF('Quarterly Performance'!$AE$3:$AE$1146, 1, 'Quarterly Performance'!F$3:F$1146) -> 65.016223 | F23: =AVERAGEIF('Quarterly Performance'!$AE$3:$AE$1146, 1, 'Quarterly Performance'!G$3:G$1146) -> 31.666886 | G23: =AVERAGEIF('Quarterly Performance'!$AE$3:$AE$1146, 1, 'Quarterly Performance'!H$3:H$1146) -> 208.71226 | H23: =AVERAGEIF('Quarterly Performance'!$AE$3:$AE$1146, 1, 'Quarterly Performance'!I$3:I$1146) -> 46.497151 | I23: =IF(E23 <Percentiles!$E$3, "Low", IF(E23 <= Percentiles!$E$4, "Medium", "High")) -> High | J23: =IF(B23 <Percentiles!B$3, "Low", IF(B23 <= Percentiles!B$4, "Medium", "High")) -> High | K23: =IF(C23 <Percentiles!C$3, "Low", IF(C23 <= Percentiles!C$4, "Medium", "High")) -> High | L23: =IF(D23 <Percentiles!D$3, "Low", IF(D23 <= Percentiles!D$4, "Medium", "High")) -> Low | M23: =IF(H23 <Percentiles!$H$3, "Low", IF(H23 <= Percentiles!$H$4, "Medium", "High")) -> Low | N23: =(F23 - AVERAGE(F$2:$F$70)) / _xlfn.STDEV.S(F$2:F$70) -> -0.089671827 | O23: =(G23 - AVERAGE($G$2:G$70)) / _xlfn.STDEV.S(G$2:G$70) -> 1.7891171 | P23: =IF(AND(N23>=0, O23>=0), "Star", IF(AND(N23>=0, O23<0), "Cash Cow", IF(AND(N23<0, O23>=0), "Question Mark", "Dog"))) -> Question Mark
A24: GuardianPay Technologies | B24: =AVERAGEIF('Quarterly Performance'!AF$3:AF$1146, 1, 'Quarterly Performance'!C$3:C$1146) -> 2.4544786e+08 | C24: =AVERAGEIF('Quarterly Performance'!$AF$3:$AF$1146, 1, 'Quarterly Performance'!D$3:D$1146) -> 43066719 | D24: =AVERAGEIF('Quarterly Performance'!$AF$3:$AF$1146, 1, 'Quarterly Performance'!E$3:E$1146) -> 2.0238114e+08 | E24: =AVERAGEIF('Quarterly Performance'!$AF$3:$AF$1146, 1, 'Quarterly Performance'!F$3:F$1146) -> 58.057929 | F24: =AVERAGEIF('Quarterly Performance'!$AF$3:$AF$1146, 1, 'Quarterly Performance'!G$3:G$1146) -> 36.779897 | G24: =AVERAGEIF('Quarterly Performance'!$AF$3:$AF$1146, 1, 'Quarterly Performance'!H$3:H$1146) -> 104.0531 | H24: =AVERAGEIF('Quarterly Performance'!$AF$3:$AF$1146, 1, 'Quarterly Performance'!I$3:I$1146) -> 48.91084 | I24: =IF(E24 <Percentiles!$E$3, "Low", IF(E24 <= Percentiles!$E$4, "Medium", "High")) -> Medium | J24: =IF(B24 <Percentiles!B$3, "Low", IF(B24 <= Percentiles!B$4, "Medium", "High")) -> Low | K24: =IF(C24 <Percentiles!C$3, "Low", IF(C24 <= Percentiles!C$4, "Medium", "High")) -> Medium | L24: =IF(D24 <Percentiles!D$3, "Low", IF(D24 <= Percentiles!D$4, "Medium", "High")) -> Medium | M24: =IF(H24 <Percentiles!$H$3, "Low", IF(H24 <= Percentiles!$H$4, "Medium", "High")) -> Medium | N24: =(F24 - AVERAGE(F$2:$F$70)) / _xlfn.STDEV.S(F$2:F$70) -> 0.79758249 | O24: =(G24 - AVERAGE($G$2:G$70)) / _xlfn.STDEV.S(G$2:G$70) -> -0.058474911 | P24: =IF(AND(N24>=0, O24>=0), "Star", IF(AND(N24>=0, O24<0), "Cash Cow", IF(AND(N24<0, O24>=0), "Question Mark", "Dog"))) -> Cash Cow
A25: Harborview Savings Bank | B25: =AVERAGEIF('Quarterly Performance'!AG$3:AG$1146, 1, 'Quarterly Performance'!C$3:C$1146) -> 2.3718942e+08 | C25: =AVERAGEIF('Quarterly Performance'!$AG$3:$AG$1146, 1, 'Quarterly Performance'!D$3:D$1146) -> 49490506 | D25: =AVERAGEIF('Quarterly Performance'!$AG$3:$AG$1146, 1, 'Quarterly Performance'!E$3:E$1146) -> 1.8769891e+08 | E25: =AVERAGEIF('Quarterly Performance'!$AG$3:$AG$1146, 1, 'Quarterly Performance'!F$3:F$1146) -> 49.469159 | F25: =AVERAGEIF('Quarterly Performance'!$AG$3:$AG$1146, 1, 'Quarterly Performance'!G$3:G$1146) -> 26.548031 | G25: =AVERAGEIF('Quarterly Performance'!$AG$3:$AG$1146, 1, 'Quarterly Performance'!H$3:H$1146) -> 4.2475682 | H25: =AVERAGEIF('Quarterly Performance'!$AG$3:$AG$1146, 1, 'Quarterly Performance'!I$3:I$1146) -> 48.62574 | I25: =IF(E25 <Percentiles!$E$3, "Low", IF(E25 <= Percentiles!$E$4, "Medium", "High")) -> Low | J25: =IF(B25 <Percentiles!B$3, "Low", IF(B25 <= Percentiles!B$4, "Medium", "High")) -> Low | K25: =IF(C25 <Percentiles!C$3, "Low", IF(C25 <= Percentiles!C$4, "Medium", "High")) -> Medium | L25: =IF(D25 <Percentiles!D$3, "Low", IF(D25 <= Percentiles!D$4, "Medium", "High")) -> Low | M25: =IF(H25 <Percentiles!$H$3, "Low", IF(H25 <= Percentiles!$H$4, "Medium", "High")) -> Medium | N25: =(F25 - AVERAGE(F$2:$F$70)) / _xlfn.STDEV.S(F$2:F$70) -> -0.97794031 | O25: =(G25 - AVERAGE($G$2:G$70)) / _xlfn.STDEV.S(G$2:G$70) -> -1.8203837 | P25: =IF(AND(N25>=0, O25>=0), "Star", IF(AND(N25>=0, O25<0), "Cash Cow", IF(AND(N25<0, O25>=0), "Question Mark", "Dog"))) -> Dog
A26: Horizon Health & Life | B26: =AVERAGEIF('Quarterly Performance'!AH$3:AH$1146, 1, 'Quarterly Performance'!C$3:C$1146) -> 2.4498817e+08 | C26: =AVERAGEIF('Quarterly Performance'!$AH$3:$AH$1146, 1, 'Quarterly Performance'!D$3:D$1146) -> 25675075 | D26: =AVERAGEIF('Quarterly Performance'!$AH$3:$AH$1146, 1, 'Quarterly Performance'!E$3:E$1146) -> 2.1931309e+08 | E26: =AVERAGEIF('Quarterly Performance'!$AH$3:$AH$1146, 1, 'Quarterly Performance'!F$3:F$1146) -> 67.536058 | F26: =AVERAGEIF('Quarterly Performance'!$AH$3:$AH$1146, 1, 'Quarterly Performance'!G$3:G$1146) -> 40.560265 | G26: =AVERAGEIF('Quarterly Performance'!$AH$3:$AH$1146, 1, 'Quarterly Performance'!H$3:H$1146) -> 48.383893 | H26: =AVERAGEIF('Quarterly Performance'!$AH$3:$AH$1146, 1, 'Quarterly Performance'!I$3:I$1146) -> 52.25087 | I26: =IF(E26 <Percentiles!$E$3, "Low", IF(E26 <= Percentiles!$E$4, "Medium", "High")) -> High | J26: =IF(B26 <Percentiles!B$3, "Low", IF(B26 <= Percentiles!B$4, "Medium", "High")) -> Low | K26: =IF(C26 <Percentiles!C$3, "Low", IF(C26 <= Percentiles!C$4, "Medium", "High")) -> Low | L26: =IF(D26 <Percentiles!D$3, "Low", IF(D26 <= Percentiles!D$4, "Medium", "High")) -> High | M26: =IF(H26 <Percentiles!$H$3, "Low", IF(H26 <= Percentiles!$H$4, "Medium", "High")) -> Medium | N26: =(F26 - AVERAGE(F$2:$F$70)) / _xlfn.STDEV.S(F$2:F$70) -> 1.453585 | O26: =(G26 - AVERAGE($G$2:G$70)) / _xlfn.STDEV.S(G$2:G$70) -> -1.0412266 | P26: =IF(AND(N26>=0, O26>=0), "Star", IF(AND(N26>=0, O26<0), "Cash Cow", IF(AND(N26<0, O26>=0), "Question Mark", "Dog"))) -> Cash Cow
A27: Horizon National Bank | B27: =AVERAGEIF('Quarterly Performance'!AI$3:AI$1146, 1, 'Quarterly Performance'!C$3:C$1146) -> 2.4739555e+08 | C27: =AVERAGEIF('Quarterly Performance'!$AI$3:$AI$1146, 1, 'Quarterly Performance'!D$3:D$1146) -> 42891630 | D27: =AVERAGEIF('Quarterly Performance'!$AI$3:$AI$1146, 1, 'Quarterly Performance'!E$3:E$1146) -> 2.0450392e+08 | E27: =AVERAGEIF('Quarterly Performance'!$AI$3:$AI$1146, 1, 'Quarterly Performance'!F$3:F$1146) -> 61.692802 | F27: =AVERAGEIF('Quarterly Performance'!$AI$3:$AI$1146, 1, 'Quarterly Performance'!G$3:G$1146) -> 28.387162 | G27: =AVERAGEIF('Quarterly Performance'!$AI$3:$AI$1146, 1, 'Quarterly Performance'!H$3:H$1146) -> 163.94184 | H27: =AVERAGEIF('Quarterly Performance'!$AI$3:$AI$1146, 1, 'Quarterly Performance'!I$3:I$1146) -> 48.451427 | I27: =IF(E27 <Percentiles!$E$3, "Low", IF(E27 <= Percentiles!$E$4, "Medium", "High")) -> Medium | J27: =IF(B27 <Percentiles!B$3, "Low", IF(B27 <= Percentiles!B$4, "Medium", "High")) -> Medium | K27: =IF(C27 <Percentiles!C$3, "Low", IF(C27 <= Percentiles!C$4, "Medium", "High")) -> Medium | L27: =IF(D27 <Percentiles!D$3, "Low", IF(D27 <= Percentiles!D$4, "Medium", "High")) -> Medium | M27: =IF(H27 <Percentiles!$H$3, "Low", IF(H27 <= Percentiles!$H$4, "Medium", "High")) -> Medium | N27: =(F27 - AVERAGE(F$2:$F$70)) / _xlfn.STDEV.S(F$2:F$70) -> -0.65879814 | O27: =(G27 - AVERAGE($G$2:G$70)) / _xlfn.STDEV.S(G$2:G$70) -> 0.99876613 | P27: =IF(AND(N27>=0, O27>=0), "Star", IF(AND(N27>=0, O27<0), "Cash Cow", IF(AND(N27<0, O27>=0), "Question Mark", "Dog"))) -> Question Mark
A28: Horizon Wealth Management | B28: =AVERAGEIF('Quarterly Performance'!AJ$3:AJ$1146, 1, 'Quarterly Performance'!C$3:C$1146) -> 2.5394902e+08 | C28: =AVERAGEIF('Quarterly Performance'!$AJ$3:$AJ$1146, 1, 'Quarterly Performance'!D$3:D$1146) -> 40350358 | D28: =AVERAGEIF('Quarterly Performance'!$AJ$3:$AJ$1146, 1, 'Quarterly Performance'!E$3:E$1146) -> 2.1359866e+08 | E28: =AVERAGEIF('Quarterly Performance'!$AJ$3:$AJ$1146, 1, 'Quarterly Performance'!F$3:F$1146) -> 55.870587 | F28: =AVERAGEIF('Quarterly Performance'!$AJ$3:$AJ$1146, 1, 'Quarterly Performance'!G$3:G$1146) -> 21.844711 | G28: =AVERAGEIF('Quarterly Performance'!$AJ$3:$AJ$1146, 1, 'Quarterly Performance'!H$3:H$1146) -> 81.173986 | H28: =AVERAGEIF('Quarterly Performance'!$AJ$3:$AJ$1146, 1, 'Quarterly Performance'!I$3:I$1146) -> 48.046036 | I28: =IF(E28 <Percentiles!$E$3, "Low", IF(E28 <= Percentiles!$E$4, "Medium", "High")) -> Medium | J28: =IF(B28 <Percentiles!B$3, "Low", IF(B28 <= Percentiles!B$4, "Medium", "High")) -> High | K28: =IF(C28 <Percentiles!C$3, "Low", IF(C28 <= Percentiles!C$4, "Medium", "High")) -> Low | L28: =IF(D28 <Percentiles!D$3, "Low", IF(D28 <= Percentiles!D$4, "Medium", "High")) -> High | M28: =IF(H28 <Percentiles!$H$3, "Low", IF(H28 <= Percentiles!$H$4, "Medium", "High")) -> Low | N28: =(F28 - AVERAGE(F$2:$F$70)) / _xlfn.STDEV.S(F$2:F$70) -> -1.7941016 | O28: =(G28 - AVERAGE($G$2:G$70)) / _xlfn.STDEV.S(G$2:G$70) -> -0.46236939 | P28: =IF(AND(N28>=0, O28>=0), "Star", IF(AND(N28>=0, O28<0), "Cash Cow", IF(AND(N28<0, O28>=0), "Question Mark", "Dog"))) -> Dog
A29: HorizonPay Tech | B29: =AVERAGEIF('Quarterly Performance'!AK$3:AK$1146, 1, 'Quarterly Performance'!C$3:C$1146) -> 2.4614566e+08 | C29: =AVERAGEIF('Quarterly Performance'!$AK$3:$AK$1146, 1, 'Quarterly Performance'!D$3:D$1146) -> 37639515 | D29: =AVERAGEIF('Quarterly Performance'!$AK$3:$AK$1146, 1, 'Quarterly Performance'!E$3:E$1146) -> 2.0850615e+08 | E29: =AVERAGEIF('Quarterly Performance'!$AK$3:$AK$1146, 1, 'Quarterly Performance'!F$3:F$1146) -> 64.456824 | F29: =AVERAGEIF('Quarterly Performance'!$AK$3:$AK$1146, 1, 'Quarterly Performance'!G$3:G$1146) -> 26.721609 | G29: =AVERAGEIF('Quarterly Performance'!$AK$3:$AK$1146, 1, 'Quarterly Performance'!H$3:H$1146) -> 113.39801 | H29: =AVERAGEIF('Quarterly Performance'!$AK$3:$AK$1146, 1, 'Quarterly Performance'!I$3:I$1146) -> 45.938655 | I29: =IF(E29 <Percentiles!$E$3, "Low", IF(E29 <= Percentiles!$E$4, "Medium", "High")) -> Medium | J29: =IF(B29 <Percentiles!B$3, "Low", IF(B29 <= Percentiles!B$4, "Medium", "High")) -> Low | K29: =IF(C29 <Percentiles!C$3, "Low", IF(C29 <= Percentiles!C$4, "Medium", "High")) -> Low | L29: =IF(D29 <Percentiles!D$3, "Low", IF(D29 <= Percentiles!D$4, "Medium", "High")) -> High | M29: =IF(H29 <Percentiles!$H$3, "Low", IF(H29 <= Percentiles!$H$4, "Medium", "High")) -> Low | N29: =(F29 - AVERAGE(F$2:$F$70)) / _xlfn.STDEV.S(F$2:F$70) -> -0.94781958 | O29: =(G29 - AVERAGE($G$2:G$70)) / _xlfn.STDEV.S(G$2:G$70) -> 0.10649484 | P29: =IF(AND(N29>=0, O29>=0), "Star", IF(AND(N29>=0, O29<0), "Cash Cow", IF(AND(N29<0, O29>=0), "Question Mark", "Dog"))) -> Question Mark
A30: Ironclad Risk Solutions | B30: =AVERAGEIF('Quarterly Performance'!AL$3:AL$1146, 1, 'Quarterly Performance'!C$3:C$1146) -> 2.5150811e+08 | C30: =AVERAGEIF('Quarterly Performance'!$AL$3:$AL$1146, 1, 'Quarterly Performance'!D$3:D$1146) -> 47036235 | D30: =AVERAGEIF('Quarterly Performance'!$AL$3:$AL$1146, 1, 'Quarterly Performance'!E$3:E$1146) -> 2.0447187e+08 | E30: =AVERAGEIF('Quarterly Performance'!$AL$3:$AL$1146, 1, 'Quarterly Performance'!F$3:F$1146) -> 60.445298 | F30: =AVERAGEIF('Quarterly Performance'!$AL$3:$AL$1146, 1, 'Quarterly Performance'!G$3:G$1146) -> 31.011727 | G30: =AVERAGEIF('Quarterly Performance'!$AL$3:$AL$1146, 1, 'Quarterly Performance'!H$3:H$1146) -> 46.617876 | H30: =AVERAGEIF('Quarterly Performance'!$AL$3:$AL$1146, 1, 'Quarterly Performance'!I$3:I$1146) -> 46.436393 | I30: =IF(E30 <Percentiles!$E$3, "Low", IF(E30 <= Percentiles!$E$4, "Medium", "High")) -> Medium | J30: =IF(B30 <Percentiles!B$3, "Low", IF(B30 <= Percentiles!B$4, "Medium", "High")) -> Medium | K30: =IF(C30 <Percentiles!C$3, "Low", IF(C30 <= Percentiles!C$4, "Medium", "High")) -> Medium | L30: =IF(D30 <Percentiles!D$3, "Low", IF(D30 <= Percentiles!D$4, "Medium", "High")) -> Medium | M30: =IF(H30 <Percentiles!$H$3, "Low", IF(H30 <= Percentiles!$H$4, "Medium", "High")) -> Low | N30: =(F30 - AVERAGE(F$2:$F$70)) / _xlfn.STDEV.S(F$2:F$70) -> -0.20336081 | O30: =(G30 - AVERAGE($G$2:G$70)) / _xlfn.STDEV.S(G$2:G$70) -> -1.0724029 | P30: =IF(AND(N30>=0, O30>=0), "Star", IF(AND(N30>=0, O30<0), "Cash Cow", IF(AND(N30<0, O30>=0), "Question Mark", "Dog"))) -> Dog
A31: Keystone Credit Union | B31: =AVERAGEIF('Quarterly Performance'!AM$3:AM$1146, 1, 'Quarterly Performance'!C$3:C$1146) -> 2.5266944e+08 | C31: =AVERAGEIF('Quarterly Performance'!$AM$3:$AM$1146, 1, 'Quarterly Performance'!D$3:D$1146) -> 54839329 | D31: =AVERAGEIF('Quarterly Performance'!$AM$3:$AM$1146, 1, 'Quarterly Performance'!E$3:E$1146) -> 1.9783011e+08 | E31: =AVERAGEIF('Quarterly Performance'!$AM$3:$AM$1146, 1, 'Quarterly Performance'!F$3:F$1146) -> 66.456858 | F31: =AVERAGEIF('Quarterly Performance'!$AM$3:$AM$1146, 1, 'Quarterly Performance'!G$3:G$1146) -> 38.439783 | G31: =AVERAGEIF('Quarterly Performance'!$AM$3:$AM$1146, 1, 'Quarterly Performance'!H$3:H$1146) -> 125.64661 | H31: =AVERAGEIF('Quarterly Performance'!$AM$3:$AM$1146, 1, 'Quarterly Performance'!I$3:I$1146) -> 52.025978 | I31: =IF(E31 <Percentiles!$E$3, "Low", IF(E31 <= Percentiles!$E$4, "Medium", "High")) -> High | J31: =IF(B31 <Percentiles!B$3, "Low", IF(B31 <= Percentiles!B$4, "Medium", "High")) -> High | K31: =IF(C31 <Percentiles!C$3, "Low", IF(C31 <= Percentiles!C$4, "Medium", "High")) -> High | L31: =IF(D31 <Percentiles!D$3, "Low", IF(D31 <= Percentiles!D$4, "Medium", "High")) -> Medium | M31: =IF(H31 <Percentiles!$H$3, "Low", IF(H31 <= Percentiles!$H$4, "Medium", "High")) -> Medium | N31: =(F31 - AVERAGE(F$2:$F$70)) / _xlfn.STDEV.S(F$2:F$70) -> 1.0856204 | O31: =(G31 - AVERAGE($G$2:G$70)) / _xlfn.STDEV.S(G$2:G$70) -> 0.32272442 | P31: =IF(AND(N31>=0, O31>=0), "Star", IF(AND(N31>=0, O31<0), "Cash Cow", IF(AND(N31<0, O31>=0), "Question Mark", "Dog"))) -> Star
A32: Liberty Digital Finance | B32: =AVERAGEIF('Quarterly Performance'!AN$3:AN$1146, 1, 'Quarterly Performance'!C$3:C$1146) -> 2.5281682e+08 | C32: =AVERAGEIF('Quarterly Performance'!$AN$3:$AN$1146, 1, 'Quarterly Performance'!D$3:D$1146) -> 48558720 | D32: =AVERAGEIF('Quarterly Performance'!$AN$3:$AN$1146, 1, 'Quarterly Performance'!E$3:E$1146) -> 2.042581e+08 | E32: =AVERAGEIF('Quarterly Performance'!$AN$3:$AN$1146, 1, 'Quarterly Performance'!F$3:F$1146) -> 61.173076 | F32: =AVERAGEIF('Quarterly Performance'!$AN$3:$AN$1146, 1, 'Quarterly Performance'!G$3:G$1146) -> 40.722478 | G32: =AVERAGEIF('Quarterly Performance'!$AN$3:$AN$1146, 1, 'Quarterly Performance'!H$3:H$1146) -> 75.866695 | H32: =AVERAGEIF('Quarterly Performance'!$AN$3:$AN$1146, 1, 'Quarterly Performance'!I$3:I$1146) -> 50.026095 | I32: =IF(E32 <Percentiles!$E$3, "Low", IF(E32 <= Percentiles!$E$4, "Medium", "High")) -> Medium | J32: =IF(B32 <Percentiles!B$3, "Low", IF(B32 <= Percentiles!B$4, "Medium", "High")) -> High | K32: =IF(C32 <Percentiles!C$3, "Low", IF(C32 <= Percentiles!C$4, "Medium", "High")) -> Medium | L32: =IF(D32 <Percentiles!D$3, "Low", IF(D32 <= Percentiles!D$4, "Medium", "High")) -> Medium | M32: =IF(H32 <Percentiles!$H$3, "Low", IF(H32 <= Percentiles!$H$4, "Medium", "High")) -> Medium | N32: =(F32 - AVERAGE(F$2:$F$70)) / _xlfn.STDEV.S(F$2:F$70) -> 1.4817336 | O32: =(G32 - AVERAGE($G$2:G$70)) / _xlfn.STDEV.S(G$2:G$70) -> -0.55606124 | P32: =IF(AND(N32>=0, O32>=0), "Star", IF(AND(N32>=0, O32<0), "Cash Cow", IF(AND(N32<0, O32>=0), "Question Mark", "Dog"))) -> Cash Cow
A33: Liberty First Bank | B33: =AVERAGEIF('Quarterly Performance'!AO$3:AO$1146, 1, 'Quarterly Performance'!C$3:C$1146) -> 2.5096172e+08 | C33: =AVERAGEIF('Quarterly Performance'!$AO$3:$AO$1146, 1, 'Quarterly Performance'!D$3:D$1146) -> 45706475 | D33: =AVERAGEIF('Quarterly Performance'!$AO$3:$AO$1146, 1, 'Quarterly Performance'!E$3:E$1146) -> 2.0525525e+08 | E33: =AVERAGEIF('Quarterly Performance'!$AO$3:$AO$1146, 1, 'Quarterly Performance'!F$3:F$1146) -> 60.465554 | F33: =AVERAGEIF('Quarterly Performance'!$AO$3:$AO$1146, 1, 'Quarterly Performance'!G$3:G$1146) -> 39.967598 | G33: =AVERAGEIF('Quarterly Performance'!$AO$3:$AO$1146, 1, 'Quarterly Performance'!H$3:H$1146) -> 66.851361 | H33: =AVERAGEIF('Quarterly Performance'!$AO$3:$AO$1146, 1, 'Quarterly Performance'!I$3:I$1146) -> 47.28749 | I33: =IF(E33 <Percentiles!$E$3, "Low", IF(E33 <= Percentiles!$E$4, "Medium", "High")) -> Medium | J33: =IF(B33 <Percentiles!B$3, "Low", IF(B33 <= Percentiles!B$4, "Medium", "High")) -> Medium | K33: =IF(C33 <Percentiles!C$3, "Low", IF(C33 <= Percentiles!C$4, "Medium", "High")) -> Medium | L33: =IF(D33 <Percentiles!D$3, "Low", IF(D33 <= Percentiles!D$4, "Medium", "High")) -> Medium | M33: =IF(H33 <Percentiles!$H$3, "Low", IF(H33 <= Percentiles!$H$4, "Medium", "High")) -> Low | N33: =(F33 - AVERAGE(F$2:$F$70)) / _xlfn.STDEV.S(F$2:F$70) -> 1.3507403 | O33: =(G33 - AVERAGE($G$2:G$70)) / _xlfn.STDEV.S(G$2:G$70) -> -0.71521269 | P33: =IF(AND(N33>=0, O33>=0), "Star", IF(AND(N33>=0, O33<0), "Cash Cow", IF(AND(N33<0, O33>=0), "Question Mark", "Dog"))) -> Cash Cow
A34: Liberty Mutual Risk Partners | B34: =AVERAGEIF('Quarterly Performance'!AP$3:AP$1146, 1, 'Quarterly Performance'!C$3:C$1146) -> 2.5143342e+08 | C34: =AVERAGEIF('Quarterly Performance'!$AP$3:$AP$1146, 1, 'Quarterly Performance'!D$3:D$1146) -> 43348053 | D34: =AVERAGEIF('Quarterly Performance'!$AP$3:$AP$1146, 1, 'Quarterly Performance'!E$3:E$1146) -> 2.0808536e+08 | E34: =AVERAGEIF('Quarterly Performance'!$AP$3:$AP$1146, 1, 'Quarterly Performance'!F$3:F$1146) -> 58.029178 | F34: =AVERAGEIF('Quarterly Performance'!$AP$3:$AP$1146, 1, 'Quarterly Performance'!G$3:G$1146) -> 42.424927 | G34: =AVERAGEIF('Quarterly Performance'!$AP$3:$AP$1146, 1, 'Quarterly Performance'!H$3:H$1146) -> 127.18324 | H34: =AVERAGEIF('Quarterly Performance'!$AP$3:$AP$1146, 1, 'Quarterly Performance'!I$3:I$1146) -> 46.486763 | I34: =IF(E34 <Percentiles!$E$3, "Low", IF(E34 <= Percentiles!$E$4, "Medium", "High")) -> Medium | J34: =IF(B34 <Percentiles!B$3, "Low", IF(B34 <= Percentiles!B$4, "Medium", "High")) -> Medium | K34: =IF(C34 <Percentiles!C$3, "Low", IF(C34 <= Percentiles!C$4, "Medium", "High")) -> Medium | L34: =IF(D34 <Percentiles!D$3, "Low", IF(D34 <= Percentiles!D$4, "Medium", "High")) -> High | M34: =IF(H34 <Percentiles!$H$3, "Low", IF(H34 <= Percentiles!$H$4, "Medium", "High")) -> Low | N34: =(F34 - AVERAGE(F$2:$F$70)) / _xlfn.STDEV.S(F$2:F$70) -> 1.7771574 | O34: =(G34 - AVERAGE($G$2:G$70)) / _xlfn.STDEV.S(G$2:G$70) -> 0.34985121 | P34: =IF(AND(N34>=0, O34>=0), "Star", IF(AND(N34>=0, O34<0), "Cash Cow", IF(AND(N34<0, O34>=0), "Question Mark", "Dog"))) -> Star
A35: Meridian Asset Solutions | B35: =AVERAGEIF('Quarterly Performance'!AQ$3:AQ$1146, 1, 'Quarterly Performance'!C$3:C$1146) -> 2.4403068e+08 | C35: =AVERAGEIF('Quarterly Performance'!$AQ$3:$AQ$1146, 1, 'Quarterly Performance'!D$3:D$1146) -> 49069246 | D35: =AVERAGEIF('Quarterly Performance'!$AQ$3:$AQ$1146, 1, 'Quarterly Performance'!E$3:E$1146) -> 1.9496143e+08 | E35: =AVERAGEIF('Quarterly Performance'!$AQ$3:$AQ$1146, 1, 'Quarterly Performance'!F$3:F$1146) -> 52.357499 | F35: =AVERAGEIF('Quarterly Performance'!$AQ$3:$AQ$1146, 1, 'Quarterly Performance'!G$3:G$1146) -> 43.208778 | G35: =AVERAGEIF('Quarterly Performance'!$AQ$3:$AQ$1146, 1, 'Quarterly Performance'!H$3:H$1146) -> 124.32131 | H35: =AVERAGEIF('Quarterly Performance'!$AQ$3:$AQ$1146, 1, 'Quarterly Performance'!I$3:I$1146) -> 56.879577 | I35: =IF(E35 <Percentiles!$E$3, "Low", IF(E35 <= Percentiles!$E$4, "Medium", "High")) -> Low | J35: =IF(B35 <Percentiles!B$3, "Low", IF(B35 <= Percentiles!B$4, "Medium", "High")) -> Low | K35: =IF(C35 <Percentiles!C$3, "Low", IF(C35 <= Percentiles!C$4, "Medium", "High")) -> Medium | L35: =IF(D35 <Percentiles!D$3, "Low", IF(D35 <= Percentiles!D$4, "Medium", "High")) -> Medium | M35: =IF(H35 <Percentiles!$H$3, "Low", IF(H35 <= Percentiles!$H$4, "Medium", "High")) -> High | N35: =(F35 - AVERAGE(F$2:$F$70)) / _xlfn.STDEV.S(F$2:F$70) -> 1.9131782 | O35: =(G35 - AVERAGE($G$2:G$70)) / _xlfn.STDEV.S(G$2:G$70) -> 0.29932843 | P35: =IF(AND(N35>=0, O35>=0), "Star", IF(AND(N35>=0, O35<0), "Cash Cow", IF(AND(N35<0, O35>=0), "Question Mark", "Dog"))) -> Star
A36: NorthBridge Financial | B36: =AVERAGEIF('Quarterly Performance'!AR$3:AR$1146, 1, 'Quarterly Performance'!C$3:C$1146) -> 2.4630056e+08 | C36: =AVERAGEIF('Quarterly Performance'!$AR$3:$AR$1146, 1, 'Quarterly Performance'!D$3:D$1146) -> 68358309 | D36: =AVERAGEIF('Quarterly Performance'!$AR$3:$AR$1146, 1, 'Quarterly Performance'!E$3:E$1146) -> 1.7794225e+08 | E36: =AVERAGEIF('Quarterly Performance'!$AR$3:$AR$1146, 1, 'Quarterly Performance'!F$3:F$1146) -> 62.658599 | F36: =AVERAGEIF('Quarterly Performance'!$AR$3:$AR$1146, 1, 'Quarterly Performance'!G$3:G$1146) -> 24.989006 | G36: =AVERAGEIF('Quarterly Performance'!$AR$3:$AR$1146, 1, 'Quarterly Performance'!H$3:H$1146) -> 40.056447 | H36: =AVERAGEIF('Quarterly Performance'!$AR$3:$AR$1146, 1, 'Quarterly Performance'!I$3:I$1146) -> 51.429888 | I36: =IF(E36 <Percentiles!$E$3, "Low", IF(E36 <= Percentiles!$E$4, "Medium", "High")) -> Medium | J36: =IF(B36 <Percentiles!B$3, "Low", IF(B36 <= Percentiles!B$4, "Medium", "High")) -> Medium | K36: =IF(C36 <Percentiles!C$3, "Low", IF(C36 <= Percentiles!C$4, "Medium", "High")) -> High | L36: =IF(D36 <Percentiles!D$3, "Low", IF(D36 <= Percentiles!D$4, "Medium", "High")) -> Low | M36: =IF(H36 <Percentiles!$H$3, "Low", IF(H36 <= Percentiles!$H$4, "Medium", "High")) -> Medium | N36: =(F36 - AVERAGE(F$2:$F$70)) / _xlfn.STDEV.S(F$2:F$70) -> -1.2484759 | O36: =(G36 - AVERAGE($G$2:G$70)) / _xlfn.STDEV.S(G$2:G$70) -> -1.1882345 | P36: =IF(AND(N36>=0, O36>=0), "Star", IF(AND(N36>=0, O36<0), "Cash Cow", IF(AND(N36<0, O36>=0), "Question Mark", "Dog"))) -> Dog
A37: NorthBridge Insurance Group | B37: =AVERAGEIF('Quarterly Performance'!AS$3:AS$1146, 1, 'Quarterly Performance'!C$3:C$1146) -> 2.520507e+08 | C37: =AVERAGEIF('Quarterly Performance'!$AS$3:$AS$1146, 1, 'Quarterly Performance'!D$3:D$1146) -> 59027970 | D37: =AVERAGEIF('Quarterly Performance'!$AS$3:$AS$1146, 1, 'Quarterly Performance'!E$3:E$1146) -> 1.9302273e+08 | E37: =AVERAGEIF('Quarterly Performance'!$AS$3:$AS$1146, 1, 'Quarterly Performance'!F$3:F$1146) -> 65.972844 | F37: =AVERAGEIF('Quarterly Performance'!$AS$3:$AS$1146, 1, 'Quarterly Performance'!G$3:G$1146) -> 34.441243 | G37: =AVERAGEIF('Quarterly Performance'!$AS$3:$AS$1146, 1, 'Quarterly Performance'!H$3:H$1146) -> 77.279925 | H37: =AVERAGEIF('Quarterly Performance'!$AS$3:$AS$1146, 1, 'Quarterly Performance'!I$3:I$1146) -> 52.469127 | I37: =IF(E37 <Percentiles!$E$3, "Low", IF(E37 <= Percentiles!$E$4, "Medium", "High")) -> High | J37: =IF(B37 <Percentiles!B$3, "Low", IF(B37 <= Percentiles!B$4, "Medium", "High")) -> Medium | K37: =IF(C37 <Percentiles!C$3, "Low", IF(C37 <= Percentiles!C$4, "Medium", "High")) -> High | L37: =IF(D37 <Percentiles!D$3, "Low", IF(D37 <= Percentiles!D$4, "Medium", "High")) -> Low | M37: =IF(H37 <Percentiles!$H$3, "Low", IF(H37 <= Percentiles!$H$4, "Medium", "High")) -> Medium | N37: =(F37 - AVERAGE(F$2:$F$70)) / _xlfn.STDEV.S(F$2:F$70) -> 0.39175879 | O37: =(G37 - AVERAGE($G$2:G$70)) / _xlfn.STDEV.S(G$2:G$70) -> -0.53111289 | P37: =IF(AND(N37>=0, O37>=0), "Star", IF(AND(N37>=0, O37<0), "Cash Cow", IF(AND(N37<0, O37>=0), "Question Mark", "Dog"))) -> Cash Cow
A38: NorthStar Capital Partners | B38: =AVERAGEIF('Quarterly Performance'!AT$3:AT$1146, 1, 'Quarterly Performance'!C$3:C$1146) -> 2.5044424e+08 | C38: =AVERAGEIF('Quarterly Performance'!$AT$3:$AT$1146, 1, 'Quarterly Performance'!D$3:D$1146) -> 52010245 | D38: =AVERAGEIF('Quarterly Performance'!$AT$3:$AT$1146, 1, 'Quarterly Performance'!E$3:E$1146) -> 1.98434e+08 | E38: =AVERAGEIF('Quarterly Performance'!$AT$3:$AT$1146, 1, 'Quarterly Performance'!F$3:F$1146) -> 56.267369 | F38: =AVERAGEIF('Quarterly Performance'!$AT$3:$AT$1146, 1, 'Quarterly Performance'!G$3:G$1146) -> 23.549862 | G38: =AVERAGEIF('Quarterly Performance'!$AT$3:$AT$1146, 1, 'Quarterly Performance'!H$3:H$1146) -> 85.576008 | H38: =AVERAGEIF('Quarterly Performance'!$AT$3:$AT$1146, 1, 'Quarterly Performance'!I$3:I$1146) -> 47.803369 | I38: =IF(E38 <Percentiles!$E$3, "Low", IF(E38 <= Percentiles!$E$4, "Medium", "High")) -> Medium | J38: =IF(B38 <Percentiles!B$3, "Low", IF(B38 <= Percentiles!B$4, "Medium", "High")) -> Medium | K38: =IF(C38 <Percentiles!C$3, "Low", IF(C38 <= Percentiles!C$4, "Medium", "High")) -> Medium | L38: =IF(D38 <Percentiles!D$3, "Low", IF(D38 <= Percentiles!D$4, "Medium", "High")) -> Medium | M38: =IF(H38 <Percentiles!$H$3, "Low", IF(H38 <= Percentiles!$H$4, "Medium", "High")) -> Low | N38: =(F38 - AVERAGE(F$2:$F$70)) / _xlfn.STDEV.S(F$2:F$70) -> -1.4982087 | O38: =(G38 - AVERAGE($G$2:G$70)) / _xlfn.STDEV.S(G$2:G$70) -> -0.38465867 | P38: =IF(AND(N38>=0, O38>=0), "Star", IF(AND(N38>=0, O38<0), "Cash Cow", IF(AND(N38<0, O38>=0), "Question Mark", "Dog"))) -> Dog
A39: NorthStar Payment Systems | B39: =AVERAGEIF('Quarterly Performance'!AU$3:AU$1146, 1, 'Quarterly Performance'!C$3:C$1146) -> 2.4976782e+08 | C39: =AVERAGEIF('Quarterly Performance'!$AU$3:$AU$1146, 1, 'Quarterly Performance'!D$3:D$1146) -> 42212861 | D39: =AVERAGEIF('Quarterly Performance'!$AU$3:$AU$1146, 1, 'Quarterly Performance'!E$3:E$1146) -> 2.0755496e+08 | E39: =AVERAGEIF('Quarterly Performance'!$AU$3:$AU$1146, 1, 'Quarterly Performance'!F$3:F$1146) -> 57.539507 | F39: =AVERAGEIF('Quarterly Performance'!$AU$3:$AU$1146, 1, 'Quarterly Performance'!G$3:G$1146) -> 29.242926 | G39: =AVERAGEIF('Quarterly Performance'!$AU$3:$AU$1146, 1, 'Quarterly Performance'!H$3:H$1146) -> 83.041609 | H39: =AVERAGEIF('Quarterly Performance'!$AU$3:$AU$1146, 1, 'Quarterly Performance'!I$3:I$1146) -> 46.190072 | I39: =IF(E39 <Percentiles!$E$3, "Low", IF(E39 <= Percentiles!$E$4, "Medium", "High")) -> Medium | J39: =IF(B39 <Percentiles!B$3, "Low", IF(B39 <= Percentiles!B$4, "Medium", "High")) -> Medium | K39: =IF(C39 <Percentiles!C$3, "Low", IF(C39 <= Percentiles!C$4, "Medium", "High")) -> Medium | L39: =IF(D39 <Percentiles!D$3, "Low", IF(D39 <= Percentiles!D$4, "Medium", "High")) -> High | M39: =IF(H39 <Percentiles!$H$3, "Low", IF(H39 <= Percentiles!$H$4, "Medium", "High")) -> Low | N39: =(F39 - AVERAGE(F$2:$F$70)) / _xlfn.STDEV.S(F$2:F$70) -> -0.51029853 | O39: =(G39 - AVERAGE($G$2:G$70)) / _xlfn.STDEV.S(G$2:G$70) -> -0.42939947 | P39: =IF(AND(N39>=0, O39>=0), "Star", IF(AND(N39>=0, O39<0), "Cash Cow", IF(AND(N39<0, O39>=0), "Question Mark", "Dog"))) -> Dog
A40: Nova Equity Management | B40: =AVERAGEIF('Quarterly Performance'!AV$3:AV$1146, 1, 'Quarterly Performance'!C$3:C$1146) -> 2.503913e+08 | C40: =AVERAGEIF('Quarterly Performance'!$AV$3:$AV$1146, 1, 'Quarterly Performance'!D$3:D$1146) -> 47813553 | D40: =AVERAGEIF('Quarterly Performance'!$AV$3:$AV$1146, 1, 'Quarterly Performance'!E$3:E$1146) -> 2.0257774e+08 | E40: =AVERAGEIF('Quarterly Performance'!$AV$3:$AV$1146, 1, 'Quarterly Performance'!F$3:F$1146) -> 55.19244 | F40: =AVERAGEIF('Quarterly Performance'!$AV$3:$AV$1146, 1, 'Quarterly Performance'!G$3:G$1146) -> 36.941661 | G40: =AVERAGEIF('Quarterly Performance'!$AV$3:$AV$1146, 1, 'Quarterly Performance'!H$3:H$1146) -> 98.288959 | H40: =AVERAGEIF('Quarterly Performance'!$AV$3:$AV$1146, 1, 'Quarterly Performance'!I$3:I$1146) -> 48.104894 | I40: =IF(E40 <Percentiles!$E$3, "Low", IF(E40 <= Percentiles!$E$4, "Medium", "High")) -> Low | J40: =IF(B40 <Percentiles!B$3, "Low", IF(B40 <= Percentiles!B$4, "Medium", "High")) -> Medium | K40: =IF(C40 <Percentiles!C$3, "Low", IF(C40 <= Percentiles!C$4, "Medium", "High")) -> Medium | L40: =IF(D40 <Percentiles!D$3, "Low", IF(D40 <= Percentiles!D$4, "Medium", "High")) -> Medium | M40: =IF(H40 <Percentiles!$H$3, "Low", IF(H40 <= Percentiles!$H$4, "Medium", "High")) -> Medium | N40: =(F40 - AVERAGE(F$2:$F$70)) / _xlfn.STDEV.S(F$2:F$70) -> 0.82565324 | O40: =(G40 - AVERAGE($G$2:G$70)) / _xlfn.STDEV.S(G$2:G$70) -> -0.16023162 | P40: =IF(AND(N40>=0, O40>=0), "Star", IF(AND(N40>=0, O40<0), "Cash Cow", IF(AND(N40<0, O40>=0), "Question Mark", "Dog"))) -> Cash Cow
A41: NovaWallet Digital | B41: =AVERAGEIF('Quarterly Performance'!AW$3:AW$1146, 1, 'Quarterly Performance'!C$3:C$1146) -> 2.5277996e+08 | C41: =AVERAGEIF('Quarterly Performance'!$AW$3:$AW$1146, 1, 'Quarterly Performance'!D$3:D$1146) -> 68289682 | D41: =AVERAGEIF('Quarterly Performance'!$AW$3:$AW$1146, 1, 'Quarterly Performance'!E$3:E$1146) -> 1.8449027e+08 | E41: =AVERAGEIF('Quarterly Performance'!$AW$3:$AW$1146, 1, 'Quarterly Performance'!F$3:F$1146) -> 60.650684 | F41: =AVERAGEIF('Quarterly Performance'!$AW$3:$AW$1146, 1, 'Quarterly Performance'!G$3:G$1146) -> 38.522361 | G41: =AVERAGEIF('Quarterly Performance'!$AW$3:$AW$1146, 1, 'Quarterly Performance'!H$3:H$1146) -> 175.85706 | H41: =AVERAGEIF('Quarterly Performance'!$AW$3:$AW$1146, 1, 'Quarterly Performance'!I$3:I$1146) -> 51.784768 | I41: =IF(E41 <Percentiles!$E$3, "Low", IF(E41 <= Percentiles!$E$4, "Medium", "High")) -> Medium | J41: =IF(B41 <Percentiles!B$3, "Low", IF(B41 <= Percentiles!B$4, "Medium", "High")) -> High | K41: =IF(C41 <Percentiles!C$3, "Low", IF(C41 <= Percentiles!C$4, "Medium", "High")) -> High | L41: =IF(D41 <Percentiles!D$3, "Low", IF(D41 <= Percentiles!D$4, "Medium", "High")) -> Low | M41: =IF(H41 <Percentiles!$H$3, "Low", IF(H41 <= Percentiles!$H$4, "Medium", "High")) -> Medium | N41: =(F41 - AVERAGE(F$2:$F$70)) / _xlfn.STDEV.S(F$2:F$70) -> 1.0999501 | O41: =(G41 - AVERAGE($G$2:G$70)) / _xlfn.STDEV.S(G$2:G$70) -> 1.2091105 | P41: =IF(AND(N41>=0, O41>=0), "Star", IF(AND(N41>=0, O41<0), "Cash Cow", IF(AND(N41<0, O41>=0), "Question Mark", "Dog"))) -> Star
A42: Orion Investment Group | B42: =AVERAGEIF('Quarterly Performance'!AX$3:AX$1146, 1, 'Quarterly Performance'!C$3:C$1146) -> 2.4893381e+08 | C42: =AVERAGEIF('Quarterly Performance'!$AX$3:$AX$1146, 1, 'Quarterly Performance'!D$3:D$1146) -> 63461376 | D42: =AVERAGEIF('Quarterly Performance'!$AX$3:$AX$1146, 1, 'Quarterly Performance'!E$3:E$1146) -> 1.8547243e+08 | E42: =AVERAGEIF('Quarterly Performance'!$AX$3:$AX$1146, 1, 'Quarterly Performance'!F$3:F$1146) -> 70.667644 | F42: =AVERAGEIF('Quarterly Performance'!$AX$3:$AX$1146, 1, 'Quarterly Performance'!G$3:G$1146) -> 33.329137 | G42: =AVERAGEIF('Quarterly Performance'!$AX$3:$AX$1146, 1, 'Quarterly Performance'!H$3:H$1146) -> 60.185561 | H42: =AVERAGEIF('Quarterly Performance'!$AX$3:$AX$1146, 1, 'Quarterly Performance'!I$3:I$1146) -> 50.176982 | I42: =IF(E42 <Percentiles!$E$3, "Low", IF(E42 <= Percentiles!$E$4, "Medium", "High")) -> High | J42: =IF(B42 <Percentiles!B$3, "Low", IF(B42 <= Percentiles!B$4, "Medium", "High")) -> Medium | K42: =IF(C42 <Percentiles!C$3, "Low", IF(C42 <= Percentiles!C$4, "Medium", "High")) -> High | L42: =IF(D42 <Percentiles!D$3, "Low", IF(D42 <= Percentiles!D$4, "Medium", "High")) -> Low | M42: =IF(H42 <Percentiles!$H$3, "Low", IF(H42 <= Percentiles!$H$4, "Medium", "High")) -> Medium | N42: =(F42 - AVERAGE(F$2:$F$70)) / _xlfn.STDEV.S(F$2:F$70) -> 0.19877656 | O42: =(G42 - AVERAGE($G$2:G$70)) / _xlfn.STDEV.S(G$2:G$70) -> -0.83288685 | P42: =IF(AND(N42>=0, O42>=0), "Star", IF(AND(N42>=0, O42<0), "Cash Cow", IF(AND(N42<0, O42>=0), "Question Mark", "Dog"))) -> Cash Cow
A43: PaySphere Technologies | B43: =AVERAGEIF('Quarterly Performance'!AY$3:AY$1146, 1, 'Quarterly Performance'!C$3:C$1146) -> 2.4668137e+08 | C43: =AVERAGEIF('Quarterly Performance'!$AY$3:$AY$1146, 1, 'Quarterly Performance'!D$3:D$1146) -> 50268237 | D43: =AVERAGEIF('Quarterly Performance'!$AY$3:$AY$1146, 1, 'Quarterly Performance'!E$3:E$1146) -> 1.9641314e+08 | E43: =AVERAGEIF('Quarterly Performance'!$AY$3:$AY$1146, 1, 'Quarterly Performance'!F$3:F$1146) -> 53.311404 | F43: =AVERAGEIF('Quarterly Performance'!$AY$3:$AY$1146, 1, 'Quarterly Performance'!G$3:G$1146) -> 31.452928 | G43: =AVERAGEIF('Quarterly Performance'!$AY$3:$AY$1146, 1, 'Quarterly Performance'!H$3:H$1146) -> 154.86622 | H43: =AVERAGEIF('Quarterly Performance'!$AY$3:$AY$1146, 1, 'Quarterly Performance'!I$3:I$1146) -> 53.248161 | I43: =IF(E43 <Percentiles!$E$3, "Low", IF(E43 <= Percentiles!$E$4, "Medium", "High")) -> Low | J43: =IF(B43 <Percentiles!B$3, "Low", IF(B43 <= Percentiles!B$4, "Medium", "High")) -> Medium | K43: =IF(C43 <Percentiles!C$3, "Low", IF(C43 <= Percentiles!C$4, "Medium", "High")) -> Medium | L43: =IF(D43 <Percentiles!D$3, "Low", IF(D43 <= Percentiles!D$4, "Medium", "High")) -> Medium | M43: =IF(H43 <Percentiles!$H$3, "Low", IF(H43 <= Percentiles!$H$4, "Medium", "High")) -> High | N43: =(F43 - AVERAGE(F$2:$F$70)) / _xlfn.STDEV.S(F$2:F$70) -> -0.12679974 | O43: =(G43 - AVERAGE($G$2:G$70)) / _xlfn.STDEV.S(G$2:G$70) -> 0.8385504 | P43: =IF(AND(N43>=0, O43>=0), "Star", IF(AND(N43>=0, O43<0), "Cash Cow", IF(AND(N43<0, O43>=0), "Question Mark", "Dog"))) -> Question Mark
A44: Pinnacle Banking Group | B44: =AVERAGEIF('Quarterly Performance'!AZ$3:AZ$1146, 1, 'Quarterly Performance'!C$3:C$1146) -> 2.4659283e+08 | C44: =AVERAGEIF('Quarterly Performance'!$AZ$3:$AZ$1146, 1, 'Quarterly Performance'!D$3:D$1146) -> 47303682 | D44: =AVERAGEIF('Quarterly Performance'!$AZ$3:$AZ$1146, 1, 'Quarterly Performance'!E$3:E$1146) -> 1.9928915e+08 | E44: =AVERAGEIF('Quarterly Performance'!$AZ$3:$AZ$1146, 1, 'Quarterly Performance'!F$3:F$1146) -> 60.339152 | F44: =AVERAGEIF('Quarterly Performance'!$AZ$3:$AZ$1146, 1, 'Quarterly Performance'!G$3:G$1146) -> 29.43114 | G44: =AVERAGEIF('Quarterly Performance'!$AZ$3:$AZ$1146, 1, 'Quarterly Performance'!H$3:H$1146) -> 82.622852 | H44: =AVERAGEIF('Quarterly Performance'!$AZ$3:$AZ$1146, 1, 'Quarterly Performance'!I$3:I$1146) -> 53.418576 | I44: =IF(E44 <Percentiles!$E$3, "Low", IF(E44 <= Percentiles!$E$4, "Medium", "High")) -> Medium | J44: =IF(B44 <Percentiles!B$3, "Low", IF(B44 <= Percentiles!B$4, "Medium", "High")) -> Medium | K44: =IF(C44 <Percentiles!C$3, "Low", IF(C44 <= Percentiles!C$4, "Medium", "High")) -> Medium | L44: =IF(D44 <Percentiles!D$3, "Low", IF(D44 <= Percentiles!D$4, "Medium", "High")) -> Medium | M44: =IF(H44 <Percentiles!$H$3, "Low", IF(H44 <= Percentiles!$H$4, "Medium", "High")) -> High | N44: =(F44 - AVERAGE(F$2:$F$70)) / _xlfn.STDEV.S(F$2:F$70) -> -0.47763795 | O44: =(G44 - AVERAGE($G$2:G$70)) / _xlfn.STDEV.S(G$2:G$70) -> -0.43679196 | P44: =IF(AND(N44>=0, O44>=0), "Star", IF(AND(N44>=0, O44<0), "Cash Cow", IF(AND(N44<0, O44>=0), "Question Mark", "Dog"))) -> Dog
A45: Pinnacle Property & Casualty | B45: =AVERAGEIF('Quarterly Performance'!BA$3:BA$1146, 1, 'Quarterly Performance'!C$3:C$1146) -> 2.4436835e+08 | C45: =AVERAGEIF('Quarterly Performance'!$BA$3:$BA$1146, 1, 'Quarterly Performance'!D$3:D$1146) -> 49793549 | D45: =AVERAGEIF('Quarterly Performance'!$BA$3:$BA$1146, 1, 'Quarterly Performance'!E$3:E$1146) -> 1.945748e+08 | E45: =AVERAGEIF('Quarterly Performance'!$BA$3:$BA$1146, 1, 'Quarterly Performance'!F$3:F$1146) -> 63.636524 | F45: =AVERAGEIF('Quarterly Performance'!$BA$3:$BA$1146, 1, 'Quarterly Performance'!G$3:G$1146) -> 31.971229 | G45: =AVERAGEIF('Quarterly Performance'!$BA$3:$BA$1146, 1, 'Quarterly Performance'!H$3:H$1146) -> 47.383525 | H45: =AVERAGEIF('Quarterly Performance'!$BA$3:$BA$1146, 1, 'Quarterly Performance'!I$3:I$1146) -> 48.974438 | I45: =IF(E45 <Percentiles!$E$3, "Low", IF(E45 <= Percentiles!$E$4, "Medium", "High")) -> Medium | J45: =IF(B45 <Percentiles!B$3, "Low", IF(B45 <= Percentiles!B$4, "Medium", "High")) -> Low | K45: =IF(C45 <Percentiles!C$3, "Low", IF(C45 <= Percentiles!C$4, "Medium", "High")) -> Medium | L45: =IF(D45 <Percentiles!D$3, "Low", IF(D45 <= Percentiles!D$4, "Medium", "High")) -> Low | M45: =IF(H45 <Percentiles!$H$3, "Low", IF(H45 <= Percentiles!$H$4, "Medium", "High")) -> Medium | N45: =(F45 - AVERAGE(F$2:$F$70)) / _xlfn.STDEV.S(F$2:F$70) -> -0.036859568 | O45: =(G45 - AVERAGE($G$2:G$70)) / _xlfn.STDEV.S(G$2:G$70) -> -1.0588865 | P45: =IF(AND(N45>=0, O45>=0), "Star", IF(AND(N45>=0, O45<0), "Cash Cow", IF(AND(N45<0, O45>=0), "Question Mark", "Dog"))) -> Dog
A46: Polaris Wealth Partners | B46: =AVERAGEIF('Quarterly Performance'!BB$3:BB$1146, 1, 'Quarterly Performance'!C$3:C$1146) -> 2.4755893e+08 | C46: =AVERAGEIF('Quarterly Performance'!$BB$3:$BB$1146, 1, 'Quarterly Performance'!D$3:D$1146) -> 40714873 | D46: =AVERAGEIF('Quarterly Performance'!$BB$3:$BB$1146, 1, 'Quarterly Performance'!E$3:E$1146) -> 2.0684406e+08 | E46: =AVERAGEIF('Quarterly Performance'!$BB$3:$BB$1146, 1, 'Quarterly Performance'!F$3:F$1146) -> 58.524076 | F46: =AVERAGEIF('Quarterly Performance'!$BB$3:$BB$1146, 1, 'Quarterly Performance'!G$3:G$1146) -> 24.741138 | G46: =AVERAGEIF('Quarterly Performance'!$BB$3:$BB$1146, 1, 'Quarterly Performance'!H$3:H$1146) -> 165.79632 | H46: =AVERAGEIF('Quarterly Performance'!$BB$3:$BB$1146, 1, 'Quarterly Performance'!I$3:I$1146) -> 51.407261 | I46: =IF(E46 <Percentiles!$E$3, "Low", IF(E46 <= Percentiles!$E$4, "Medium", "High")) -> Medium | J46: =IF(B46 <Percentiles!B$3, "Low", IF(B46 <= Percentiles!B$4, "Medium", "High")) -> Medium | K46: =IF(C46 <Percentiles!C$3, "Low", IF(C46 <= Percentiles!C$4, "Medium", "High")) -> Low | L46: =IF(D46 <Percentiles!D$3, "Low", IF(D46 <= Percentiles!D$4, "Medium", "High")) -> Medium | M46: =IF(H46 <Percentiles!$H$3, "Low", IF(H46 <= Percentiles!$H$4, "Medium", "High")) -> Medium | N46: =(F46 - AVERAGE(F$2:$F$70)) / _xlfn.STDEV.S(F$2:F$70) -> -1.2914882 | O46: =(G46 - AVERAGE($G$2:G$70)) / _xlfn.STDEV.S(G$2:G$70) -> 1.0315041 | P46: =IF(AND(N46>=0, O46>=0), "Star", IF(AND(N46>=0, O46<0), "Cash Cow", IF(AND(N46<0, O46>=0), "Question Mark", "Dog"))) -> Question Mark
A47: Prairie Horizon Bank | B47: =AVERAGEIF('Quarterly Performance'!BC$3:BC$1146, 1, 'Quarterly Performance'!C$3:C$1146) -> 2.5574128e+08 | C47: =AVERAGEIF('Quarterly Performance'!$BC$3:$BC$1146, 1, 'Quarterly Performance'!D$3:D$1146) -> 37455007 | D47: =AVERAGEIF('Quarterly Performance'!$BC$3:$BC$1146, 1, 'Quarterly Performance'!E$3:E$1146) -> 2.1828627e+08 | E47: =AVERAGEIF('Quarterly Performance'!$BC$3:$BC$1146, 1, 'Quarterly Performance'!F$3:F$1146) -> 62.967079 | F47: =AVERAGEIF('Quarterly Performance'!$BC$3:$BC$1146, 1, 'Quarterly Performance'!G$3:G$1146) -> 30.495665 | G47: =AVERAGEIF('Quarterly Performance'!$BC$3:$BC$1146, 1, 'Quarterly Performance'!H$3:H$1146) -> 162.88488 | H47: =AVERAGEIF('Quarterly Performance'!$BC$3:$BC$1146, 1, 'Quarterly Performance'!I$3:I$1146) -> 52.807588 | I47: =IF(E47 <Percentiles!$E$3, "Low", IF(E47 <= Percentiles!$E$4, "Medium", "High")) -> Medium | J47: =IF(B47 <Percentiles!B$3, "Low", IF(B47 <= Percentiles!B$4, "Medium", "High")) -> High | K47: =IF(C47 <Percentiles!C$3, "Low", IF(C47 <= Percentiles!C$4, "Medium", "High")) -> Low | L47: =IF(D47 <Percentiles!D$3, "Low", IF(D47 <= Percentiles!D$4, "Medium", "High")) -> High | M47: =IF(H47 <Percentiles!$H$3, "Low", IF(H47 <= Percentiles!$H$4, "Medium", "High")) -> High | N47: =(F47 - AVERAGE(F$2:$F$70)) / _xlfn.STDEV.S(F$2:F$70) -> -0.2929123 | O47: =(G47 - AVERAGE($G$2:G$70)) / _xlfn.STDEV.S(G$2:G$70) -> 0.98010721 | P47: =IF(AND(N47>=0, O47>=0), "Star", IF(AND(N47>=0, O47<0), "Cash Cow", IF(AND(N47<0, O47>=0), "Question Mark", "Dog"))) -> Question Mark
A48: Prairie Horizon Insurance | B48: =AVERAGEIF('Quarterly Performance'!BD$3:BD$1146, 1, 'Quarterly Performance'!C$3:C$1146) -> 2.3881315e+08 | C48: =AVERAGEIF('Quarterly Performance'!$BD$3:$BD$1146, 1, 'Quarterly Performance'!D$3:D$1146) -> 39712195 | D48: =AVERAGEIF('Quarterly Performance'!$BD$3:$BD$1146, 1, 'Quarterly Performance'!E$3:E$1146) -> 1.9910095e+08 | E48: =AVERAGEIF('Quarterly Performance'!$BD$3:$BD$1146, 1, 'Quarterly Performance'!F$3:F$1146) -> 54.519658 | F48: =AVERAGEIF('Quarterly Performance'!$BD$3:$BD$1146, 1, 'Quarterly Performance'!G$3:G$1146) -> 29.162937 | G48: =AVERAGEIF('Quarterly Performance'!$BD$3:$BD$1146, 1, 'Quarterly Performance'!H$3:H$1146) -> 124.75827 | H48: =AVERAGEIF('Quarterly Performance'!$BD$3:$BD$1146, 1, 'Quarterly Performance'!I$3:I$1146) -> 48.468612 | I48: =IF(E48 <Percentiles!$E$3, "Low", IF(E48 <= Percentiles!$E$4, "Medium", "High")) -> Low | J48: =IF(B48 <Percentiles!B$3, "Low", IF(B48 <= Percentiles!B$4, "Medium", "High")) -> Low | K48: =IF(C48 <Percentiles!C$3, "Low", IF(C48 <= Percentiles!C$4, "Medium", "High")) -> Low | L48: =IF(D48 <Percentiles!D$3, "Low", IF(D48 <= Percentiles!D$4, "Medium", "High")) -> Medium | M48: =IF(H48 <Percentiles!$H$3, "Low", IF(H48 <= Percentiles!$H$4, "Medium", "High")) -> Medium | N48: =(F48 - AVERAGE(F$2:$F$70)) / _xlfn.STDEV.S(F$2:F$70) -> -0.52417893 | O48: =(G48 - AVERAGE($G$2:G$70)) / _xlfn.STDEV.S(G$2:G$70) -> 0.30704219 | P48: =IF(AND(N48>=0, O48>=0), "Star", IF(AND(N48>=0, O48<0), "Cash Cow", IF(AND(N48<0, O48>=0), "Question Mark", "Dog"))) -> Question Mark
A49: Riverstone Trust Co. | B49: =AVERAGEIF('Quarterly Performance'!BE$3:BE$1146, 1, 'Quarterly Performance'!C$3:C$1146) -> 2.5132064e+08 | C49: =AVERAGEIF('Quarterly Performance'!$BE$3:$BE$1146, 1, 'Quarterly Performance'!D$3:D$1146) -> 59173604 | D49: =AVERAGEIF('Quarterly Performance'!$BE$3:$BE$1146, 1, 'Quarterly Performance'!E$3:E$1146) -> 1.9214704e+08 | E49: =AVERAGEIF('Quarterly Performance'!$BE$3:$BE$1146, 1, 'Quarterly Performance'!F$3:F$1146) -> 69.02643 | F49: =AVERAGEIF('Quarterly Performance'!$BE$3:$BE$1146, 1, 'Quarterly Performance'!G$3:G$1146) -> 34.473637 | G49: =AVERAGEIF('Quarterly Performance'!$BE$3:$BE$1146, 1, 'Quarterly Performance'!H$3:H$1146) -> 111.86918 | H49: =AVERAGEIF('Quarterly Performance'!$BE$3:$BE$1146, 1, 'Quarterly Performance'!I$3:I$1146) -> 47.541741 | I49: =IF(E49 <Percentiles!$E$3, "Low", IF(E49 <= Percentiles!$E$4, "Medium", "High")) -> High | J49: =IF(B49 <Percentiles!B$3, "Low", IF(B49 <= Percentiles!B$4, "Medium", "High")) -> Medium | K49: =IF(C49 <Percentiles!C$3, "Low", IF(C49 <= Percentiles!C$4, "Medium", "High")) -> High | L49: =IF(D49 <Percentiles!D$3, "Low", IF(D49 <= Percentiles!D$4, "Medium", "High")) -> Low | M49: =IF(H49 <Percentiles!$H$3, "Low", IF(H49 <= Percentiles!$H$4, "Medium", "High")) -> Low | N49: =(F49 - AVERAGE(F$2:$F$70)) / _xlfn.STDEV.S(F$2:F$70) -> 0.39738009 | O49: =(G49 - AVERAGE($G$2:G$70)) / _xlfn.STDEV.S(G$2:G$70) -> 0.079505649 | P49: =IF(AND(N49>=0, O49>=0), "Star", IF(AND(N49>=0, O49<0), "Cash Cow", IF(AND(N49<0, O49>=0), "Question Mark", "Dog"))) -> Star
A50: SafeHarbor Ins. Group | B50: =AVERAGEIF('Quarterly Performance'!BF$3:BF$1146, 1, 'Quarterly Performance'!C$3:C$1146) -> 2.5617494e+08 | C50: =AVERAGEIF('Quarterly Performance'!$BF$3:$BF$1146, 1, 'Quarterly Performance'!D$3:D$1146) -> 34273646 | D50: =AVERAGEIF('Quarterly Performance'!$BF$3:$BF$1146, 1, 'Quarterly Performance'!E$3:E$1146) -> 2.2190129e+08 | E50: =AVERAGEIF('Quarterly Performance'!$BF$3:$BF$1146, 1, 'Quarterly Performance'!F$3:F$1146) -> 72.236545 | F50: =AVERAGEIF('Quarterly Performance'!$BF$3:$BF$1146, 1, 'Quarterly Performance'!G$3:G$1146) -> 21.745911 | G50: =AVERAGEIF('Quarterly Performance'!$BF$3:$BF$1146, 1, 'Quarterly Performance'!H$3:H$1146) -> 102.41195 | H50: =AVERAGEIF('Quarterly Performance'!$BF$3:$BF$1146, 1, 'Quarterly Performance'!I$3:I$1146) -> 53.377983 | I50: =IF(E50 <Percentiles!$E$3, "Low", IF(E50 <= Percentiles!$E$4, "Medium", "High")) -> High | J50: =IF(B50 <Percentiles!B$3, "Low", IF(B50 <= Percentiles!B$4, "Medium", "High")) -> High | K50: =IF(C50 <Percentiles!C$3, "Low", IF(C50 <= Percentiles!C$4, "Medium", "High")) -> Low | L50: =IF(D50 <Percentiles!D$3, "Low", IF(D50 <= Percentiles!D$4, "Medium", "High")) -> High | M50: =IF(H50 <Percentiles!$H$3, "Low", IF(H50 <= Percentiles!$H$4, "Medium", "High")) -> High | N50: =(F50 - AVERAGE(F$2:$F$70)) / _xlfn.STDEV.S(F$2:F$70) -> -1.8112461 | O50: =(G50 - AVERAGE($G$2:G$70)) / _xlfn.STDEV.S(G$2:G$70) -> -0.087446804 | P50: =IF(AND(N50>=0, O50>=0), "Star", IF(AND(N50>=0, O50<0), "Cash Cow", IF(AND(N50<0, O50>=0), "Question Mark", "Dog"))) -> Dog
A51: SafeHarbor Insurance Group | B51: =AVERAGEIF('Quarterly Performance'!BG$3:BG$1146, 1, 'Quarterly Performance'!C$3:C$1146) -> 2.5093558e+08 | C51: =AVERAGEIF('Quarterly Performance'!$BG$3:$BG$1146, 1, 'Quarterly Performance'!D$3:D$1146) -> 41268177 | D51: =AVERAGEIF('Quarterly Performance'!$BG$3:$BG$1146, 1, 'Quarterly Performance'!E$3:E$1146) -> 2.0966741e+08 | E51: =AVERAGEIF('Quarterly Performance'!$BG$3:$BG$1146, 1, 'Quarterly Performance'!F$3:F$1146) -> 65.612505 | F51: =AVERAGEIF('Quarterly Performance'!$BG$3:$BG$1146, 1, 'Quarterly Performance'!G$3:G$1146) -> 38.479941 | G51: =AVERAGEIF('Quarterly Performance'!$BG$3:$BG$1146, 1, 'Quarterly Performance'!H$3:H$1146) -> 82.501763 | H51: =AVERAGEIF('Quarterly Performance'!$BG$3:$BG$1146, 1, 'Quarterly Performance'!I$3:I$1146) -> 46.116995 | I51: =IF(E51 <Percentiles!$E$3, "Low", IF(E51 <= Percentiles!$E$4, "Medium", "High")) -> High | J51: =IF(B51 <Percentiles!B$3, "Low", IF(B51 <= Percentiles!B$4, "Medium", "High")) -> Medium | K51: =IF(C51 <Percentiles!C$3, "Low", IF(C51 <= Percentiles!C$4, "Medium", "High")) -> Low | L51: =IF(D51 <Percentiles!D$3, "Low", IF(D51 <= Percentiles!D$4, "Medium", "High")) -> High | M51: =IF(H51 <Percentiles!$H$3, "Low", IF(H51 <= Percentiles!$H$4, "Medium", "High")) -> Low | N51: =(F51 - AVERAGE(F$2:$F$70)) / _xlfn.STDEV.S(F$2:F$70) -> 1.092589 | O51: =(G51 - AVERAGE($G$2:G$70)) / _xlfn.STDEV.S(G$2:G$70) -> -0.4389296 | P51: =IF(AND(N51>=0, O51>=0), "Star", IF(AND(N51>=0, O51<0), "Cash Cow", IF(AND(N51<0, O51>=0), "Question Mark", "Dog"))) -> Cash Cow
A52: ShieldPoint Insurance | B52: =AVERAGEIF('Quarterly Performance'!BH$3:BH$1146, 1, 'Quarterly Performance'!C$3:C$1146) -> 2.4836305e+08 | C52: =AVERAGEIF('Quarterly Performance'!$BH$3:$BH$1146, 1, 'Quarterly Performance'!D$3:D$1146) -> 40653139 | D52: =AVERAGEIF('Quarterly Performance'!$BH$3:$BH$1146, 1, 'Quarterly Performance'!E$3:E$1146) -> 2.0770991e+08 | E52: =AVERAGEIF('Quarterly Performance'!$BH$3:$BH$1146, 1, 'Quarterly Performance'!F$3:F$1146) -> 60.109826 | F52: =AVERAGEIF('Quarterly Performance'!$BH$3:$BH$1146, 1, 'Quarterly Performance'!G$3:G$1146) -> 27.986721 | G52: =AVERAGEIF('Quarterly Performance'!$BH$3:$BH$1146, 1, 'Quarterly Performance'!H$3:H$1146) -> 63.387949 | H52: =AVERAGEIF('Quarterly Performance'!$BH$3:$BH$1146, 1, 'Quarterly Performance'!I$3:I$1146) -> 49.554826 | I52: =IF(E52 <Percentiles!$E$3, "Low", IF(E52 <= Percentiles!$E$4, "Medium", "High")) -> Medium | J52: =IF(B52 <Percentiles!B$3, "Low", IF(B52 <= Percentiles!B$4, "Medium", "High")) -> Medium | K52: =IF(C52 <Percentiles!C$3, "Low", IF(C52 <= Percentiles!C$4, "Medium", "High")) -> Low | L52: =IF(D52 <Percentiles!D$3, "Low", IF(D52 <= Percentiles!D$4, "Medium", "High")) -> High | M52: =IF(H52 <Percentiles!$H$3, "Low", IF(H52 <= Percentiles!$H$4, "Medium", "High")) -> Medium | N52: =(F52 - AVERAGE(F$2:$F$70)) / _xlfn.STDEV.S(F$2:F$70) -> -0.72828625 | O52: =(G52 - AVERAGE($G$2:G$70)) / _xlfn.STDEV.S(G$2:G$70) -> -0.77635376 | P52: =IF(AND(N52>=0, O52>=0), "Star", IF(AND(N52>=0, O52<0), "Cash Cow", IF(AND(N52<0, O52>=0), "Question Mark", "Dog"))) -> Dog
A53: Silverline Asset Advisors | B53: =AVERAGEIF('Quarterly Performance'!BI$3:BI$1146, 1, 'Quarterly Performance'!C$3:C$1146) -> 2.5098921e+08 | C53: =AVERAGEIF('Quarterly Performance'!$BI$3:$BI$1146, 1, 'Quarterly Performance'!D$3:D$1146) -> 39504352 | D53: =AVERAGEIF('Quarterly Performance'!$BI$3:$BI$1146, 1, 'Quarterly Performance'!E$3:E$1146) -> 2.1148486e+08 | E53: =AVERAGEIF('Quarterly Performance'!$BI$3:$BI$1146, 1, 'Quarterly Performance'!F$3:F$1146) -> 48.246844 | F53: =AVERAGEIF('Quarterly Performance'!$BI$3:$BI$1146, 1, 'Quarterly Performance'!G$3:G$1146) -> 34.276326 | G53: =AVERAGEIF('Quarterly Performance'!$BI$3:$BI$1146, 1, 'Quarterly Performance'!H$3:H$1146) -> 208.00575 | H53: =AVERAGEIF('Quarterly Performance'!$BI$3:$BI$1146, 1, 'Quarterly Performance'!I$3:I$1146) -> 47.655579 | I53: =IF(E53 <Percentiles!$E$3, "Low", IF(E53 <= Percentiles!$E$4, "Medium", "High")) -> Low | J53: =IF(B53 <Percentiles!B$3, "Low", IF(B53 <= Percentiles!B$4, "Medium", "High")) -> Medium | K53: =IF(C53 <Percentiles!C$3, "Low", IF(C53 <= Percentiles!C$4, "Medium", "High")) -> Low | L53: =IF(D53 <Percentiles!D$3, "Low", IF(D53 <= Percentiles!D$4, "Medium", "High")) -> High | M53: =IF(H53 <Percentiles!$H$3, "Low", IF(H53 <= Percentiles!$H$4, "Medium", "High")) -> Low | N53: =(F53 - AVERAGE(F$2:$F$70)) / _xlfn.STDEV.S(F$2:F$70) -> 0.36314101 | O53: =(G53 - AVERAGE($G$2:G$70)) / _xlfn.STDEV.S(G$2:G$70) -> 1.7766448 | P53: =IF(AND(N53>=0, O53>=0), "Star", IF(AND(N53>=0, O53<0), "Cash Cow", IF(AND(N53<0, O53>=0), "Question Mark", "Dog"))) -> Star
A54: Sterling Asset Management | B54: =AVERAGEIF('Quarterly Performance'!BJ$3:BJ$1146, 1, 'Quarterly Performance'!C$3:C$1146) -> 2.4335849e+08 | C54: =AVERAGEIF('Quarterly Performance'!$BJ$3:$BJ$1146, 1, 'Quarterly Performance'!D$3:D$1146) -> 57678909 | D54: =AVERAGEIF('Quarterly Performance'!$BJ$3:$BJ$1146, 1, 'Quarterly Performance'!E$3:E$1146) -> 1.8567958e+08 | E54: =AVERAGEIF('Quarterly Performance'!$BJ$3:$BJ$1146, 1, 'Quarterly Performance'!F$3:F$1146) -> 60.391046 | F54: =AVERAGEIF('Quarterly Performance'!$BJ$3:$BJ$1146, 1, 'Quarterly Performance'!G$3:G$1146) -> 37.293691 | G54: =AVERAGEIF('Quarterly Performance'!$BJ$3:$BJ$1146, 1, 'Quarterly Performance'!H$3:H$1146) -> 124.83141 | H54: =AVERAGEIF('Quarterly Performance'!$BJ$3:$BJ$1146, 1, 'Quarterly Performance'!I$3:I$1146) -> 50.642302 | I54: =IF(E54 <Percentiles!$E$3, "Low", IF(E54 <= Percentiles!$E$4, "Medium", "High")) -> Medium | J54: =IF(B54 <Percentiles!B$3, "Low", IF(B54 <= Percentiles!B$4, "Medium", "High")) -> Low | K54: =IF(C54 <Percentiles!C$3, "Low", IF(C54 <= Percentiles!C$4, "Medium", "High")) -> High | L54: =IF(D54 <Percentiles!D$3, "Low", IF(D54 <= Percentiles!D$4, "Medium", "High")) -> Low | M54: =IF(H54 <Percentiles!$H$3, "Low", IF(H54 <= Percentiles!$H$4, "Medium", "High")) -> Medium | N54: =(F54 - AVERAGE(F$2:$F$70)) / _xlfn.STDEV.S(F$2:F$70) -> 0.88674053 | O54: =(G54 - AVERAGE($G$2:G$70)) / _xlfn.STDEV.S(G$2:G$70) -> 0.30833335 | P54: =IF(AND(N54>=0, O54>=0), "Star", IF(AND(N54>=0, O54<0), "Cash Cow", IF(AND(N54<0, O54>=0), "Question Mark", "Dog"))) -> Star
A55: Sterling FinTech Labs | B55: =AVERAGEIF('Quarterly Performance'!BK$3:BK$1146, 1, 'Quarterly Performance'!C$3:C$1146) -> 2.5047144e+08 | C55: =AVERAGEIF('Quarterly Performance'!$BK$3:$BK$1146, 1, 'Quarterly Performance'!D$3:D$1146) -> 53989856 | D55: =AVERAGEIF('Quarterly Performance'!$BK$3:$BK$1146, 1, 'Quarterly Performance'!E$3:E$1146) -> 1.9648159e+08 | E55: =AVERAGEIF('Quarterly Performance'!$BK$3:$BK$1146, 1, 'Quarterly Performance'!F$3:F$1146) -> 60.775384 | F55: =AVERAGEIF('Quarterly Performance'!$BK$3:$BK$1146, 1, 'Quarterly Performance'!G$3:G$1146) -> 34.005262 | G55: =AVERAGEIF('Quarterly Performance'!$BK$3:$BK$1146, 1, 'Quarterly Performance'!H$3:H$1146) -> 112.62473 | H55: =AVERAGEIF('Quarterly Performance'!$BK$3:$BK$1146, 1, 'Quarterly Performance'!I$3:I$1146) -> 47.423935 | I55: =IF(E55 <Percentiles!$E$3, "Low", IF(E55 <= Percentiles!$E$4, "Medium", "High")) -> Medium | J55: =IF(B55 <Percentiles!B$3, "Low", IF(B55 <= Percentiles!B$4, "Medium", "High")) -> Medium | K55: =IF(C55 <Percentiles!C$3, "Low", IF(C55 <= Percentiles!C$4, "Medium", "High")) -> Medium | L55: =IF(D55 <Percentiles!D$3, "Low", IF(D55 <= Percentiles!D$4, "Medium", "High")) -> Medium | M55: =IF(H55 <Percentiles!$H$3, "Low", IF(H55 <= Percentiles!$H$4, "Medium", "High")) -> Low | N55: =(F55 - AVERAGE(F$2:$F$70)) / _xlfn.STDEV.S(F$2:F$70) -> 0.3161036 | O55: =(G55 - AVERAGE($G$2:G$70)) / _xlfn.STDEV.S(G$2:G$70) -> 0.09284375 | P55: =IF(AND(N55>=0, O55>=0), "Star", IF(AND(N55>=0, O55<0), "Cash Cow", IF(AND(N55<0, O55>=0), "Question Mark", "Dog"))) -> Star
A56: Sterling L&H | B56: =AVERAGEIF('Quarterly Performance'!BL$3:BL$1146, 1, 'Quarterly Performance'!C$3:C$1146) -> 2.4165829e+08 | C56: =AVERAGEIF('Quarterly Performance'!$BL$3:$BL$1146, 1, 'Quarterly Performance'!D$3:D$1146) -> 32533796 | D56: =AVERAGEIF('Quarterly Performance'!$BL$3:$BL$1146, 1, 'Quarterly Performance'!E$3:E$1146) -> 2.0912449e+08 | E56: =AVERAGEIF('Quarterly Performance'!$BL$3:$BL$1146, 1, 'Quarterly Performance'!F$3:F$1146) -> 84.353382 | F56: =AVERAGEIF('Quarterly Performance'!$BL$3:$BL$1146, 1, 'Quarterly Performance'!G$3:G$1146) -> 35.251675 | G56: =AVERAGEIF('Quarterly Performance'!$BL$3:$BL$1146, 1, 'Quarterly Performance'!H$3:H$1146) -> 323.77221 | H56: =AVERAGEIF('Quarterly Performance'!$BL$3:$BL$1146, 1, 'Quarterly Performance'!I$3:I$1146) -> 61.158517 | I56: =IF(E56 <Percentiles!$E$3, "Low", IF(E56 <= Percentiles!$E$4, "Medium", "High")) -> High | J56: =IF(B56 <Percentiles!B$3, "Low", IF(B56 <= Percentiles!B$4, "Medium", "High")) -> Low | K56: =IF(C56 <Percentiles!C$3, "Low", IF(C56 <= Percentiles!C$4, "Medium", "High")) -> Low | L56: =IF(D56 <Percentiles!D$3, "Low", IF(D56 <= Percentiles!D$4, "Medium", "High")) -> High | M56: =IF(H56 <Percentiles!$H$3, "Low", IF(H56 <= Percentiles!$H$4, "Medium", "High")) -> High | N56: =(F56 - AVERAGE(F$2:$F$70)) / _xlfn.STDEV.S(F$2:F$70) -> 0.53239205 | O56: =(G56 - AVERAGE($G$2:G$70)) / _xlfn.STDEV.S(G$2:G$70) -> 3.8203187 | P56: =IF(AND(N56>=0, O56>=0), "Star", IF(AND(N56>=0, O56<0), "Cash Cow", IF(AND(N56<0, O56>=0), "Question Mark", "Dog"))) -> Star
A57: Sterling Life & Health | B57: =AVERAGEIF('Quarterly Performance'!BM$3:BM$1146, 1, 'Quarterly Performance'!C$3:C$1146) -> 2.5466925e+08 | C57: =AVERAGEIF('Quarterly Performance'!$BM$3:$BM$1146, 1, 'Quarterly Performance'!D$3:D$1146) -> 53936974 | D57: =AVERAGEIF('Quarterly Performance'!$BM$3:$BM$1146, 1, 'Quarterly Performance'!E$3:E$1146) -> 2.0073228e+08 | E57: =AVERAGEIF('Quarterly Performance'!$BM$3:$BM$1146, 1, 'Quarterly Performance'!F$3:F$1146) -> 55.553725 | F57: =AVERAGEIF('Quarterly Performance'!$BM$3:$BM$1146, 1, 'Quarterly Performance'!G$3:G$1146) -> 28.538383 | G57: =AVERAGEIF('Quarterly Performance'!$BM$3:$BM$1146, 1, 'Quarterly Performance'!H$3:H$1146) -> 92.842561 | H57: =AVERAGEIF('Quarterly Performance'!$BM$3:$BM$1146, 1, 'Quarterly Performance'!I$3:I$1146) -> 55.409932 | I57: =IF(E57 <Percentiles!$E$3, "Low", IF(E57 <= Percentiles!$E$4, "Medium", "High")) -> Low | J57: =IF(B57 <Percentiles!B$3, "Low", IF(B57 <= Percentiles!B$4, "Medium", "High")) -> High | K57: =IF(C57 <Percentiles!C$3, "Low", IF(C57 <= Percentiles!C$4, "Medium", "High")) -> Medium | L57: =IF(D57 <Percentiles!D$3, "Low", IF(D57 <= Percentiles!D$4, "Medium", "High")) -> Medium | M57: =IF(H57 <Percentiles!$H$3, "Low", IF(H57 <= Percentiles!$H$4, "Medium", "High")) -> High | N57: =(F57 - AVERAGE(F$2:$F$70)) / _xlfn.STDEV.S(F$2:F$70) -> -0.63255702 | O57: =(G57 - AVERAGE($G$2:G$70)) / _xlfn.STDEV.S(G$2:G$70) -> -0.25637917 | P57: =IF(AND(N57>=0, O57>=0), "Star", IF(AND(N57>=0, O57<0), "Cash Cow", IF(AND(N57<0, O57>=0), "Question Mark", "Dog"))) -> Dog
A58: Sterling Trust & Deposits | B58: =AVERAGEIF('Quarterly Performance'!BN$3:BN$1146, 1, 'Quarterly Performance'!C$3:C$1146) -> 2.5016449e+08 | C58: =AVERAGEIF('Quarterly Performance'!$BN$3:$BN$1146, 1, 'Quarterly Performance'!D$3:D$1146) -> 49820163 | D58: =AVERAGEIF('Quarterly Performance'!$BN$3:$BN$1146, 1, 'Quarterly Performance'!E$3:E$1146) -> 2.0034433e+08 | E58: =AVERAGEIF('Quarterly Performance'!$BN$3:$BN$1146, 1, 'Quarterly Performance'!F$3:F$1146) -> 63.65932 | F58: =AVERAGEIF('Quarterly Performance'!$BN$3:$BN$1146, 1, 'Quarterly Performance'!G$3:G$1146) -> 39.788826 | G58: =AVERAGEIF('Quarterly Performance'!$BN$3:$BN$1146, 1, 'Quarterly Performance'!H$3:H$1146) -> 118.3333 | H58: =AVERAGEIF('Quarterly Performance'!$BN$3:$BN$1146, 1, 'Quarterly Performance'!I$3:I$1146) -> 49.674747 | I58: =IF(E58 <Percentiles!$E$3, "Low", IF(E58 <= Percentiles!$E$4, "Medium", "High")) -> Medium | J58: =IF(B58 <Percentiles!B$3, "Low", IF(B58 <= Percentiles!B$4, "Medium", "High")) -> Medium | K58: =IF(C58 <Percentiles!C$3, "Low", IF(C58 <= Percentiles!C$4, "Medium", "High")) -> Medium | L58: =IF(D58 <Percentiles!D$3, "Low", IF(D58 <= Percentiles!D$4, "Medium", "High")) -> Medium | M58: =IF(H58 <Percentiles!$H$3, "Low", IF(H58 <= Percentiles!$H$4, "Medium", "High")) -> Medium | N58: =(F58 - AVERAGE(F$2:$F$70)) / _xlfn.STDEV.S(F$2:F$70) -> 1.3197182 | O58: =(G58 - AVERAGE($G$2:G$70)) / _xlfn.STDEV.S(G$2:G$70) -> 0.19361948 | P58: =IF(AND(N58>=0, O58>=0), "Star", IF(AND(N58>=0, O58<0), "Cash Cow", IF(AND(N58<0, O58>=0), "Question Mark", "Dog"))) -> Star
A59: Summit Savings & Loan | B59: =AVERAGEIF('Quarterly Performance'!BO$3:BO$1146, 1, 'Quarterly Performance'!C$3:C$1146) -> 2.5045939e+08 | C59: =AVERAGEIF('Quarterly Performance'!$BO$3:$BO$1146, 1, 'Quarterly Performance'!D$3:D$1146) -> 50632479 | D59: =AVERAGEIF('Quarterly Performance'!$BO$3:$BO$1146, 1, 'Quarterly Performance'!E$3:E$1146) -> 1.9982691e+08 | E59: =AVERAGEIF('Quarterly Performance'!$BO$3:$BO$1146, 1, 'Quarterly Performance'!F$3:F$1146) -> 70.709931 | F59: =AVERAGEIF('Quarterly Performance'!$BO$3:$BO$1146, 1, 'Quarterly Performance'!G$3:G$1146) -> 27.596108 | G59: =AVERAGEIF('Quarterly Performance'!$BO$3:$BO$1146, 1, 'Quarterly Performance'!H$3:H$1146) -> 34.645379 | H59: =AVERAGEIF('Quarterly Performance'!$BO$3:$BO$1146, 1, 'Quarterly Performance'!I$3:I$1146) -> 53.159396 | I59: =IF(E59 <Percentiles!$E$3, "Low", IF(E59 <= Percentiles!$E$4, "Medium", "High")) -> High | J59: =IF(B59 <Percentiles!B$3, "Low", IF(B59 <= Percentiles!B$4, "Medium", "High")) -> Medium | K59: =IF(C59 <Percentiles!C$3, "Low", IF(C59 <= Percentiles!C$4, "Medium", "High")) -> Medium | L59: =IF(D59 <Percentiles!D$3, "Low", IF(D59 <= Percentiles!D$4, "Medium", "High")) -> Medium | M59: =IF(H59 <Percentiles!$H$3, "Low", IF(H59 <= Percentiles!$H$4, "Medium", "High")) -> High | N59: =(F59 - AVERAGE(F$2:$F$70)) / _xlfn.STDEV.S(F$2:F$70) -> -0.79606889 | O59: =(G59 - AVERAGE($G$2:G$70)) / _xlfn.STDEV.S(G$2:G$70) -> -1.2837584 | P59: =IF(AND(N59>=0, O59>=0), "Star", IF(AND(N59>=0, O59<0), "Cash Cow", IF(AND(N59<0, O59>=0), "Question Mark", "Dog"))) -> Dog
A60: SummitStone Digital Wallets | B60: =AVERAGEIF('Quarterly Performance'!BP$3:BP$1146, 1, 'Quarterly Performance'!C$3:C$1146) -> 2.46296e+08 | C60: =AVERAGEIF('Quarterly Performance'!$BP$3:$BP$1146, 1, 'Quarterly Performance'!D$3:D$1146) -> 65433851 | D60: =AVERAGEIF('Quarterly Performance'!$BP$3:$BP$1146, 1, 'Quarterly Performance'!E$3:E$1146) -> 1.8086215e+08 | E60: =AVERAGEIF('Quarterly Performance'!$BP$3:$BP$1146, 1, 'Quarterly Performance'!F$3:F$1146) -> 59.419613 | F60: =AVERAGEIF('Quarterly Performance'!$BP$3:$BP$1146, 1, 'Quarterly Performance'!G$3:G$1146) -> 42.385302 | G60: =AVERAGEIF('Quarterly Performance'!$BP$3:$BP$1146, 1, 'Quarterly Performance'!H$3:H$1146) -> 106.32492 | H60: =AVERAGEIF('Quarterly Performance'!$BP$3:$BP$1146, 1, 'Quarterly Performance'!I$3:I$1146) -> 50.871496 | I60: =IF(E60 <Percentiles!$E$3, "Low", IF(E60 <= Percentiles!$E$4, "Medium", "High")) -> Medium | J60: =IF(B60 <Percentiles!B$3, "Low", IF(B60 <= Percentiles!B$4, "Medium", "High")) -> Low | K60: =IF(C60 <Percentiles!C$3, "Low", IF(C60 <= Percentiles!C$4, "Medium", "High")) -> High | L60: =IF(D60 <Percentiles!D$3, "Low", IF(D60 <= Percentiles!D$4, "Medium", "High")) -> Low | M60: =IF(H60 <Percentiles!$H$3, "Low", IF(H60 <= Percentiles!$H$4, "Medium", "High")) -> Medium | N60: =(F60 - AVERAGE(F$2:$F$70)) / _xlfn.STDEV.S(F$2:F$70) -> 1.7702815 | O60: =(G60 - AVERAGE($G$2:G$70)) / _xlfn.STDEV.S(G$2:G$70) -> -0.018369509 | P60: =IF(AND(N60>=0, O60>=0), "Star", IF(AND(N60>=0, O60<0), "Cash Cow", IF(AND(N60<0, O60>=0), "Question Mark", "Dog"))) -> Cash Cow
A61: SummitStone Investments | B61: =AVERAGEIF('Quarterly Performance'!BQ$3:BQ$1146, 1, 'Quarterly Performance'!C$3:C$1146) -> 2.5332668e+08 | C61: =AVERAGEIF('Quarterly Performance'!$BQ$3:$BQ$1146, 1, 'Quarterly Performance'!D$3:D$1146) -> 61963912 | D61: =AVERAGEIF('Quarterly Performance'!$BQ$3:$BQ$1146, 1, 'Quarterly Performance'!E$3:E$1146) -> 1.9136277e+08 | E61: =AVERAGEIF('Quarterly Performance'!$BQ$3:$BQ$1146, 1, 'Quarterly Performance'!F$3:F$1146) -> 58.459452 | F61: =AVERAGEIF('Quarterly Performance'!$BQ$3:$BQ$1146, 1, 'Quarterly Performance'!G$3:G$1146) -> 31.51444 | G61: =AVERAGEIF('Quarterly Performance'!$BQ$3:$BQ$1146, 1, 'Quarterly Performance'!H$3:H$1146) -> 40.577698 | H61: =AVERAGEIF('Quarterly Performance'!$BQ$3:$BQ$1146, 1, 'Quarterly Performance'!I$3:I$1146) -> 51.494896 | I61: =IF(E61 <Percentiles!$E$3, "Low", IF(E61 <= Percentiles!$E$4, "Medium", "High")) -> Medium | J61: =IF(B61 <Percentiles!B$3, "Low", IF(B61 <= Percentiles!B$4, "Medium", "High")) -> High | K61: =IF(C61 <Percentiles!C$3, "Low", IF(C61 <= Percentiles!C$4, "Medium", "High")) -> High | L61: =IF(D61 <Percentiles!D$3, "Low", IF(D61 <= Percentiles!D$4, "Medium", "High")) -> Low | M61: =IF(H61 <Percentiles!$H$3, "Low", IF(H61 <= Percentiles!$H$4, "Medium", "High")) -> Medium | N61: =(F61 - AVERAGE(F$2:$F$70)) / _xlfn.STDEV.S(F$2:F$70) -> -0.11612553 | O61: =(G61 - AVERAGE($G$2:G$70)) / _xlfn.STDEV.S(G$2:G$70) -> -1.1790327 | P61: =IF(AND(N61>=0, O61>=0), "Star", IF(AND(N61>=0, O61<0), "Cash Cow", IF(AND(N61<0, O61>=0), "Question Mark", "Dog"))) -> Dog
A62: SummitStone Risk Advisors | B62: =AVERAGEIF('Quarterly Performance'!BR$3:BR$1146, 1, 'Quarterly Performance'!C$3:C$1146) -> 2.6063287e+08 | C62: =AVERAGEIF('Quarterly Performance'!$BR$3:$BR$1146, 1, 'Quarterly Performance'!D$3:D$1146) -> 53178426 | D62: =AVERAGEIF('Quarterly Performance'!$BR$3:$BR$1146, 1, 'Quarterly Performance'!E$3:E$1146) -> 2.0745444e+08 | E62: =AVERAGEIF('Quarterly Performance'!$BR$3:$BR$1146, 1, 'Quarterly Performance'!F$3:F$1146) -> 62.876299 | F62: =AVERAGEIF('Quarterly Performance'!$BR$3:$BR$1146, 1, 'Quarterly Performance'!G$3:G$1146) -> 33.865561 | G62: =AVERAGEIF('Quarterly Performance'!$BR$3:$BR$1146, 1, 'Quarterly Performance'!H$3:H$1146) -> 183.32661 | H62: =AVERAGEIF('Quarterly Performance'!$BR$3:$BR$1146, 1, 'Quarterly Performance'!I$3:I$1146) -> 50.536352 | I62: =IF(E62 <Percentiles!$E$3, "Low", IF(E62 <= Percentiles!$E$4, "Medium", "High")) -> Medium | J62: =IF(B62 <Percentiles!B$3, "Low", IF(B62 <= Percentiles!B$4, "Medium", "High")) -> High | K62: =IF(C62 <Percentiles!C$3, "Low", IF(C62 <= Percentiles!C$4, "Medium", "High")) -> Medium | L62: =IF(D62 <Percentiles!D$3, "Low", IF(D62 <= Percentiles!D$4, "Medium", "High")) -> High | M62: =IF(H62 <Percentiles!$H$3, "Low", IF(H62 <= Percentiles!$H$4, "Medium", "High")) -> Medium | N62: =(F62 - AVERAGE(F$2:$F$70)) / _xlfn.STDEV.S(F$2:F$70) -> 0.29186145 | O62: =(G62 - AVERAGE($G$2:G$70)) / _xlfn.STDEV.S(G$2:G$70) -> 1.3409735 | P62: =IF(AND(N62>=0, O62>=0), "Star", IF(AND(N62>=0, O62<0), "Cash Cow", IF(AND(N62<0, O62>=0), "Question Mark", "Dog"))) -> Star
A63: SwiftPay | B63: =AVERAGEIF('Quarterly Performance'!BS$3:BS$1146, 1, 'Quarterly Performance'!C$3:C$1146) -> 2.5688362e+08 | C63: =AVERAGEIF('Quarterly Performance'!$BS$3:$BS$1146, 1, 'Quarterly Performance'!D$3:D$1146) -> 68821288 | D63: =AVERAGEIF('Quarterly Performance'!$BS$3:$BS$1146, 1, 'Quarterly Performance'!E$3:E$1146) -> 1.8806233e+08 | E63: =AVERAGEIF('Quarterly Performance'!$BS$3:$BS$1146, 1, 'Quarterly Performance'!F$3:F$1146) -> 63.173185 | F63: =AVERAGEIF('Quarterly Performance'!$BS$3:$BS$1146, 1, 'Quarterly Performance'!G$3:G$1146) -> 27.463282 | G63: =AVERAGEIF('Quarterly Performance'!$BS$3:$BS$1146, 1, 'Quarterly Performance'!H$3:H$1146) -> 60.570167 | H63: =AVERAGEIF('Quarterly Performance'!$BS$3:$BS$1146, 1, 'Quarterly Performance'!I$3:I$1146) -> 53.994789 | I63: =IF(E63 <Percentiles!$E$3, "Low", IF(E63 <= Percentiles!$E$4, "Medium", "High")) -> Medium | J63: =IF(B63 <Percentiles!B$3, "Low", IF(B63 <= Percentiles!B$4, "Medium", "High")) -> High | K63: =IF(C63 <Percentiles!C$3, "Low", IF(C63 <= Percentiles!C$4, "Medium", "High")) -> High | L63: =IF(D63 <Percentiles!D$3, "Low", IF(D63 <= Percentiles!D$4, "Medium", "High")) -> Low | M63: =IF(H63 <Percentiles!$H$3, "Low", IF(H63 <= Percentiles!$H$4, "Medium", "High")) -> High | N63: =(F63 - AVERAGE(F$2:$F$70)) / _xlfn.STDEV.S(F$2:F$70) -> -0.819118 | O63: =(G63 - AVERAGE($G$2:G$70)) / _xlfn.STDEV.S(G$2:G$70) -> -0.82609724 | P63: =IF(AND(N63>=0, O63>=0), "Star", IF(AND(N63>=0, O63<0), "Cash Cow", IF(AND(N63<0, O63>=0), "Question Mark", "Dog"))) -> Dog
A64: SwiftPay Solutions | B64: =AVERAGEIF('Quarterly Performance'!BT$3:BT$1146, 1, 'Quarterly Performance'!C$3:C$1146) -> 2.5248322e+08 | C64: =AVERAGEIF('Quarterly Performance'!$BT$3:$BT$1146, 1, 'Quarterly Performance'!D$3:D$1146) -> 35639790 | D64: =AVERAGEIF('Quarterly Performance'!$BT$3:$BT$1146, 1, 'Quarterly Performance'!E$3:E$1146) -> 2.1684343e+08 | E64: =AVERAGEIF('Quarterly Performance'!$BT$3:$BT$1146, 1, 'Quarterly Performance'!F$3:F$1146) -> 54.545214 | F64: =AVERAGEIF('Quarterly Performance'!$BT$3:$BT$1146, 1, 'Quarterly Performance'!G$3:G$1146) -> 27.69162 | G64: =AVERAGEIF('Quarterly Performance'!$BT$3:$BT$1146, 1, 'Quarterly Performance'!H$3:H$1146) -> 161.89622 | H64: =AVERAGEIF('Quarterly Performance'!$BT$3:$BT$1146, 1, 'Quarterly Performance'!I$3:I$1146) -> 49.180387 | I64: =IF(E64 <Percentiles!$E$3, "Low", IF(E64 <= Percentiles!$E$4, "Medium", "High")) -> Low | J64: =IF(B64 <Percentiles!B$3, "Low", IF(B64 <= Percentiles!B$4, "Medium", "High")) -> High | K64: =IF(C64 <Percentiles!C$3, "Low", IF(C64 <= Percentiles!C$4, "Medium", "High")) -> Low | L64: =IF(D64 <Percentiles!D$3, "Low", IF(D64 <= Percentiles!D$4, "Medium", "High")) -> High | M64: =IF(H64 <Percentiles!$H$3, "Low", IF(H64 <= Percentiles!$H$4, "Medium", "High")) -> Medium | N64: =(F64 - AVERAGE(F$2:$F$70)) / _xlfn.STDEV.S(F$2:F$70) -> -0.77949479 | O64: =(G64 - AVERAGE($G$2:G$70)) / _xlfn.STDEV.S(G$2:G$70) -> 0.96265405 | P64: =IF(AND(N64>=0, O64>=0), "Star", IF(AND(N64>=0, O64<0), "Cash Cow", IF(AND(N64<0, O64>=0), "Question Mark", "Dog"))) -> Question Mark
A65: Titan Global Investments | B65: =AVERAGEIF('Quarterly Performance'!BU$3:BU$1146, 1, 'Quarterly Performance'!C$3:C$1146) -> 2.4436412e+08 | C65: =AVERAGEIF('Quarterly Performance'!$BU$3:$BU$1146, 1, 'Quarterly Performance'!D$3:D$1146) -> 45804070 | D65: =AVERAGEIF('Quarterly Performance'!$BU$3:$BU$1146, 1, 'Quarterly Performance'!E$3:E$1146) -> 1.9856005e+08 | E65: =AVERAGEIF('Quarterly Performance'!$BU$3:$BU$1146, 1, 'Quarterly Performance'!F$3:F$1146) -> 70.4662 | F65: =AVERAGEIF('Quarterly Performance'!$BU$3:$BU$1146, 1, 'Quarterly Performance'!G$3:G$1146) -> 28.197064 | G65: =AVERAGEIF('Quarterly Performance'!$BU$3:$BU$1146, 1, 'Quarterly Performance'!H$3:H$1146) -> 19.62763 | H65: =AVERAGEIF('Quarterly Performance'!$BU$3:$BU$1146, 1, 'Quarterly Performance'!I$3:I$1146) -> 54.000896 | I65: =IF(E65 <Percentiles!$E$3, "Low", IF(E65 <= Percentiles!$E$4, "Medium", "High")) -> High | J65: =IF(B65 <Percentiles!B$3, "Low", IF(B65 <= Percentiles!B$4, "Medium", "High")) -> Low | K65: =IF(C65 <Percentiles!C$3, "Low", IF(C65 <= Percentiles!C$4, "Medium", "High")) -> Medium | L65: =IF(D65 <Percentiles!D$3, "Low", IF(D65 <= Percentiles!D$4, "Medium", "High")) -> Medium | M65: =IF(H65 <Percentiles!$H$3, "Low", IF(H65 <= Percentiles!$H$4, "Medium", "High")) -> High | N65: =(F65 - AVERAGE(F$2:$F$70)) / _xlfn.STDEV.S(F$2:F$70) -> -0.69178562 | O65: =(G65 - AVERAGE($G$2:G$70)) / _xlfn.STDEV.S(G$2:G$70) -> -1.548873 | P65: =IF(AND(N65>=0, O65>=0), "Star", IF(AND(N65>=0, O65<0), "Cash Cow", IF(AND(N65<0, O65>=0), "Question Mark", "Dog"))) -> Dog
A66: Titan Global Invsts. | B66: =AVERAGEIF('Quarterly Performance'!BV$3:BV$1146, 1, 'Quarterly Performance'!C$3:C$1146) -> 2.4054043e+08 | C66: =AVERAGEIF('Quarterly Performance'!$BV$3:$BV$1146, 1, 'Quarterly Performance'!D$3:D$1146) -> 39209427 | D66: =AVERAGEIF('Quarterly Performance'!$BV$3:$BV$1146, 1, 'Quarterly Performance'!E$3:E$1146) -> 2.01331e+08 | E66: =AVERAGEIF('Quarterly Performance'!$BV$3:$BV$1146, 1, 'Quarterly Performance'!F$3:F$1146) -> 46.559051 | F66: =AVERAGEIF('Quarterly Performance'!$BV$3:$BV$1146, 1, 'Quarterly Performance'!G$3:G$1146) -> 34.420694 | G66: =AVERAGEIF('Quarterly Performance'!$BV$3:$BV$1146, 1, 'Quarterly Performance'!H$3:H$1146) -> 3.1808837 | H66: =AVERAGEIF('Quarterly Performance'!$BV$3:$BV$1146, 1, 'Quarterly Performance'!I$3:I$1146) -> 51.118977 | I66: =IF(E66 <Percentiles!$E$3, "Low", IF(E66 <= Percentiles!$E$4, "Medium", "High")) -> Low | J66: =IF(B66 <Percentiles!B$3, "Low", IF(B66 <= Percentiles!B$4, "Medium", "High")) -> Low | K66: =IF(C66 <Percentiles!C$3, "Low", IF(C66 <= Percentiles!C$4, "Medium", "High")) -> Low | L66: =IF(D66 <Percentiles!D$3, "Low", IF(D66 <= Percentiles!D$4, "Medium", "High")) -> Medium | M66: =IF(H66 <Percentiles!$H$3, "Low", IF(H66 <= Percentiles!$H$4, "Medium", "High")) -> Medium | N66: =(F66 - AVERAGE(F$2:$F$70)) / _xlfn.STDEV.S(F$2:F$70) -> 0.38819306 | O66: =(G66 - AVERAGE($G$2:G$70)) / _xlfn.STDEV.S(G$2:G$70) -> -1.8392143 | P66: =IF(AND(N66>=0, O66>=0), "Star", IF(AND(N66>=0, O66<0), "Cash Cow", IF(AND(N66<0, O66>=0), "Question Mark", "Dog"))) -> Cash Cow
A67: Titan Reinsurance Corp. | B67: =AVERAGEIF('Quarterly Performance'!BW$3:BW$1146, 1, 'Quarterly Performance'!C$3:C$1146) -> 2.492105e+08 | C67: =AVERAGEIF('Quarterly Performance'!$BW$3:$BW$1146, 1, 'Quarterly Performance'!D$3:D$1146) -> 58040252 | D67: =AVERAGEIF('Quarterly Performance'!$BW$3:$BW$1146, 1, 'Quarterly Performance'!E$3:E$1146) -> 1.9117025e+08 | E67: =AVERAGEIF('Quarterly Performance'!$BW$3:$BW$1146, 1, 'Quarterly Performance'!F$3:F$1146) -> 59.472671 | F67: =AVERAGEIF('Quarterly Performance'!$BW$3:$BW$1146, 1, 'Quarterly Performance'!G$3:G$1146) -> 39.22014 | G67: =AVERAGEIF('Quarterly Performance'!$BW$3:$BW$1146, 1, 'Quarterly Performance'!H$3:H$1146) -> 155.73995 | H67: =AVERAGEIF('Quarterly Performance'!$BW$3:$BW$1146, 1, 'Quarterly Performance'!I$3:I$1146) -> 52.637678 | I67: =IF(E67 <Percentiles!$E$3, "Low", IF(E67 <= Percentiles!$E$4, "Medium", "High")) -> Medium | J67: =IF(B67 <Percentiles!B$3, "Low", IF(B67 <= Percentiles!B$4, "Medium", "High")) -> Medium | K67: =IF(C67 <Percentiles!C$3, "Low", IF(C67 <= Percentiles!C$4, "Medium", "High")) -> High | L67: =IF(D67 <Percentiles!D$3, "Low", IF(D67 <= Percentiles!D$4, "Medium", "High")) -> Low | M67: =IF(H67 <Percentiles!$H$3, "Low", IF(H67 <= Percentiles!$H$4, "Medium", "High")) -> High | N67: =(F67 - AVERAGE(F$2:$F$70)) / _xlfn.STDEV.S(F$2:F$70) -> 1.2210349 | O67: =(G67 - AVERAGE($G$2:G$70)) / _xlfn.STDEV.S(G$2:G$70) -> 0.85397485 | P67: =IF(AND(N67>=0, O67>=0), "Star", IF(AND(N67>=0, O67<0), "Cash Cow", IF(AND(N67<0, O67>=0), "Question Mark", "Dog"))) -> Star
A68: TitanPay Innovations | B68: =AVERAGEIF('Quarterly Performance'!BX$3:BX$1146, 1, 'Quarterly Performance'!C$3:C$1146) -> 2.4988368e+08 | C68: =AVERAGEIF('Quarterly Performance'!$BX$3:$BX$1146, 1, 'Quarterly Performance'!D$3:D$1146) -> 50481749 | D68: =AVERAGEIF('Quarterly Performance'!$BX$3:$BX$1146, 1, 'Quarterly Performance'!E$3:E$1146) -> 1.9940193e+08 | E68: =AVERAGEIF('Quarterly Performance'!$BX$3:$BX$1146, 1, 'Quarterly Performance'!F$3:F$1146) -> 80.337794 | F68: =AVERAGEIF('Quarterly Performance'!$BX$3:$BX$1146, 1, 'Quarterly Performance'!G$3:G$1146) -> 29.648899 | G68: =AVERAGEIF('Quarterly Performance'!$BX$3:$BX$1146, 1, 'Quarterly Performance'!H$3:H$1146) -> 149.97852 | H68: =AVERAGEIF('Quarterly Performance'!$BX$3:$BX$1146, 1, 'Quarterly Performance'!I$3:I$1146) -> 51.361446 | I68: =IF(E68 <Percentiles!$E$3, "Low", IF(E68 <= Percentiles!$E$4, "Medium", "High")) -> High | J68: =IF(B68 <Percentiles!B$3, "Low", IF(B68 <= Percentiles!B$4, "Medium", "High")) -> Medium | K68: =IF(C68 <Percentiles!C$3, "Low", IF(C68 <= Percentiles!C$4, "Medium", "High")) -> Medium | L68: =IF(D68 <Percentiles!D$3, "Low", IF(D68 <= Percentiles!D$4, "Medium", "High")) -> Medium | M68: =IF(H68 <Percentiles!$H$3, "Low", IF(H68 <= Percentiles!$H$4, "Medium", "High")) -> Medium | N68: =(F68 - AVERAGE(F$2:$F$70)) / _xlfn.STDEV.S(F$2:F$70) -> -0.43985059 | O68: =(G68 - AVERAGE($G$2:G$70)) / _xlfn.STDEV.S(G$2:G$70) -> 0.75226581 | P68: =IF(AND(N68>=0, O68>=0), "Star", IF(AND(N68>=0, O68<0), "Cash Cow", IF(AND(N68<0, O68>=0), "Question Mark", "Dog"))) -> Question Mark
A69: Unity Federal Credit Union | B69: =AVERAGEIF('Quarterly Performance'!BY$3:BY$1146, 1, 'Quarterly Performance'!C$3:C$1146) -> 2.4419729e+08 | C69: =AVERAGEIF('Quarterly Performance'!$BY$3:$BY$1146, 1, 'Quarterly Performance'!D$3:D$1146) -> 49786098 | D69: =AVERAGEIF('Quarterly Performance'!$BY$3:$BY$1146, 1, 'Quarterly Performance'!E$3:E$1146) -> 1.9441119e+08 | E69: =AVERAGEIF('Quarterly Performance'!$BY$3:$BY$1146, 1, 'Quarterly Performance'!F$3:F$1146) -> 44.069251 | F69: =AVERAGEIF('Quarterly Performance'!$BY$3:$BY$1146, 1, 'Quarterly Performance'!G$3:G$1146) -> 33.726894 | G69: =AVERAGEIF('Quarterly Performance'!$BY$3:$BY$1146, 1, 'Quarterly Performance'!H$3:H$1146) -> 182.70831 | H69: =AVERAGEIF('Quarterly Performance'!$BY$3:$BY$1146, 1, 'Quarterly Performance'!I$3:I$1146) -> 50.703507 | I69: =IF(E69 <Percentiles!$E$3, "Low", IF(E69 <= Percentiles!$E$4, "Medium", "High")) -> Low | J69: =IF(B69 <Percentiles!B$3, "Low", IF(B69 <= Percentiles!B$4, "Medium", "High")) -> Low | K69: =IF(C69 <Percentiles!C$3, "Low", IF(C69 <= Percentiles!C$4, "Medium", "High")) -> Medium | L69: =IF(D69 <Percentiles!D$3, "Low", IF(D69 <= Percentiles!D$4, "Medium", "High")) -> Low | M69: =IF(H69 <Percentiles!$H$3, "Low", IF(H69 <= Percentiles!$H$4, "Medium", "High")) -> Medium | N69: =(F69 - AVERAGE(F$2:$F$70)) / _xlfn.STDEV.S(F$2:F$70) -> 0.26779868 | O69: =(G69 - AVERAGE($G$2:G$70)) / _xlfn.STDEV.S(G$2:G$70) -> 1.3300585 | P69: =IF(AND(N69>=0, O69>=0), "Star", IF(AND(N69>=0, O69<0), "Cash Cow", IF(AND(N69<0, O69>=0), "Question Mark", "Dog"))) -> Star
A70: Vanguard Wealth Strategies | B70: =AVERAGEIF('Quarterly Performance'!BZ$3:BZ$1146, 1, 'Quarterly Performance'!C$3:C$1146) -> 2.5246225e+08 | C70: =AVERAGEIF('Quarterly Performance'!$BZ$3:$BZ$1146, 1, 'Quarterly Performance'!D$3:D$1146) -> 47160183 | D70: =AVERAGEIF('Quarterly Performance'!$BZ$3:$BZ$1146, 1, 'Quarterly Performance'!E$3:E$1146) -> 2.0530206e+08 | E70: =AVERAGEIF('Quarterly Performance'!$BZ$3:$BZ$1146, 1, 'Quarterly Performance'!F$3:F$1146) -> 68.629005 | F70: =AVERAGEIF('Quarterly Performance'!$BZ$3:$BZ$1146, 1, 'Quarterly Performance'!G$3:G$1146) -> 30.985824 | G70: =AVERAGEIF('Quarterly Performance'!$BZ$3:$BZ$1146, 1, 'Quarterly Performance'!H$3:H$1146) -> 98.667658 | H70: =AVERAGEIF('Quarterly Performance'!$BZ$3:$BZ$1146, 1, 'Quarterly Performance'!I$3:I$1146) -> 47.737752 | I70: =IF(E70 <Percentiles!$E$3, "Low", IF(E70 <= Percentiles!$E$4, "Medium", "High")) -> High | J70: =IF(B70 <Percentiles!B$3, "Low", IF(B70 <= Percentiles!B$4, "Medium", "High")) -> Medium | K70: =IF(C70 <Percentiles!C$3, "Low", IF(C70 <= Percentiles!C$4, "Medium", "High")) -> Medium | L70: =IF(D70 <Percentiles!D$3, "Low", IF(D70 <= Percentiles!D$4, "Medium", "High")) -> Medium | M70: =IF(H70 <Percentiles!$H$3, "Low", IF(H70 <= Percentiles!$H$4, "Medium", "High")) -> Low | N70: =(F70 - AVERAGE(F$2:$F$70)) / _xlfn.STDEV.S(F$2:F$70) -> -0.20785573 | O70: =(G70 - AVERAGE($G$2:G$70)) / _xlfn.STDEV.S(G$2:G$70) -> -0.15354628 | P70: =IF(AND(N70>=0, O70>=0), "Star", IF(AND(N70>=0, O70<0), "Cash Cow", IF(AND(N70<0, O70>=0), "Question Mark", "Dog"))) -> Dog

Sheet Percentiles
A1: Company | B1: Average of Revenue | C1: Average of Profits | D1: Average of Costs | E1: Average of Customer Satisfaction Score | F1: Average of Market Share | G1: Average of Growth Potential | H1: Average of Stock Price
A3: Q1 | B3: =_xlfn.PERCENTILE.INC('Average Annual Performance'!B2:B70, 0.25) -> 2.4630056e+08 | C3: =_xlfn.PERCENTILE.INC('Average Annual Performance'!C2:C70, 0.25) -> 41734835 | D3: =_xlfn.PERCENTILE.INC('Average Annual Performance'!D2:D70, 0.25) -> 1.9496143e+08 | E3: =_xlfn.PERCENTILE.INC('Average Annual Performance'!E2:E70, 0.25) -> 55.870587 | F3: =_xlfn.PERCENTILE.INC('Average Annual Performance'!F2:F70, 0.25) -> 27.628856 | G3: =_xlfn.PERCENTILE.INC('Average Annual Performance'!G2:G70, 0.25) -> 75.866695 | H3: =_xlfn.PERCENTILE.INC('Average Annual Performance'!H2:H70, 0.25) -> 48.104894
A4: Q3 | B4: =_xlfn.PERCENTILE.INC('Average Annual Performance'!B2:B70, 0.75) -> 2.5246225e+08 | C4: =_xlfn.PERCENTILE.INC('Average Annual Performance'!C2:C70, 0.75) -> 53989856 | D4: =_xlfn.PERCENTILE.INC('Average Annual Performance'!D2:D70, 0.75) -> 2.0684406e+08 | E4: =_xlfn.PERCENTILE.INC('Average Annual Performance'!E2:E70, 0.75) -> 64.456824 | F4: =_xlfn.PERCENTILE.INC('Average Annual Performance'!F2:F70, 0.75) -> 36.779897 | G4: =_xlfn.PERCENTILE.INC('Average Annual Performance'!G2:G70, 0.75) -> 145.36089 | H4: =_xlfn.PERCENTILE.INC('Average Annual Performance'!H2:H70, 0.75) -> 52.469127
